Workbook

Sheet DASHBOARD

Sheet DUES CONTRIBUTIONS

Sheet LEVY CONTRIBUTIONS

Sheet ACCOUNTS

Sheet TREASURER BILL

Sheet TRADING ACCOUNT

Sheet PERSONAL PROFILE

Sheet RECORDS

Sheet YEARLY DUES FEES
B2: YEARLY DUES FEES
B3: NO. | C3: ELDER | D3: TOTAL | E3: 2023 | F3: 2024 | G3: 2025 | H3: 2026 | I3: 2027 | J3: 2028 | K3: 2029 | L3: 2030 | M3: 2031 | N3: 2032
D4: DUES | E4: ¢ | F4: ¢ | G4: ¢ | H4: ¢ | I4: ¢ | J4: ¢ | K4: ¢ | L4: ¢ | M4: ¢
B5: 1 | C5: Alex Ackah | D5: =SUM(E5:N5) -> 3300 | F5: 900 | G5: 1200 | H5: 1200
B6: 2 | C6: Danso Kingsley | D6: =SUM(E6:N6) -> 2400 | G6: 1200 | H6: 1200
B7: 3 | C7: Fanuel Hagan | D7: =SUM(E7:N7) -> 3900 | E7: 600 | F7: 900 | G7: 1200 | H7: 1200
B8: 4 | C8: Frederick Wortey Tawiah | D8: =SUM(E8:N8) -> 3900 | E8: 600 | F8: 900 | G8: 1200 | H8: 1200
B9: 5 | C9: George Yeboah | D9: =SUM(E9:N9) -> 2400 | G9: 1200 | H9: 1200
B10: 6 | C10: Isaac Darko | D10: =SUM(E10:N10) -> 3900 | E10: 600 | F10: 900 | G10: 1200 | H10: 1200
B11: 7 | C11: Isaac Donkor | D11: =SUM(E11:N11) -> 3300 | F11: 900 | G11: 1200 | H11: 1200
B12: 8 | C12: John Aidoo | D12: =SUM(E12:N12) -> 1200 | H12: 1200
B13: 9 | C13: John Darbo | D13: =SUM(E13:N13) -> 2400 | G13: 1200 | H13: 1200
B14: 10 | C14: John Ofosuhene Asare | D14: =SUM(E14:N14) -> 3900 | E14: 600 | F14: 900 | G14: 1200 | H14: 1200
B15: 11 | C15: Johnson Wood | D15: =SUM(E15:N15) -> 3900 | E15: 600 | F15: 900 | G15: 1200 | H15: 1200
B16: 12 | C16: Jonas Wereko | D16: =SUM(E16:N16) -> 3900 | E16: 600 | F16: 900 | G16: 1200 | H16: 1200
B17: 13 | C17: Jonathan Danso Siaw | D17: =SUM(E17:N17) -> 3900 | E17: 600 | F17: 900 | G17: 1200 | H17: 1200
B18: 14 | C18: Joseph Kofi Amanfo | D18: =SUM(E18:N18) -> 3900 | E18: 600 | F18: 900 | G18: 1200 | H18: 1200
B19: 15 | C19: Justice Kojo Acheampong | D19: =SUM(E19:N19) -> 3900 | E19: 600 | F19: 900 | G19: 1200 | H19: 1200
B20: 16 | C20: Just-Mark Kwabena Quansah | D20: =SUM(E20:N20) -> 3900 | E20: 600 | F20: 900 | G20: 1200 | H20: 1200
B21: 17 | C21: Maxwell Ofei Siaw | D21: =SUM(E21:N21) -> 3900 | E21: 600 | F21: 900 | G21: 1200 | H21: 1200
B22: 18 | C22: Moses Oduro | D22: =SUM(E22:N22) -> 3900 | E22: 600 | F22: 900 | G22: 1200 | H22: 1200
B23: 19 | C23: Osei Kwame | D23: =SUM(E23:N23) -> 3900 | E23: 600 | F23: 900 | G23: 1200 | H23: 1200
B24: 20 | C24: Peter Kingsford Nkrumah | D24: =SUM(E24:N24) -> 3900 | E24: 600 | F24: 900 | G24: 1200 | H24: 1200
B25: 21 | C25: Prince Asante Ahwireng | D25: =SUM(E25:N25) -> 3900 | E25: 600 | F25: 900 | G25: 1200 | H25: 1200
... B28: 24 | C28: William Kojo Anane | D28: =SUM(E28:N28) -> 3900 | E28: 600 | F28: 900 | G28: 1200 | H28: 1200
B30: TOTAL | D30: =SUBTOTAL(9,D5:D28) -> 85200 | E30: =SUBTOTAL(9,E5:E28) -> 10800 | F30: =SUBTOTAL(9,F5:F28) -> 18000 | G30: =SUBTOTAL(9,G5:G28) -> 27600 | H30: =SUBTOTAL(9,H5:H28) -> 28800 | I30: =SUBTOTAL(9,I5:I28) -> 0 | J30: =SUBTOTAL(9,J5:J28) -> 0 | K30: =SUBTOTAL(9,K5:K28) -> 0 | ... N30: =SUBTOTAL(9,N5:N28) -> 0
B31: COUNT | D31: =COUNTIF(D5:D29,">0") -> 24 | E31: =COUNTIF(E5:E29,">0") -> 18 | F31: =COUNTIF(F5:F29,">0") -> 20 | G31: =COUNTIF(G5:G29,">0") -> 23 | H31: =COUNTIF(H5:H29,">0") -> 24 | I31: =COUNTIF(I5:I29,">0") -> 0 | J31: =COUNTIF(J5:J29,">0") -> 0 | K31: =COUNTIF(K5:K29,">0") -> 0 | ... N31: =COUNTIF(N5:N29,">0") -> 0

Sheet YEARLY DUES
B2: YEARLY DUES
B3: NO. | C3: ELDER | D3: TOTAL | E3: 2023 | F3: 2024 | G3: 2025 | H3: 2026 | I3: 2027 | J3: 2028 | K3: 2029 | L3: 2030 | M3: 2031 | N3: 2032
D4: DUES | E4: ¢ | F4: ¢ | G4: ¢ | H4: ¢ | I4: ¢ | J4: ¢ | K4: ¢ | L4: ¢ | M4: ¢
B5: 1 | C5: Alex Ackah | D5: =SUM(E5:N5) -> 3000 | E5: =IFERROR(VLOOKUP($C5,'MONTHLY DUES 2023'!$C$5:$D$25,2,0),0) -> 0 | F5: =IFERROR(VLOOKUP($C5,'MONTHLY DUES 2024'!$C$5:$D$25,2,0),0) -> 900 | G5: =IFERROR(VLOOKUP($C5,'MONTHLY DUES 2025'!$C$5:$D$25,2,0),0) -> 1200 | H5: =IFERROR(VLOOKUP($C5,'MONTHLY DUES 2026'!$C$5:$D$26,2,0),0) -> 900 | I5: =IFERROR(VLOOKUP($C5,'MONTHLY DUES 2027'!$C$5:$D$27,2,0),0) -> 0 | J5: =IFERROR(VLOOKUP($C5,'MONTHLY DUES 2028'!$C$5:$D$27,2,0),0) -> 0 | K5: =IFERROR(VLOOKUP($C5,'MONTHLY DUES 2029'!$C$5:$D$27,2,0),0) -> 0 | L5: =IFERROR(VLOOKUP($C5,'MONTHLY DUES 2030'!$C$5:$D$27,2,0),0) -> 0 | M5: =IFERROR(VLOOKUP($C5,'MONTHLY DUES 2031'!$C$5:$D$27,2,0),0) -> 0 | N5: =IFERROR(VLOOKUP($C5,'MONTHLY DUES 2032'!$C$5:$D$27,2,0),0) -> 0
B6: 2 | C6: Danso Kingsley | D6: =SUM(E6:N6) -> 1500 | E6: =IFERROR(VLOOKUP($C6,'MONTHLY DUES 2023'!$C$5:$D$25,2,0),0) -> 0 | F6: =IFERROR(VLOOKUP($C6,'MONTHLY DUES 2024'!$C$5:$D$25,2,0),0) -> 0 | G6: =IFERROR(VLOOKUP($C6,'MONTHLY DUES 2025'!$C$5:$D$25,2,0),0) -> 1200 | H6: =IFERROR(VLOOKUP($C6,'MONTHLY DUES 2026'!$C$5:$D$26,2,0),0) -> 300 | I6: =IFERROR(VLOOKUP($C6,'MONTHLY DUES 2027'!$C$5:$D$27,2,0),0) -> 0 | J6: =IFERROR(VLOOKUP($C6,'MONTHLY DUES 2028'!$C$5:$D$27,2,0),0) -> 0 | K6: =IFERROR(VLOOKUP($C6,'MONTHLY DUES 2029'!$C$5:$D$27,2,0),0) -> 0 | L6: =IFERROR(VLOOKUP($C6,'MONTHLY DUES 2030'!$C$5:$D$27,2,0),0) -> 0 | M6: =IFERROR(VLOOKUP($C6,'MONTHLY DUES 2031'!$C$5:$D$27,2,0),0) -> 0 | N6: =IFERROR(VLOOKUP($C6,'MONTHLY DUES 2032'!$C$5:$D$27,2,0),0) -> 0
B7: 3 | C7: Fanuel Hagan | D7: =SUM(E7:N7) -> 3400 | E7: =IFERROR(VLOOKUP($C7,'MONTHLY DUES 2023'!$C$5:$D$25,2,0),0) -> 600 | F7: =IFERROR(VLOOKUP($C7,'MONTHLY DUES 2024'!$C$5:$D$25,2,0),0) -> 900 | G7: =IFERROR(VLOOKUP($C7,'MONTHLY DUES 2025'!$C$5:$D$25,2,0),0) -> 1200 | H7: =IFERROR(VLOOKUP($C7,'MONTHLY DUES 2026'!$C$5:$D$26,2,0),0) -> 700 | I7: =IFERROR(VLOOKUP($C7,'MONTHLY DUES 2027'!$C$5:$D$27,2,0),0) -> 0 | J7: =IFERROR(VLOOKUP($C7,'MONTHLY DUES 2028'!$C$5:$D$27,2,0),0) -> 0 | K7: =IFERROR(VLOOKUP($C7,'MONTHLY DUES 2029'!$C$5:$D$27,2,0),0) -> 0 | L7: =IFERROR(VLOOKUP($C7,'MONTHLY DUES 2030'!$C$5:$D$27,2,0),0) -> 0 | M7: =IFERROR(VLOOKUP($C7,'MONTHLY DUES 2031'!$C$5:$D$27,2,0),0) -> 0 | N7: =IFERROR(VLOOKUP($C7,'MONTHLY DUES 2032'!$C$5:$D$27,2,0),0) -> 0
B8: 4 | C8: Frederick Wortey Tawiah | D8: =SUM(E8:N8) -> 3400 | E8: =IFERROR(VLOOKUP($C8,'MONTHLY DUES 2023'!$C$5:$D$25,2,0),0) -> 600 | F8: =IFERROR(VLOOKUP($C8,'MONTHLY DUES 2024'!$C$5:$D$25,2,0),0) -> 900 | G8: =IFERROR(VLOOKUP($C8,'MONTHLY DUES 2025'!$C$5:$D$25,2,0),0) -> 1200 | H8: =IFERROR(VLOOKUP($C8,'MONTHLY DUES 2026'!$C$5:$D$26,2,0),0) -> 700 | I8: =IFERROR(VLOOKUP($C8,'MONTHLY DUES 2027'!$C$5:$D$27,2,0),0) -> 0 | J8: =IFERROR(VLOOKUP($C8,'MONTHLY DUES 2028'!$C$5:$D$27,2,0),0) -> 0 | K8: =IFERROR(VLOOKUP($C8,'MONTHLY DUES 2029'!$C$5:$D$27,2,0),0) -> 0 | L8: =IFERROR(VLOOKUP($C8,'MONTHLY DUES 2030'!$C$5:$D$27,2,0),0) -> 0 | M8: =IFERROR(VLOOKUP($C8,'MONTHLY DUES 2031'!$C$5:$D$27,2,0),0) -> 0 | N8: =IFERROR(VLOOKUP($C8,'MONTHLY DUES 2032'!$C$5:$D$27,2,0),0) -> 0
B9: 5 | C9: George Yeboah | D9: =SUM(E9:N9) -> 200 | E9: =IFERROR(VLOOKUP($C9,'MONTHLY DUES 2023'!$C$5:$D$25,2,0),0) -> 0 | F9: =IFERROR(VLOOKUP($C9,'MONTHLY DUES 2024'!$C$5:$D$25,2,0),0) -> 0 | G9: =IFERROR(VLOOKUP($C9,'MONTHLY DUES 2025'!$C$5:$D$25,2,0),0) -> 200 | H9: =IFERROR(VLOOKUP($C9,'MONTHLY DUES 2026'!$C$5:$D$26,2,0),0) -> 0 | I9: =IFERROR(VLOOKUP($C9,'MONTHLY DUES 2027'!$C$5:$D$27,2,0),0) -> 0 | J9: =IFERROR(VLOOKUP($C9,'MONTHLY DUES 2028'!$C$5:$D$27,2,0),0) -> 0 | K9: =IFERROR(VLOOKUP($C9,'MONTHLY DUES 2029'!$C$5:$D$27,2,0),0) -> 0 | L9: =IFERROR(VLOOKUP($C9,'MONTHLY DUES 2030'!$C$5:$D$27,2,0),0) -> 0 | M9: =IFERROR(VLOOKUP($C9,'MONTHLY DUES 2031'!$C$5:$D$27,2,0),0) -> 0 | N9: =IFERROR(VLOOKUP($C9,'MONTHLY DUES 2032'!$C$5:$D$27,2,0),0) -> 0
B10: 6 | C10: Isaac Darko | D10: =SUM(E10:N10) -> 3900 | E10: =IFERROR(VLOOKUP($C10,'MONTHLY DUES 2023'!$C$5:$D$25,2,0),0) -> 600 | F10: =IFERROR(VLOOKUP($C10,'MONTHLY DUES 2024'!$C$5:$D$25,2,0),0) -> 900 | G10: =IFERROR(VLOOKUP($C10,'MONTHLY DUES 2025'!$C$5:$D$25,2,0),0) -> 1200 | H10: =IFERROR(VLOOKUP($C10,'MONTHLY DUES 2026'!$C$5:$D$26,2,0),0) -> 1200 | I10: =IFERROR(VLOOKUP($C10,'MONTHLY DUES 2027'!$C$5:$D$27,2,0),0) -> 0 | J10: =IFERROR(VLOOKUP($C10,'MONTHLY DUES 2028'!$C$5:$D$27,2,0),0) -> 0 | K10: =IFERROR(VLOOKUP($C10,'MONTHLY DUES 2029'!$C$5:$D$27,2,0),0) -> 0 | L10: =IFERROR(VLOOKUP($C10,'MONTHLY DUES 2030'!$C$5:$D$27,2,0),0) -> 0 | M10: =IFERROR(VLOOKUP($C10,'MONTHLY DUES 2031'!$C$5:$D$27,2,0),0) -> 0 | N10: =IFERROR(VLOOKUP($C10,'MONTHLY DUES 2032'!$C$5:$D$27,2,0),0) -> 0
B11: 7 | C11: Isaac Donkor | D11: =SUM(E11:N11) -> 3300 | E11: =IFERROR(VLOOKUP($C11,'MONTHLY DUES 2023'!$C$5:$D$25,2,0),0) -> 0 | F11: =IFERROR(VLOOKUP($C11,'MONTHLY DUES 2024'!$C$5:$D$25,2,0),0) -> 900 | G11: =IFERROR(VLOOKUP($C11,'MONTHLY DUES 2025'!$C$5:$D$25,2,0),0) -> 1200 | H11: =IFERROR(VLOOKUP($C11,'MONTHLY DUES 2026'!$C$5:$D$26,2,0),0) -> 1200
B12: 55 | C12: John Aidoo | D12: =SUM(E12:N12) -> 900 | E12: =IFERROR(VLOOKUP($C12,'MONTHLY DUES 2023'!$C$5:$D$25,2,0),0) -> 0 | F12: =IFERROR(VLOOKUP($C12,'MONTHLY DUES 2024'!$C$5:$D$25,2,0),0) -> 0 | G12: =IFERROR(VLOOKUP($C12,'MONTHLY DUES 2025'!$C$5:$D$25,2,0),0) -> 0 | H12: =IFERROR(VLOOKUP($C12,'MONTHLY DUES 2026'!$C$5:$D$26,2,0),0) -> 900
B13: 8 | C13: John Darbo | D13: =SUM(E13:N13) -> 350 | E13: =IFERROR(VLOOKUP($C13,'MONTHLY DUES 2023'!$C$5:$D$25,2,0),0) -> 0 | F13: =IFERROR(VLOOKUP($C13,'MONTHLY DUES 2024'!$C$5:$D$25,2,0),0) -> 0 | G13: =IFERROR(VLOOKUP($C13,'MONTHLY DUES 2025'!$C$5:$D$25,2,0),0) -> 350 | H13: =IFERROR(VLOOKUP($C13,'MONTHLY DUES 2026'!$C$5:$D$26,2,0),0) -> 0 | I13: =IFERROR(VLOOKUP($C13,'MONTHLY DUES 2027'!$C$5:$D$27,2,0),0) -> 0 | J13: =IFERROR(VLOOKUP($C13,'MONTHLY DUES 2028'!$C$5:$D$27,2,0),0) -> 0 | K13: =IFERROR(VLOOKUP($C13,'MONTHLY DUES 2029'!$C$5:$D$27,2,0),0) -> 0 | L13: =IFERROR(VLOOKUP($C13,'MONTHLY DUES 2030'!$C$5:$D$27,2,0),0) -> 0 | M13: =IFERROR(VLOOKUP($C13,'MONTHLY DUES 2031'!$C$5:$D$27,2,0),0) -> 0 | N13: =IFERROR(VLOOKUP($C13,'MONTHLY DUES 2032'!$C$5:$D$27,2,0),0) -> 0
B14: 9 | C14: John Ofosuhene Asare | D14: =SUM(E14:N14) -> 3400 | E14: =IFERROR(VLOOKUP($C14,'MONTHLY DUES 2023'!$C$5:$D$25,2,0),0) -> 600 | F14: =IFERROR(VLOOKUP($C14,'MONTHLY DUES 2024'!$C$5:$D$25,2,0),0) -> 900 | G14: =IFERROR(VLOOKUP($C14,'MONTHLY DUES 2025'!$C$5:$D$25,2,0),0) -> 1200 | H14: =IFERROR(VLOOKUP($C14,'MONTHLY DUES 2026'!$C$5:$D$26,2,0),0) -> 700 | I14: =IFERROR(VLOOKUP($C14,'MONTHLY DUES 2027'!$C$5:$D$27,2,0),0) -> 0 | J14: =IFERROR(VLOOKUP($C14,'MONTHLY DUES 2028'!$C$5:$D$27,2,0),0) -> 0 | K14: =IFERROR(VLOOKUP($C14,'MONTHLY DUES 2029'!$C$5:$D$27,2,0),0) -> 0 | L14: =IFERROR(VLOOKUP($C14,'MONTHLY DUES 2030'!$C$5:$D$27,2,0),0) -> 0 | M14: =IFERROR(VLOOKUP($C14,'MONTHLY DUES 2031'!$C$5:$D$27,2,0),0) -> 0 | N14: =IFERROR(VLOOKUP($C14,'MONTHLY DUES 2032'!$C$5:$D$27,2,0),0) -> 0
B15: 10 | C15: Johnson Wood | D15: =SUM(E15:N15) -> 3500 | E15: =IFERROR(VLOOKUP($C15,'MONTHLY DUES 2023'!$C$5:$D$25,2,0),0) -> 600 | F15: =IFERROR(VLOOKUP($C15,'MONTHLY DUES 2024'!$C$5:$D$25,2,0),0) -> 900 | G15: =IFERROR(VLOOKUP($C15,'MONTHLY DUES 2025'!$C$5:$D$25,2,0),0) -> 1200 | H15: =IFERROR(VLOOKUP($C15,'MONTHLY DUES 2026'!$C$5:$D$26,2,0),0) -> 800 | I15: =IFERROR(VLOOKUP($C15,'MONTHLY DUES 2027'!$C$5:$D$27,2,0),0) -> 0 | J15: =IFERROR(VLOOKUP($C15,'MONTHLY DUES 2028'!$C$5:$D$27,2,0),0) -> 0 | K15: =IFERROR(VLOOKUP($C15,'MONTHLY DUES 2029'!$C$5:$D$27,2,0),0) -> 0 | L15: =IFERROR(VLOOKUP($C15,'MONTHLY DUES 2030'!$C$5:$D$27,2,0),0) -> 0 | M15: =IFERROR(VLOOKUP($C15,'MONTHLY DUES 2031'!$C$5:$D$27,2,0),0) -> 0 | N15: =IFERROR(VLOOKUP($C15,'MONTHLY DUES 2032'!$C$5:$D$27,2,0),0) -> 0
B16: 11 | C16: Jonas Wereko | D16: =SUM(E16:N16) -> 3600 | E16: =IFERROR(VLOOKUP($C16,'MONTHLY DUES 2023'!$C$5:$D$25,2,0),0) -> 600 | F16: =IFERROR(VLOOKUP($C16,'MONTHLY DUES 2024'!$C$5:$D$25,2,0),0) -> 900 | G16: =IFERROR(VLOOKUP($C16,'MONTHLY DUES 2025'!$C$5:$D$25,2,0),0) -> 1200 | H16: =IFERROR(VLOOKUP($C16,'MONTHLY DUES 2026'!$C$5:$D$26,2,0),0) -> 900 | I16: =IFERROR(VLOOKUP($C16,'MONTHLY DUES 2027'!$C$5:$D$27,2,0),0) -> 0 | J16: =IFERROR(VLOOKUP($C16,'MONTHLY DUES 2028'!$C$5:$D$27,2,0),0) -> 0 | K16: =IFERROR(VLOOKUP($C16,'MONTHLY DUES 2029'!$C$5:$D$27,2,0),0) -> 0 | L16: =IFERROR(VLOOKUP($C16,'MONTHLY DUES 2030'!$C$5:$D$27,2,0),0) -> 0 | M16: =IFERROR(VLOOKUP($C16,'MONTHLY DUES 2031'!$C$5:$D$27,2,0),0) -> 0 | N16: =IFERROR(VLOOKUP($C16,'MONTHLY DUES 2032'!$C$5:$D$27,2,0),0) -> 0
B17: 12 | C17: Jonathan Danso Siaw | D17: =SUM(E17:N17) -> 3900 | E17: =IFERROR(VLOOKUP($C17,'MONTHLY DUES 2023'!$C$5:$D$25,2,0),0) -> 600 | F17: =IFERROR(VLOOKUP($C17,'MONTHLY DUES 2024'!$C$5:$D$25,2,0),0) -> 900 | G17: =IFERROR(VLOOKUP($C17,'MONTHLY DUES 2025'!$C$5:$D$25,2,0),0) -> 1200 | H17: =IFERROR(VLOOKUP($C17,'MONTHLY DUES 2026'!$C$5:$D$26,2,0),0) -> 1200 | I17: =IFERROR(VLOOKUP($C17,'MONTHLY DUES 2027'!$C$5:$D$27,2,0),0) -> 0 | J17: =IFERROR(VLOOKUP($C17,'MONTHLY DUES 2028'!$C$5:$D$27,2,0),0) -> 0 | K17: =IFERROR(VLOOKUP($C17,'MONTHLY DUES 2029'!$C$5:$D$27,2,0),0) -> 0 | L17: =IFERROR(VLOOKUP($C17,'MONTHLY DUES 2030'!$C$5:$D$27,2,0),0) -> 0 | M17: =IFERROR(VLOOKUP($C17,'MONTHLY DUES 2031'!$C$5:$D$27,2,0),0) -> 0 | N17: =IFERROR(VLOOKUP($C17,'MONTHLY DUES 2032'!$C$5:$D$27,2,0),0) -> 0
B18: 13 | C18: Joseph Kofi Amanfo | D18: =SUM(E18:N18) -> 1000 | E18: =IFERROR(VLOOKUP($C18,'MONTHLY DUES 2023'!$C$5:$D$25,2,0),0) -> 600 | F18: =IFERROR(VLOOKUP($C18,'MONTHLY DUES 2024'!$C$5:$D$25,2,0),0) -> 400 | G18: =IFERROR(VLOOKUP($C18,'MONTHLY DUES 2025'!$C$5:$D$25,2,0),0) -> 0 | H18: =IFERROR(VLOOKUP($C18,'MONTHLY DUES 2026'!$C$5:$D$26,2,0),0) -> 0 | I18: =IFERROR(VLOOKUP($C18,'MONTHLY DUES 2027'!$C$5:$D$27,2,0),0) -> 0 | J18: =IFERROR(VLOOKUP($C18,'MONTHLY DUES 2028'!$C$5:$D$27,2,0),0) -> 0 | K18: =IFERROR(VLOOKUP($C18,'MONTHLY DUES 2029'!$C$5:$D$27,2,0),0) -> 0 | L18: =IFERROR(VLOOKUP($C18,'MONTHLY DUES 2030'!$C$5:$D$27,2,0),0) -> 0 | M18: =IFERROR(VLOOKUP($C18,'MONTHLY DUES 2031'!$C$5:$D$27,2,0),0) -> 0 | N18: =IFERROR(VLOOKUP($C18,'MONTHLY DUES 2032'!$C$5:$D$27,2,0),0) -> 0
B19: 14 | C19: Justice Kojo Acheampong | D19: =SUM(E19:N19) -> 3000 | E19: =IFERROR(VLOOKUP($C19,'MONTHLY DUES 2023'!$C$5:$D$25,2,0),0) -> 600 | F19: =IFERROR(VLOOKUP($C19,'MONTHLY DUES 2024'!$C$5:$D$25,2,0),0) -> 900 | G19: =IFERROR(VLOOKUP($C19,'MONTHLY DUES 2025'!$C$5:$D$25,2,0),0) -> 1200 | H19: =IFERROR(VLOOKUP($C19,'MONTHLY DUES 2026'!$C$5:$D$26,2,0),0) -> 300 | I19: =IFERROR(VLOOKUP($C19,'MONTHLY DUES 2027'!$C$5:$D$27,2,0),0) -> 0 | J19: =IFERROR(VLOOKUP($C19,'MONTHLY DUES 2028'!$C$5:$D$27,2,0),0) -> 0 | K19: =IFERROR(VLOOKUP($C19,'MONTHLY DUES 2029'!$C$5:$D$27,2,0),0) -> 0 | L19: =IFERROR(VLOOKUP($C19,'MONTHLY DUES 2030'!$C$5:$D$27,2,0),0) -> 0 | M19: =IFERROR(VLOOKUP($C19,'MONTHLY DUES 2031'!$C$5:$D$27,2,0),0) -> 0 | N19: =IFERROR(VLOOKUP($C19,'MONTHLY DUES 2032'!$C$5:$D$27,2,0),0) -> 0
B20: 15 | C20: Just-Mark Kwabena Quansah | D20: =SUM(E20:N20) -> 3000 | E20: =IFERROR(VLOOKUP($C20,'MONTHLY DUES 2023'!$C$5:$D$25,2,0),0) -> 600 | F20: =IFERROR(VLOOKUP($C20,'MONTHLY DUES 2024'!$C$5:$D$25,2,0),0) -> 900 | G20: =IFERROR(VLOOKUP($C20,'MONTHLY DUES 2025'!$C$5:$D$25,2,0),0) -> 1200 | H20: =IFERROR(VLOOKUP($C20,'MONTHLY DUES 2026'!$C$5:$D$26,2,0),0) -> 300 | I20: =IFERROR(VLOOKUP($C20,'MONTHLY DUES 2027'!$C$5:$D$27,2,0),0) -> 0 | J20: =IFERROR(VLOOKUP($C20,'MONTHLY DUES 2028'!$C$5:$D$27,2,0),0) -> 0 | K20: =IFERROR(VLOOKUP($C20,'MONTHLY DUES 2029'!$C$5:$D$27,2,0),0) -> 0 | L20: =IFERROR(VLOOKUP($C20,'MONTHLY DUES 2030'!$C$5:$D$27,2,0),0) -> 0 | M20: =IFERROR(VLOOKUP($C20,'MONTHLY DUES 2031'!$C$5:$D$27,2,0),0) -> 0 | N20: =IFERROR(VLOOKUP($C20,'MONTHLY DUES 2032'!$C$5:$D$27,2,0),0) -> 0
B21: 16 | C21: Maxwell Ofei Siaw | D21: =SUM(E21:N21) -> 3700 | E21: =IFERROR(VLOOKUP($C21,'MONTHLY DUES 2023'!$C$5:$D$25,2,0),0) -> 600 | F21: =IFERROR(VLOOKUP($C21,'MONTHLY DUES 2024'!$C$5:$D$25,2,0),0) -> 900 | G21: =IFERROR(VLOOKUP($C21,'MONTHLY DUES 2025'!$C$5:$D$25,2,0),0) -> 1200 | H21: =IFERROR(VLOOKUP($C21,'MONTHLY DUES 2026'!$C$5:$D$26,2,0),0) -> 1000 | I21: =IFERROR(VLOOKUP($C21,'MONTHLY DUES 2027'!$C$5:$D$27,2,0),0) -> 0 | J21: =IFERROR(VLOOKUP($C21,'MONTHLY DUES 2028'!$C$5:$D$27,2,0),0) -> 0 | K21: =IFERROR(VLOOKUP($C21,'MONTHLY DUES 2029'!$C$5:$D$27,2,0),0) -> 0 | L21: =IFERROR(VLOOKUP($C21,'MONTHLY DUES 2030'!$C$5:$D$27,2,0),0) -> 0 | M21: =IFERROR(VLOOKUP($C21,'MONTHLY DUES 2031'!$C$5:$D$27,2,0),0) -> 0 | N21: =IFERROR(VLOOKUP($C21,'MONTHLY DUES 2032'!$C$5:$D$27,2,0),0) -> 0
B22: 17 | C22: Moses Oduro | D22: =SUM(E22:N22) -> 3900 | E22: =IFERROR(VLOOKUP($C22,'MONTHLY DUES 2023'!$C$5:$D$25,2,0),0) -> 600 | F22: =IFERROR(VLOOKUP($C22,'MONTHLY DUES 2024'!$C$5:$D$25,2,0),0) -> 900 | G22: =IFERROR(VLOOKUP($C22,'MONTHLY DUES 2025'!$C$5:$D$25,2,0),0) -> 1200 | H22: =IFERROR(VLOOKUP($C22,'MONTHLY DUES 2026'!$C$5:$D$26,2,0),0) -> 1200 | I22: =IFERROR(VLOOKUP($C22,'MONTHLY DUES 2027'!$C$5:$D$27,2,0),0) -> 0 | J22: =IFERROR(VLOOKUP($C22,'MONTHLY DUES 2028'!$C$5:$D$27,2,0),0) -> 0 | K22: =IFERROR(VLOOKUP($C22,'MONTHLY DUES 2029'!$C$5:$D$27,2,0),0) -> 0 | L22: =IFERROR(VLOOKUP($C22,'MONTHLY DUES 2030'!$C$5:$D$27,2,0),0) -> 0 | M22: =IFERROR(VLOOKUP($C22,'MONTHLY DUES 2031'!$C$5:$D$27,2,0),0) -> 0 | N22: =IFERROR(VLOOKUP($C22,'MONTHLY DUES 2032'!$C$5:$D$27,2,0),0) -> 0
B23: 18 | C23: Osei Kwame | D23: =SUM(E23:N23) -> 3500 | E23: =IFERROR(VLOOKUP($C23,'MONTHLY DUES 2023'!$C$5:$D$25,2,0),0) -> 600 | F23: =IFERROR(VLOOKUP($C23,'MONTHLY DUES 2024'!$C$5:$D$25,2,0),0) -> 900 | G23: =IFERROR(VLOOKUP($C23,'MONTHLY DUES 2025'!$C$5:$D$25,2,0),0) -> 1200 | H23: =IFERROR(VLOOKUP($C23,'MONTHLY DUES 2026'!$C$5:$D$26,2,0),0) -> 800 | I23: =IFERROR(VLOOKUP($C23,'MONTHLY DUES 2027'!$C$5:$D$27,2,0),0) -> 0 | J23: =IFERROR(VLOOKUP($C23,'MONTHLY DUES 2028'!$C$5:$D$27,2,0),0) -> 0 | K23: =IFERROR(VLOOKUP($C23,'MONTHLY DUES 2029'!$C$5:$D$27,2,0),0) -> 0 | L23: =IFERROR(VLOOKUP($C23,'MONTHLY DUES 2030'!$C$5:$D$27,2,0),0) -> 0 | M23: =IFERROR(VLOOKUP($C23,'MONTHLY DUES 2031'!$C$5:$D$27,2,0),0) -> 0 | N23: =IFERROR(VLOOKUP($C23,'MONTHLY DUES 2032'!$C$5:$D$27,2,0),0) -> 0
B24: 19 | C24: Peter Kingsford Nkrumah | D24: =SUM(E24:N24) -> 900 | E24: =IFERROR(VLOOKUP($C24,'MONTHLY DUES 2023'!$C$5:$D$25,2,0),0) -> 600 | F24: =IFERROR(VLOOKUP($C24,'MONTHLY DUES 2024'!$C$5:$D$25,2,0),0) -> 300 | G24: =IFERROR(VLOOKUP($C24,'MONTHLY DUES 2025'!$C$5:$D$25,2,0),0) -> 0 | H24: =IFERROR(VLOOKUP($C24,'MONTHLY DUES 2026'!$C$5:$D$26,2,0),0) -> 0 | I24: =IFERROR(VLOOKUP($C24,'MONTHLY DUES 2027'!$C$5:$D$27,2,0),0) -> 0 | J24: =IFERROR(VLOOKUP($C24,'MONTHLY DUES 2028'!$C$5:$D$27,2,0),0) -> 0 | K24: =IFERROR(VLOOKUP($C24,'MONTHLY DUES 2029'!$C$5:$D$27,2,0),0) -> 0 | L24: =IFERROR(VLOOKUP($C24,'MONTHLY DUES 2030'!$C$5:$D$27,2,0),0) -> 0 | M24: =IFERROR(VLOOKUP($C24,'MONTHLY DUES 2031'!$C$5:$D$27,2,0),0) -> 0 | N24: =IFERROR(VLOOKUP($C24,'MONTHLY DUES 2032'!$C$5:$D$27,2,0),0) -> 0
... B28: 23 | C28: William Kojo Anane | D28: =SUM(E28:N28) -> 3900 | E28: =IFERROR(VLOOKUP($C28,'MONTHLY DUES 2023'!$C$5:$D$25,2,0),0) -> 600 | F28: =IFERROR(VLOOKUP($C28,'MONTHLY DUES 2024'!$C$5:$D$25,2,0),0) -> 900 | G28: =IFERROR(VLOOKUP($C28,'MONTHLY DUES 2025'!$C$5:$D$25,2,0),0) -> 1200 | H28: =IFERROR(VLOOKUP($C28,'MONTHLY DUES 2026'!$C$5:$D$26,2,0),0) -> 1200 | I28: =IFERROR(VLOOKUP($C28,'MONTHLY DUES 2027'!$C$5:$D$27,2,0),0) -> 0 | J28: =IFERROR(VLOOKUP($C28,'MONTHLY DUES 2028'!$C$5:$D$27,2,0),0) -> 0 | K28: =IFERROR(VLOOKUP($C28,'MONTHLY DUES 2029'!$C$5:$D$27,2,0),0) -> 0 | L28: =IFERROR(VLOOKUP($C28,'MONTHLY DUES 2030'!$C$5:$D$27,2,0),0) -> 0 | M28: =IFERROR(VLOOKUP($C28,'MONTHLY DUES 2031'!$C$5:$D$27,2,0),0) -> 0 | N28: =IFERROR(VLOOKUP($C28,'MONTHLY DUES 2032'!$C$5:$D$27,2,0),0) -> 0
B30: TOTAL | D30: =SUBTOTAL(9,D5:D28) -> 65950 | E30: =SUBTOTAL(9,E5:E28) -> 10800 | F30: =SUBTOTAL(9,F5:F28) -> 16900 | G30: =SUBTOTAL(9,G5:G28) -> 22350 | H30: =SUBTOTAL(9,H5:H28) -> 15900 | I30: =SUBTOTAL(9,I5:I28) -> 0 | J30: =SUBTOTAL(9,J5:J28) -> 0 | K30: =SUBTOTAL(9,K5:K28) -> 0 | ... N30: =SUBTOTAL(9,N5:N28) -> 0
B31: COUNT | D31: =COUNTIF(D5:D29,">0") -> 24 | E31: =COUNTIF(E5:E29,">0") -> 18 | F31: =COUNTIF(F5:F29,">0") -> 20 | G31: =COUNTIF(G5:G29,">0") -> 21 | H31: =COUNTIF(H5:H29,">0") -> 19 | I31: =COUNTIF(I5:I29,">0") -> 0 | J31: =COUNTIF(J5:J29,">0") -> 0 | K31: =COUNTIF(K5:K29,">0") -> 0 | ... N31: =COUNTIF(N5:N29,">0") -> 0

Sheet MONTHLY DUES 2023
B2: MONTHLY DUES - 2023
B3: NO. | C3: ELDER | D3: TOTAL | E3: SHARES | F3: 44927 | G3: 44958 | H3: 44986 | I3: 45017 | J3: 45047 | K3: 45078 | L3: 45108 | M3: 45139 | N3: 45170 | O3: 45200 | P3: 45231 | Q3: 45261
D4: DUES | E4: 50 | F4: ¢ | G4: ¢ | H4: ¢ | I4: ¢ | J4: ¢ | K4: ¢ | L4: ¢ | M4: ¢ | N4: ¢ | O4: ¢ | Q4: ¢
B5: 1 | C5: Fanuel Hagan | D5: =SUM(F5:Q5) -> 600 | E5: =D5/$E$4 -> 12 | F5: 50 | G5: 50 | H5: 50 | I5: 50 | J5: 50 | K5: 50 | L5: 50 | M5: 50 | N5: 50 | O5: 50 | P5: 50 | Q5: 50
B6: 2 | C6: Frederick Wortey Tawiah | D6: =SUM(F6:Q6) -> 600 | E6: =D6/$E$4 -> 12 | F6: 50 | G6: 50 | H6: 50 | I6: 50 | J6: 50 | K6: 50 | L6: 50 | M6: 50 | N6: 50 | O6: 50 | P6: 50 | Q6: 50
B7: 3 | C7: Isaac Darko | D7: =SUM(F7:Q7) -> 600 | E7: =D7/$E$4 -> 12 | F7: 50 | G7: 50 | H7: 50 | I7: 50 | J7: 50 | K7: 50 | L7: 50 | M7: 50 | N7: 50 | O7: 50 | P7: 50 | Q7: 50
B8: 4 | C8: John Ofosuhene Asare | D8: =SUM(F8:Q8) -> 600 | E8: =D8/$E$4 -> 12 | F8: 50 | G8: 50 | H8: 50 | I8: 50 | J8: 50 | K8: 50 | L8: 50 | M8: 50 | N8: 50 | O8: 50 | P8: 50 | Q8: 50
B9: 5 | C9: Johnson Wood | D9: =SUM(F9:Q9) -> 600 | E9: =D9/$E$4 -> 12 | F9: 50 | G9: 50 | H9: 50 | I9: 50 | J9: 50 | K9: 50 | L9: 50 | M9: 50 | N9: 50 | O9: 50 | P9: 50 | Q9: 50
B10: 6 | C10: Jonas Wereko | D10: =SUM(F10:Q10) -> 600 | E10: =D10/$E$4 -> 12 | F10: 50 | G10: 50 | H10: 50 | I10: 50 | J10: 50 | K10: 50 | L10: 50 | M10: 50 | N10: 50 | O10: 50 | P10: 50 | Q10: 50
B11: 7 | C11: Jonathan Danso Siaw | D11: =SUM(F11:Q11) -> 600 | E11: =D11/$E$4 -> 12 | F11: 50 | G11: 50 | H11: 50 | I11: 50 | J11: 50 | K11: 50 | L11: 50 | M11: 50 | N11: 50 | O11: 50 | P11: 50 | Q11: 50
B12: 8 | C12: Joseph Kofi Amanfo | D12: =SUM(F12:Q12) -> 600 | E12: =D12/$E$4 -> 12 | F12: 50 | G12: 50 | H12: 50 | I12: 50 | J12: 50 | K12: 50 | L12: 50 | M12: 50 | N12: 50 | O12: 50 | P12: 50 | Q12: 50
B13: 9 | C13: Justice Kojo Acheampong | D13: =SUM(F13:Q13) -> 600 | E13: =D13/$E$4 -> 12 | F13: 50 | G13: 50 | H13: 50 | I13: 50 | J13: 50 | K13: 50 | L13: 50 | M13: 50 | N13: 50 | O13: 50 | P13: 50 | Q13: 50
B14: 10 | C14: Just-Mark Kwabena Quansah | D14: =SUM(F14:Q14) -> 600 | E14: =D14/$E$4 -> 12 | F14: 50 | G14: 50 | H14: 50 | I14: 50 | J14: 50 | K14: 50 | L14: 50 | M14: 50 | N14: 50 | O14: 50 | P14: 50 | Q14: 50
B15: 11 | C15: Maxwell Ofei Siaw | D15: =SUM(F15:Q15) -> 600 | E15: =D15/$E$4 -> 12 | F15: 50 | G15: 50 | H15: 50 | I15: 50 | J15: 50 | K15: 50 | L15: 50 | M15: 50 | N15: 50 | O15: 50 | P15: 50 | Q15: 50
B16: 12 | C16: Moses Oduro | D16: =SUM(F16:Q16) -> 600 | E16: =D16/$E$4 -> 12 | F16: 50 | G16: 50 | H16: 50 | I16: 50 | J16: 50 | K16: 50 | L16: 50 | M16: 50 | N16: 50 | O16: 50 | P16: 50 | Q16: 50
... B22: 18 | C22: William Kojo Anane | D22: =SUM(F22:Q22) -> 600 | E22: =D22/$E$4 -> 12 | F22: 50 | G22: 50 | H22: 50 | I22: 50 | J22: 50 | K22: 50 | L22: 50 | M22: 50 | N22: 50 | O22: 50 | P22: 50 | Q22: 50
B25: TOTAL | D25: =SUBTOTAL(9,D5:D22) -> 10800 | E25: =SUBTOTAL(9,E5:E22) -> 216 | F25: =SUBTOTAL(9,F5:F22) -> 900 | G25: =SUBTOTAL(9,G5:G22) -> 900 | H25: =SUBTOTAL(9,H5:H22) -> 900 | I25: =SUBTOTAL(9,I5:I22) -> 900 | J25: =SUBTOTAL(9,J5:J22) -> 900 | K25: =SUBTOTAL(9,K5:K22) -> 900 | ... Q25: =SUBTOTAL(9,Q5:Q22) -> 900
B26: COUNT | D26: =COUNTIF(D5:D24,">0") -> 18 | E26: =COUNTIF(E5:E24,">0") -> 18 | F26: =COUNTIF(F5:F24,">0") -> 18 | G26: =COUNTIF(G5:G24,">0") -> 18 | H26: =COUNTIF(H5:H24,">0") -> 18 | I26: =COUNTIF(I5:I24,">0") -> 18 | J26: =COUNTIF(J5:J24,">0") -> 18 | K26: =COUNTIF(K5:K24,">0") -> 18 | ... Q26: =COUNTIF(Q5:Q24,">0") -> 18

Sheet MONTHLY DUES 2024
B2: MONTHLY DUES - 2024
B3: NO. | C3: ELDER | D3: TOTAL | E3: SHARES | F3: 45292 | G3: 45323 | H3: 45352 | I3: 45383 | J3: 45413 | K3: 45444 | L3: 45474 | M3: 45505 | N3: 45536 | O3: 45566 | P3: 45597 | Q3: 45627
D4: DUES | E4: 50 | F4: ¢ | G4: ¢ | H4: ¢ | I4: ¢ | J4: ¢ | K4: ¢ | L4: ¢ | M4: ¢ | N4: ¢ | O4: ¢ | Q4: ¢
B5: 1 | C5: Alex Ackah | D5: =SUM(F5:Q5) -> 900 | E5: =D5/$E$4 -> 18 | F5: 50 | G5: 50 | H5: 50 | I5: 50 | J5: 50 | K5: 50 | L5: 100 | M5: 100 | N5: 100 | O5: 100 | P5: 100 | Q5: 100
B6: 2 | C6: Fanuel Hagan | D6: =SUM(F6:Q6) -> 900 | E6: =D6/$E$4 -> 18 | F6: 50 | G6: 50 | H6: 50 | I6: 50 | J6: 50 | K6: 50 | L6: 100 | M6: 100 | N6: 100 | O6: 100 | P6: 100 | Q6: 100
B7: 3 | C7: Frederick Wortey Tawiah | D7: =SUM(F7:Q7) -> 900 | E7: =D7/$E$4 -> 18 | F7: 50 | G7: 50 | H7: 50 | I7: 50 | J7: 50 | K7: 50 | L7: 100 | M7: 100 | N7: 100 | O7: 100 | P7: 100 | Q7: 100
B8: 4 | C8: Isaac Darko | D8: =SUM(F8:Q8) -> 900 | E8: =D8/$E$4 -> 18 | F8: 50 | G8: 50 | H8: 50 | I8: 50 | J8: 50 | K8: 50 | L8: 100 | M8: 100 | N8: 100 | O8: 100 | P8: 100 | Q8: 100
B9: 5 | C9: Isaac Donkor | D9: =SUM(F9:Q9) -> 900 | E9: =D9/$E$4 -> 18 | F9: 50 | G9: 50 | H9: 50 | I9: 50 | J9: 50 | K9: 50 | L9: 100 | M9: 100 | N9: 100 | O9: 100 | P9: 100 | Q9: 100
B10: 6 | C10: John Ofosuhene Asare | D10: =SUM(F10:Q10) -> 900 | E10: =D10/$E$4 -> 18 | F10: 50 | G10: 50 | H10: 50 | I10: 50 | J10: 50 | K10: 50 | L10: 100 | M10: 100 | N10: 100 | O10: 100 | P10: 100 | Q10: 100
B11: 7 | C11: Johnson Wood | D11: =SUM(F11:Q11) -> 900 | E11: =D11/$E$4 -> 18 | F11: 50 | G11: 50 | H11: 50 | I11: 50 | J11: 50 | K11: 50 | L11: 100 | M11: 100 | N11: 100 | O11: 100 | P11: 100 | Q11: 100
B12: 8 | C12: Jonas Wereko | D12: =SUM(F12:Q12) -> 900 | E12: =D12/$E$4 -> 18 | F12: 50 | G12: 50 | H12: 50 | I12: 50 | J12: 50 | K12: 50 | L12: 100 | M12: 100 | N12: 100 | O12: 100 | P12: 100 | Q12: 100
B13: 9 | C13: Jonathan Danso Siaw | D13: =SUM(F13:Q13) -> 900 | E13: =D13/$E$4 -> 18 | F13: 50 | G13: 50 | H13: 50 | I13: 50 | J13: 50 | K13: 50 | L13: 100 | M13: 100 | N13: 100 | O13: 100 | P13: 100 | Q13: 100
B14: 10 | C14: Justice Kojo Acheampong | D14: =SUM(F14:Q14) -> 900 | E14: =D14/$E$4 -> 18 | F14: 50 | G14: 50 | H14: 50 | I14: 50 | J14: 50 | K14: 50 | L14: 100 | M14: 100 | N14: 100 | O14: 100 | P14: 100 | Q14: 100
B15: 11 | C15: Just-Mark Kwabena Quansah | D15: =SUM(F15:Q15) -> 900 | E15: =D15/$E$4 -> 18 | F15: 50 | G15: 50 | H15: 50 | I15: 50 | J15: 50 | K15: 50 | L15: 100 | M15: 100 | N15: 100 | O15: 100 | P15: 100 | Q15: 100
B16: 12 | C16: Maxwell Ofei Siaw | D16: =SUM(F16:Q16) -> 900 | E16: =D16/$E$4 -> 18 | F16: 50 | G16: 50 | H16: 50 | I16: 50 | J16: 50 | K16: 50 | L16: 100 | M16: 100 | N16: 100 | O16: 100 | P16: 100 | Q16: 100
... B22: 18 | C22: William Kojo Anane | D22: =SUM(F22:Q22) -> 900 | E22: =D22/$E$4 -> 18 | F22: 50 | G22: 50 | H22: 50 | I22: 50 | J22: 50 | K22: 50 | L22: 100 | M22: 100 | N22: 100 | O22: 100 | P22: 100 | Q22: 100
B23: 19 | C23: Joseph Kofi Amanfo | D23: =SUM(F23:Q23) -> 400 | E23: =D23/$E$4 -> 8 | F23: 50 | G23: 50 | H23: 50 | I23: 50 | J23: 50 | K23: 50 | L23: 100
B24: 20 | C24: Peter Kingsford Nkrumah | D24: =SUM(F24:Q24) -> 300 | E24: =D24/$E$4 -> 6 | F24: 50 | G24: 50 | H24: 50 | I24: 50 | J24: 50 | K24: 50
B27: TOTAL | D27: =SUBTOTAL(9,D5:D25) -> 16900 | E27: =SUBTOTAL(9,E5:E25) -> 338 | F27: =SUBTOTAL(9,F5:F25) -> 1000 | G27: =SUBTOTAL(9,G5:G25) -> 1000 | H27: =SUBTOTAL(9,H5:H25) -> 1000 | I27: =SUBTOTAL(9,I5:I25) -> 1000 | J27: =SUBTOTAL(9,J5:J25) -> 1000 | K27: =SUBTOTAL(9,K5:K25) -> 1000 | ... Q27: =SUBTOTAL(9,Q5:Q25) -> 1800
B28: COUNT | D28: =COUNT(D5:D26) -> 20 | E28: =COUNT(E5:E26) -> 20 | F28: =COUNT(F5:F26) -> 20 | G28: =COUNT(G5:G26) -> 20 | H28: =COUNT(H5:H26) -> 20 | I28: =COUNT(I5:I26) -> 20 | J28: =COUNT(J5:J26) -> 20 | K28: =COUNT(K5:K26) -> 20 | ... Q28: =COUNT(Q5:Q26) -> 18

Sheet MONTHLY DUES 2025
B2: MONTHLY DUES - 2025
B3: NO. | C3: ELDER | D3: TOTAL | E3: SHARES | F3: 45658 | G3: 45689 | H3: 45717 | I3: 45748 | J3: 45778 | K3: 45809 | L3: 45839 | M3: 45870 | N3: 45901 | O3: 45931 | P3: 45962 | Q3: 45992
D4: DUES | E4: 50 | F4: ¢ | G4: ¢ | H4: ¢ | I4: ¢ | J4: ¢ | K4: ¢ | L4: ¢ | M4: ¢ | N4: ¢ | O4: ¢ | Q4: ¢
B5: 1 | C5: Alex Ackah | D5: =SUM(F5:Q5) -> 1200 | E5: =D5/$E$4 -> 24 | F5: 100 | G5: 100 | H5: 100 | I5: 100 | J5: 100 | K5: 100 | L5: 100 | M5: 100 | N5: 100 | O5: 100 | P5: 100 | Q5: 100
B6: 2 | C6: Danso Kingsley | D6: =SUM(F6:Q6) -> 1200 | E6: =D6/$E$4 -> 24 | F6: 100 | G6: 100 | H6: 100 | I6: 100 | J6: 100 | K6: 100 | L6: 100 | M6: 100 | N6: 100 | O6: 100 | P6: 100 | Q6: 100
B7: 3 | C7: Fanuel Hagan | D7: =SUM(F7:Q7) -> 1200 | E7: =D7/$E$4 -> 24 | F7: 100 | G7: 100 | H7: 100 | I7: 100 | J7: 100 | K7: 100 | L7: 100 | M7: 100 | N7: 100 | O7: 100 | P7: 100 | Q7: 100
B8: 4 | C8: Frederick Wortey Tawiah | D8: =SUM(F8:Q8) -> 1200 | E8: =D8/$E$4 -> 24 | F8: 100 | G8: 100 | H8: 100 | I8: 100 | J8: 100 | K8: 100 | L8: 100 | M8: 100 | N8: 100 | O8: 100 | P8: 100 | Q8: 100
B9: 5 | C9: Isaac Darko | D9: =SUM(F9:Q9) -> 1200 | E9: =D9/$E$4 -> 24 | F9: 100 | G9: 100 | H9: 100 | I9: 100 | J9: 100 | K9: 100 | L9: 100 | M9: 100 | N9: 100 | O9: 100 | P9: 100 | Q9: 100
B10: 6 | C10: Isaac Donkor | D10: =SUM(F10:Q10) -> 1200 | E10: =D10/$E$4 -> 24 | F10: 100 | G10: 100 | H10: 100 | I10: 100 | J10: 100 | K10: 100 | L10: 100 | M10: 100 | N10: 100 | O10: 100 | P10: 100 | Q10: 100
B11: 7 | C11: John Ofosuhene Asare | D11: =SUM(F11:Q11) -> 1200 | E11: =D11/$E$4 -> 24 | F11: 100 | G11: 100 | H11: 100 | I11: 100 | J11: 100 | K11: 100 | L11: 100 | M11: 100 | N11: 100 | O11: 100 | P11: 100 | Q11: 100
B12: 8 | C12: Johnson Wood | D12: =SUM(F12:Q12) -> 1200 | E12: =D12/$E$4 -> 24 | F12: 100 | G12: 100 | H12: 100 | I12: 100 | J12: 100 | K12: 100 | L12: 100 | M12: 100 | N12: 100 | O12: 100 | P12: 100 | Q12: 100
B13: 9 | C13: Jonas Wereko | D13: =SUM(F13:Q13) -> 1200 | E13: =D13/$E$4 -> 24 | F13: 100 | G13: 100 | H13: 100 | I13: 100 | J13: 100 | K13: 100 | L13: 100 | M13: 100 | N13: 100 | O13: 100 | P13: 100 | Q13: 100
B14: 10 | C14: Jonathan Danso Siaw | D14: =SUM(F14:Q14) -> 1200 | E14: =D14/$E$4 -> 24 | F14: 100 | G14: 100 | H14: 100 | I14: 100 | J14: 100 | K14: 100 | L14: 100 | M14: 100 | N14: 100 | O14: 100 | P14: 100 | Q14: 100
B15: 11 | C15: Just-Mark Kwabena Quansah | D15: =SUM(F15:Q15) -> 1200 | E15: =D15/$E$4 -> 24 | F15: 100 | G15: 100 | H15: 100 | I15: 100 | J15: 100 | K15: 100 | L15: 100 | M15: 100 | N15: 100 | O15: 100 | P15: 100 | Q15: 100
B16: 12 | C16: Maxwell Ofei Siaw | D16: =SUM(F16:Q16) -> 1200 | E16: =D16/$E$4 -> 24 | F16: 100 | G16: 100 | H16: 100 | I16: 100 | J16: 100 | K16: 100 | L16: 100 | M16: 100 | N16: 100 | O16: 100 | P16: 100 | Q16: 100
... B22: 18 | C22: Justice Kojo Acheampong | D22: =SUM(F22:Q22) -> 1200 | E22: =D22/$E$4 -> 24 | F22: 100 | G22: 100 | H22: 100 | I22: 100 | J22: 100 | K22: 100 | L22: 100 | M22: 100 | N22: 100 | O22: 100 | P22: 100 | Q22: 100
B23: 19 | C23: John Darbo | D23: =SUM(F23:Q23) -> 350 | E23: =D23/$E$4 -> 7 | F23: 100 | G23: 100 | H23: 100 | I23: 50
B24: 20 | C24: George Yeboah | D24: =SUM(F24:Q24) -> 200 | E24: =D24/$E$4 -> 4 | F24: 100 | G24: 100
B25: 21 | C25: Samuel Yaw Nkansah | D25: =SUM(F25:Q25) -> 200 | E25: =D25/$E$4 -> 4 | F25: 100 | G25: 100
B28: TOTAL | D28: =SUBTOTAL(9,D5:D27) -> 22350 | E28: =SUBTOTAL(9,E5:E27) -> 447 | F28: =SUBTOTAL(9,F5:F27) -> 2100 | G28: =SUBTOTAL(9,G5:G27) -> 2100 | H28: =SUBTOTAL(9,H5:H27) -> 1900 | I28: =SUBTOTAL(9,I5:I27) -> 1850 | J28: =SUBTOTAL(9,J5:J27) -> 1800 | K28: =SUBTOTAL(9,K5:K27) -> 1800 | ... Q28: =SUBTOTAL(9,Q5:Q27) -> 1800
B29: COUNT | D29: =COUNTIF(D5:D27,">0") -> 21 | E29: =COUNTIF(E5:E27,">0") -> 21 | F29: =COUNTIF(F5:F27,">0") -> 21 | G29: =COUNTIF(G5:G27,">0") -> 21 | H29: =COUNTIF(H5:H27,">0") -> 19 | I29: =COUNTIF(I5:I27,">0") -> 19 | J29: =COUNTIF(J5:J27,">0") -> 18 | K29: =COUNTIF(K5:K27,">0") -> 18 | ... Q29: =COUNTIF(Q5:Q27,">0") -> 18

Sheet MONTHLY DUES 2026
B2: MONTHLY DUES - 2026
B3: NO. | C3: ELDER | D3: TOTAL | E3: SHARES | F3: 46023 | G3: 46054 | H3: 46082 | I3: 46113 | J3: 46143 | K3: 46174 | L3: 46204 | M3: 46235 | N3: 46266 | O3: 46296 | P3: 46327 | Q3: 46357
D4: DUES | E4: 50 | F4: ¢ | G4: ¢ | H4: ¢ | I4: ¢ | J4: ¢ | K4: ¢ | L4: ¢ | M4: ¢ | N4: ¢ | O4: ¢ | Q4: ¢
B5: 1 | C5: Isaac Darko | D5: =SUM(F5:Q5) -> 1200 | E5: =D5/$E$4 -> 24 | F5: 100 | G5: 100 | H5: 100 | I5: 100 | J5: 100 | K5: 100 | L5: 100 | M5: 100 | N5: 100 | O5: 100 | P5: 100 | Q5: 100
B6: 2 | C6: Isaac Donkor | D6: =SUM(F6:Q6) -> 1200 | E6: =D6/$E$4 -> 24 | F6: 100 | G6: 100 | H6: 100 | I6: 100 | J6: 100 | K6: 100 | L6: 100 | M6: 100 | N6: 100 | O6: 100 | P6: 100 | Q6: 100
B7: 3 | C7: Jonathan Danso Siaw | D7: =SUM(F7:Q7) -> 1200 | E7: =D7/$E$4 -> 24 | F7: 100 | G7: 100 | H7: 100 | I7: 100 | J7: 100 | K7: 100 | L7: 100 | M7: 100 | N7: 100 | O7: 100 | P7: 100 | Q7: 100
B8: 4 | C8: Moses Oduro | D8: =SUM(F8:Q8) -> 1200 | E8: =D8/$E$4 -> 24 | F8: 100 | G8: 100 | H8: 100 | I8: 100 | J8: 100 | K8: 100 | L8: 100 | M8: 100 | N8: 100 | O8: 100 | P8: 100 | Q8: 100
B9: 5 | C9: William Kojo Anane | D9: =SUM(F9:Q9) -> 1200 | E9: =D9/$E$4 -> 24 | F9: 100 | G9: 100 | H9: 100 | I9: 100 | J9: 100 | K9: 100 | L9: 100 | M9: 100 | N9: 100 | O9: 100 | P9: 100 | Q9: 100
B10: 6 | C10: Maxwell Ofei Siaw | D10: =SUM(F10:Q10) -> 1000 | E10: =D10/$E$4 -> 20 | F10: 100 | G10: 100 | H10: 100 | I10: 100 | J10: 100 | K10: 100 | L10: 100 | M10: 100 | N10: 100 | O10: 100
B11: 7 | C11: Vincent Agamatey | D11: =SUM(F11:Q11) -> 1000 | E11: =D11/$E$4 -> 20 | F11: 100 | G11: 100 | H11: 100 | I11: 100 | J11: 100 | K11: 100 | L11: 100 | M11: 100 | N11: 100 | O11: 100
B12: 8 | C12: Alex Ackah | D12: =SUM(F12:Q12) -> 900 | E12: =D12/$E$4 -> 18 | F12: 100 | G12: 100 | H12: 100 | I12: 100 | J12: 100 | K12: 100 | L12: 100 | M12: 100 | N12: 100
B13: 9 | C13: John Aidoo | D13: =SUM(F13:Q13) -> 900 | E13: =D13/$E$4 -> 18 | F13: 100 | G13: 100 | H13: 100 | I13: 100 | J13: 100 | K13: 100 | L13: 100 | M13: 100 | N13: 100
B14: 10 | C14: Jonas Wereko | D14: =SUM(F14:Q14) -> 900 | E14: =D14/$E$4 -> 18 | F14: 100 | G14: 100 | H14: 100 | I14: 100 | J14: 100 | K14: 100 | L14: 100 | M14: 100 | N14: 100
B15: 11 | C15: Johnson Wood | D15: =SUM(F15:Q15) -> 800 | E15: =D15/$E$4 -> 16 | F15: 100 | G15: 100 | H15: 100 | I15: 100 | J15: 100 | K15: 100 | L15: 100 | M15: 100
B16: 12 | C16: Osei Kwame | D16: =SUM(F16:Q16) -> 800 | E16: =D16/$E$4 -> 16 | F16: 100 | G16: 100 | H16: 100 | I16: 100 | J16: 100 | K16: 100 | L16: 100 | M16: 100
B17: 13 | C17: Fanuel Hagan | D17: =SUM(F17:Q17) -> 700 | E17: =D17/$E$4 -> 14 | F17: 100 | G17: 100 | H17: 100 | I17: 100 | J17: 100 | K17: 100 | L17: 100
B18: 14 | C18: Frederick Wortey Tawiah | D18: =SUM(F18:Q18) -> 700 | E18: =D18/$E$4 -> 14 | F18: 100 | G18: 100 | H18: 100 | I18: 100 | J18: 100 | K18: 100 | L18: 100
B19: 15 | C19: John Ofosuhene Asare | D19: =SUM(F19:Q19) -> 700 | E19: =D19/$E$4 -> 14 | F19: 100 | G19: 100 | H19: 100 | I19: 100 | J19: 100 | K19: 100 | L19: 100
B20: 16 | C20: Prince Asante Ahwireng | D20: =SUM(F20:Q20) -> 600 | E20: =D20/$E$4 -> 12 | F20: 100 | G20: 100 | H20: 100 | I20: 100 | J20: 100 | K20: 100
B21: 17 | C21: Danso Kingsley | D21: =SUM(F21:Q21) -> 300 | E21: =D21/$E$4 -> 6 | F21: 100 | G21: 100 | H21: 100
B22: 18 | C22: Just-Mark Kwabena Quansah | D22: =SUM(F22:Q22) -> 300 | E22: =D22/$E$4 -> 6 | F22: 100 | G22: 100 | H22: 100
B23: 19 | C23: Justice Kojo Acheampong | D23: =SUM(F23:Q23) -> 300 | E23: =D23/$E$4 -> 6 | F23: 100 | G23: 100 | H23: 100
B26: TOTAL | D26: =SUBTOTAL(9,D5:D25) -> 15900 | E26: =SUBTOTAL(9,E5:E25) -> 318 | F26: =SUBTOTAL(9,F5:F25) -> 1900 | G26: =SUBTOTAL(9,G5:G25) -> 1900 | H26: =SUBTOTAL(9,H5:H25) -> 1900 | I26: =SUBTOTAL(9,I5:I25) -> 1600 | J26: =SUBTOTAL(9,J5:J25) -> 1600 | K26: =SUBTOTAL(9,K5:K25) -> 1600 | ... Q26: =SUBTOTAL(9,Q5:Q25) -> 500
B27: COUNT | D27: =COUNTIF(D5:D25,">0") -> 19 | E27: =COUNTIF(E5:E25,">0") -> 19 | F27: =COUNTIF(F5:F25,">0") -> 19 | G27: =COUNTIF(G5:G25,">0") -> 19 | H27: =COUNTIF(H5:H25,">0") -> 19 | I27: =COUNTIF(I5:I25,">0") -> 16 | J27: =COUNTIF(J5:J25,">0") -> 16 | K27: =COUNTIF(K5:K25,">0") -> 16 | ... Q27: =COUNTIF(Q5:Q25,">0") -> 5

Sheet MONTHLY DUES 2027
B2: MONTHLY DUES - 2027
B3: NO. | C3: ELDER | D3: TOTAL | E3: COUNT | F3: 46388 | G3: 46419 | H3: 46447 | I3: 46478 | J3: 46508 | K3: 46539 | L3: 46569 | M3: 46600 | N3: 46631 | O3: 46661 | P3: 46692 | Q3: 46722
D4: DUES | F4: ¢ | G4: ¢ | H4: ¢ | I4: ¢ | J4: ¢ | K4: ¢ | L4: ¢ | M4: ¢ | N4: ¢ | O4: ¢ | Q4: ¢
B5: 1 | D5: =SUM(F5:Q5) -> 0 | E5: =COUNT(F5:Q5) -> 0
B6: 2 | D6: =SUM(F6:Q6) -> 0 | E6: =COUNT(F6:Q6) -> 0
B7: 3 | D7: =SUM(F7:Q7) -> 0 | E7: =COUNT(F7:Q7) -> 0
B8: 4 | D8: =SUM(F8:Q8) -> 0 | E8: =COUNT(F8:Q8) -> 0
B9: 5 | D9: =SUM(F9:Q9) -> 0 | E9: =COUNT(F9:Q9) -> 0
B10: 6 | D10: =SUM(F10:Q10) -> 0 | E10: =COUNT(F10:Q10) -> 0
B11: 7 | D11: =SUM(F11:Q11) -> 0 | E11: =COUNT(F11:Q11) -> 0
B12: 8 | D12: =SUM(F12:Q12) -> 0 | E12: =COUNT(F12:Q12) -> 0
B13: 9 | D13: =SUM(F13:Q13) -> 0 | E13: =COUNT(F13:Q13) -> 0
B14: 10 | D14: =SUM(F14:Q14) -> 0 | E14: =COUNT(F14:Q14) -> 0
B15: 11 | D15: =SUM(F15:Q15) -> 0 | E15: =COUNT(F15:Q15) -> 0
B16: 12 | D16: =SUM(F16:Q16) -> 0 | E16: =COUNT(F16:Q16) -> 0
... B27: 23 | D27: =SUM(F27:Q27) -> 0 | E27: =COUNT(F27:Q27) -> 0
B30: TOTAL | D30: =SUBTOTAL(9,D5:D29) -> 0 | E30: =SUBTOTAL(9,E5:E29) -> 0 | F30: =SUBTOTAL(9,F5:F29) -> 0 | G30: =SUBTOTAL(9,G5:G29) -> 0 | H30: =SUBTOTAL(9,H5:H29) -> 0 | I30: =SUBTOTAL(9,I5:I29) -> 0 | J30: =SUBTOTAL(9,J5:J29) -> 0 | K30: =SUBTOTAL(9,K5:K29) -> 0 | ... Q30: =SUBTOTAL(9,Q5:Q29) -> 0
B31: COUNT | D31: =COUNTIF(D5:D29,">0") -> 0 | E31: =COUNTIF(E5:E29,">0") -> 0 | F31: =COUNTIF(F5:F29,">0") -> 0 | G31: =COUNTIF(G5:G29,">0") -> 0 | H31: =COUNTIF(H5:H29,">0") -> 0 | I31: =COUNTIF(I5:I29,">0") -> 0 | J31: =COUNTIF(J5:J29,">0") -> 0 | K31: =COUNTIF(K5:K29,">0") -> 0 | ... Q31: =COUNTIF(Q5:Q29,">0") -> 0

Sheet MONTHLY DUES 2028
B2: MONTHLY DUES - 2028
B3: NO. | C3: ELDER | D3: TOTAL | E3: COUNT | F3: 46753 | G3: 46784 | H3: 46813 | I3: 46844 | J3: 46874 | K3: 46905 | L3: 46935 | M3: 46966 | N3: 46997 | O3: 47027 | P3: 47058 | Q3: 47088
D4: DUES | F4: ¢ | G4: ¢ | H4: ¢ | I4: ¢ | J4: ¢ | K4: ¢ | L4: ¢ | M4: ¢ | N4: ¢ | O4: ¢ | Q4: ¢
B5: 1 | D5: =SUM(F5:Q5) -> 0 | E5: =COUNT(F5:Q5) -> 0
B6: 2 | D6: =SUM(F6:Q6) -> 0 | E6: =COUNT(F6:Q6) -> 0
B7: 3 | D7: =SUM(F7:Q7) -> 0 | E7: =COUNT(F7:Q7) -> 0
B8: 4 | D8: =SUM(F8:Q8) -> 0 | E8: =COUNT(F8:Q8) -> 0
B9: 5 | D9: =SUM(F9:Q9) -> 0 | E9: =COUNT(F9:Q9) -> 0
B10: 6 | D10: =SUM(F10:Q10) -> 0 | E10: =COUNT(F10:Q10) -> 0
B11: 7 | D11: =SUM(F11:Q11) -> 0 | E11: =COUNT(F11:Q11) -> 0
B12: 8 | D12: =SUM(F12:Q12) -> 0 | E12: =COUNT(F12:Q12) -> 0
B13: 9 | D13: =SUM(F13:Q13) -> 0 | E13: =COUNT(F13:Q13) -> 0
B14: 10 | D14: =SUM(F14:Q14) -> 0 | E14: =COUNT(F14:Q14) -> 0
B15: 11 | D15: =SUM(F15:Q15) -> 0 | E15: =COUNT(F15:Q15) -> 0
B16: 12 | D16: =SUM(F16:Q16) -> 0 | E16: =COUNT(F16:Q16) -> 0
... B27: 23 | D27: =SUM(F27:Q27) -> 0 | E27: =COUNT(F27:Q27) -> 0
B30: TOTAL | D30: =SUBTOTAL(9,D5:D29) -> 0 | E30: =SUBTOTAL(9,E5:E29) -> 0 | F30: =SUBTOTAL(9,F5:F29) -> 0 | G30: =SUBTOTAL(9,G5:G29) -> 0 | H30: =SUBTOTAL(9,H5:H29) -> 0 | I30: =SUBTOTAL(9,I5:I29) -> 0 | J30: =SUBTOTAL(9,J5:J29) -> 0 | K30: =SUBTOTAL(9,K5:K29) -> 0 | ... Q30: =SUBTOTAL(9,Q5:Q29) -> 0
B31: COUNT | D31: =COUNTIF(D5:D29,">0") -> 0 | E31: =COUNTIF(E5:E29,">0") -> 0 | F31: =COUNTIF(F5:F29,">0") -> 0 | G31: =COUNTIF(G5:G29,">0") -> 0 | H31: =COUNTIF(H5:H29,">0") -> 0 | I31: =COUNTIF(I5:I29,">0") -> 0 | J31: =COUNTIF(J5:J29,">0") -> 0 | K31: =COUNTIF(K5:K29,">0") -> 0 | ... Q31: =COUNTIF(Q5:Q29,">0") -> 0

Sheet MONTHLY DUES 2029
B2: MONTHLY DUES - 2029
B3: NO. | C3: ELDER | D3: TOTAL | E3: COUNT | F3: 47119 | G3: 47150 | H3: 47178 | I3: 47209 | J3: 47239 | K3: 47270 | L3: 47300 | M3: 47331 | N3: 47362 | O3: 47392 | P3: 47423 | Q3: 47453
D4: DUES | F4: ¢ | G4: ¢ | H4: ¢ | I4: ¢ | J4: ¢ | K4: ¢ | L4: ¢ | M4: ¢ | N4: ¢ | O4: ¢ | Q4: ¢
B5: 1 | D5: =SUM(F5:Q5) -> 0 | E5: =COUNT(F5:Q5) -> 0
B6: 2 | D6: =SUM(F6:Q6) -> 0 | E6: =COUNT(F6:Q6) -> 0
B7: 3 | D7: =SUM(F7:Q7) -> 0 | E7: =COUNT(F7:Q7) -> 0
B8: 4 | D8: =SUM(F8:Q8) -> 0 | E8: =COUNT(F8:Q8) -> 0
B9: 5 | D9: =SUM(F9:Q9) -> 0 | E9: =COUNT(F9:Q9) -> 0
B10: 6 | D10: =SUM(F10:Q10) -> 0 | E10: =COUNT(F10:Q10) -> 0
B11: 7 | D11: =SUM(F11:Q11) -> 0 | E11: =COUNT(F11:Q11) -> 0
B12: 8 | D12: =SUM(F12:Q12) -> 0 | E12: =COUNT(F12:Q12) -> 0
B13: 9 | D13: =SUM(F13:Q13) -> 0 | E13: =COUNT(F13:Q13) -> 0
B14: 10 | D14: =SUM(F14:Q14) -> 0 | E14: =COUNT(F14:Q14) -> 0
B15: 11 | D15: =SUM(F15:Q15) -> 0 | E15: =COUNT(F15:Q15) -> 0
B16: 12 | D16: =SUM(F16:Q16) -> 0 | E16: =COUNT(F16:Q16) -> 0
... B27: 23 | D27: =SUM(F27:Q27) -> 0 | E27: =COUNT(F27:Q27) -> 0
B30: TOTAL | D30: =SUBTOTAL(9,D5:D29) -> 0 | E30: =SUBTOTAL(9,E5:E29) -> 0 | F30: =SUBTOTAL(9,F5:F29) -> 0 | G30: =SUBTOTAL(9,G5:G29) -> 0 | H30: =SUBTOTAL(9,H5:H29) -> 0 | I30: =SUBTOTAL(9,I5:I29) -> 0 | J30: =SUBTOTAL(9,J5:J29) -> 0 | K30: =SUBTOTAL(9,K5:K29) -> 0 | ... Q30: =SUBTOTAL(9,Q5:Q29) -> 0
B31: COUNT | D31: =COUNTIF(D5:D29,">0") -> 0 | E31: =COUNTIF(E5:E29,">0") -> 0 | F31: =COUNTIF(F5:F29,">0") -> 0 | G31: =COUNTIF(G5:G29,">0") -> 0 | H31: =COUNTIF(H5:H29,">0") -> 0 | I31: =COUNTIF(I5:I29,">0") -> 0 | J31: =COUNTIF(J5:J29,">0") -> 0 | K31: =COUNTIF(K5:K29,">0") -> 0 | ... Q31: =COUNTIF(Q5:Q29,">0") -> 0

Sheet MONTHLY DUES 2030
B2: MONTHLY DUES - 2030
B3: NO. | C3: ELDER | D3: TOTAL | E3: COUNT | F3: 47484 | G3: 47515 | H3: 47543 | I3: 47574 | J3: 47604 | K3: 47635 | L3: 47665 | M3: 47696 | N3: 47727 | O3: 47757 | P3: 47788 | Q3: 47818
D4: DUES | F4: ¢ | G4: ¢ | H4: ¢ | I4: ¢ | J4: ¢ | K4: ¢ | L4: ¢ | M4: ¢ | N4: ¢ | O4: ¢ | Q4: ¢
B5: 1 | D5: =SUM(F5:Q5) -> 0 | E5: =COUNT(F5:Q5) -> 0
B6: 2 | D6: =SUM(F6:Q6) -> 0 | E6: =COUNT(F6:Q6) -> 0
B7: 3 | D7: =SUM(F7:Q7) -> 0 | E7: =COUNT(F7:Q7) -> 0
B8: 4 | D8: =SUM(F8:Q8) -> 0 | E8: =COUNT(F8:Q8) -> 0
B9: 5 | D9: =SUM(F9:Q9) -> 0 | E9: =COUNT(F9:Q9) -> 0
B10: 6 | D10: =SUM(F10:Q10) -> 0 | E10: =COUNT(F10:Q10) -> 0
B11: 7 | D11: =SUM(F11:Q11) -> 0 | E11: =COUNT(F11:Q11) -> 0
B12: 8 | D12: =SUM(F12:Q12) -> 0 | E12: =COUNT(F12:Q12) -> 0
B13: 9 | D13: =SUM(F13:Q13) -> 0 | E13: =COUNT(F13:Q13) -> 0
B14: 10 | D14: =SUM(F14:Q14) -> 0 | E14: =COUNT(F14:Q14) -> 0
B15: 11 | D15: =SUM(F15:Q15) -> 0 | E15: =COUNT(F15:Q15) -> 0
B16: 12 | D16: =SUM(F16:Q16) -> 0 | E16: =COUNT(F16:Q16) -> 0
... B27: 23 | D27: =SUM(F27:Q27) -> 0 | E27: =COUNT(F27:Q27) -> 0
B30: TOTAL | D30: =SUBTOTAL(9,D5:D29) -> 0 | E30: =SUBTOTAL(9,E5:E29) -> 0 | F30: =SUBTOTAL(9,F5:F29) -> 0 | G30: =SUBTOTAL(9,G5:G29) -> 0 | H30: =SUBTOTAL(9,H5:H29) -> 0 | I30: =SUBTOTAL(9,I5:I29) -> 0 | J30: =SUBTOTAL(9,J5:J29) -> 0 | K30: =SUBTOTAL(9,K5:K29) -> 0 | ... Q30: =SUBTOTAL(9,Q5:Q29) -> 0
B31: COUNT | D31: =COUNTIF(D5:D29,">0") -> 0 | E31: =COUNTIF(E5:E29,">0") -> 0 | F31: =COUNTIF(F5:F29,">0") -> 0 | G31: =COUNTIF(G5:G29,">0") -> 0 | H31: =COUNTIF(H5:H29,">0") -> 0 | I31: =COUNTIF(I5:I29,">0") -> 0 | J31: =COUNTIF(J5:J29,">0") -> 0 | K31: =COUNTIF(K5:K29,">0") -> 0 | ... Q31: =COUNTIF(Q5:Q29,">0") -> 0

Sheet MONTHLY DUES 2031
B2: MONTHLY DUES - 2031
B3: NO. | C3: ELDER | D3: TOTAL | E3: COUNT | F3: 47849 | G3: 47880 | H3: 47908 | I3: 47939 | J3: 47969 | K3: 48000 | L3: 48030 | M3: 48061 | N3: 48092 | O3: 48122 | P3: 48153 | Q3: 48183
D4: DUES | F4: ¢ | G4: ¢ | H4: ¢ | I4: ¢ | J4: ¢ | K4: ¢ | L4: ¢ | M4: ¢ | N4: ¢ | O4: ¢ | Q4: ¢
B5: 1 | D5: =SUM(F5:Q5) -> 0 | E5: =COUNT(F5:Q5) -> 0
B6: 2 | D6: =SUM(F6:Q6) -> 0 | E6: =COUNT(F6:Q6) -> 0
B7: 3 | D7: =SUM(F7:Q7) -> 0 | E7: =COUNT(F7:Q7) -> 0
B8: 4 | D8: =SUM(F8:Q8) -> 0 | E8: =COUNT(F8:Q8) -> 0
B9: 5 | D9: =SUM(F9:Q9) -> 0 | E9: =COUNT(F9:Q9) -> 0
B10: 6 | D10: =SUM(F10:Q10) -> 0 | E10: =COUNT(F10:Q10) -> 0
B11: 7 | D11: =SUM(F11:Q11) -> 0 | E11: =COUNT(F11:Q11) -> 0
B12: 8 | D12: =SUM(F12:Q12) -> 0 | E12: =COUNT(F12:Q12) -> 0
B13: 9 | D13: =SUM(F13:Q13) -> 0 | E13: =COUNT(F13:Q13) -> 0
B14: 10 | D14: =SUM(F14:Q14) -> 0 | E14: =COUNT(F14:Q14) -> 0
B15: 11 | D15: =SUM(F15:Q15) -> 0 | E15: =COUNT(F15:Q15) -> 0
B16: 12 | D16: =SUM(F16:Q16) -> 0 | E16: =COUNT(F16:Q16) -> 0
... B23: 19 | D23: =SUM(F23:Q23) -> 0 | E23: =COUNT(F23:Q23) -> 0
B24: 20 | D24: =SUM(F24:Q24) -> 0
B25: 21 | D25: =SUM(F25:Q25) -> 0
B26: 22 | D26: =SUM(F26:Q26) -> 0
B27: 23 | D27: =SUM(F27:Q27) -> 0
B30: TOTAL | D30: =SUBTOTAL(9,D5:D29) -> 0 | E30: =SUBTOTAL(9,E5:E29) -> 0 | F30: =SUBTOTAL(9,F5:F29) -> 0 | G30: =SUBTOTAL(9,G5:G29) -> 0 | H30: =SUBTOTAL(9,H5:H29) -> 0 | I30: =SUBTOTAL(9,I5:I29) -> 0 | J30: =SUBTOTAL(9,J5:J29) -> 0 | K30: =SUBTOTAL(9,K5:K29) -> 0 | ... Q30: =SUBTOTAL(9,Q5:Q29) -> 0
B31: COUNT | D31: =COUNTIF(D5:D29,">0") -> 0 | E31: =COUNTIF(E5:E29,">0") -> 0 | F31: =COUNTIF(F5:F29,">0") -> 0 | G31: =COUNTIF(G5:G29,">0") -> 0 | H31: =COUNTIF(H5:H29,">0") -> 0 | I31: =COUNTIF(I5:I29,">0") -> 0 | J31: =COUNTIF(J5:J29,">0") -> 0 | K31: =COUNTIF(K5:K29,">0") -> 0 | ... Q31: =COUNTIF(Q5:Q29,">0") -> 0

Sheet MONTHLY DUES 2032
B2: MONTHLY DUES - 2032
B3: NO. | C3: ELDER | D3: TOTAL | E3: COUNT | F3: 48214 | G3: 48245 | H3: 48274 | I3: 48305 | J3: 48335 | K3: 48366 | L3: 48396 | M3: 48427 | N3: 48458 | O3: 48488 | P3: 48519 | Q3: 48549
D4: DUES | F4: ¢ | G4: ¢ | H4: ¢ | I4: ¢ | J4: ¢ | K4: ¢ | L4: ¢ | M4: ¢ | N4: ¢ | O4: ¢ | Q4: ¢
B5: 1 | D5: =SUM(F5:Q5) -> 0 | E5: =COUNT(F5:Q5) -> 0
B6: 2 | D6: =SUM(F6:Q6) -> 0 | E6: =COUNT(F6:Q6) -> 0
B7: 3 | D7: =SUM(F7:Q7) -> 0 | E7: =COUNT(F7:Q7) -> 0
B8: 4 | D8: =SUM(F8:Q8) -> 0 | E8: =COUNT(F8:Q8) -> 0
B9: 5 | D9: =SUM(F9:Q9) -> 0 | E9: =COUNT(F9:Q9) -> 0
B10: 6 | D10: =SUM(F10:Q10) -> 0 | E10: =COUNT(F10:Q10) -> 0
B11: 7 | D11: =SUM(F11:Q11) -> 0 | E11: =COUNT(F11:Q11) -> 0
B12: 8 | D12: =SUM(F12:Q12) -> 0 | E12: =COUNT(F12:Q12) -> 0
B13: 9 | D13: =SUM(F13:Q13) -> 0 | E13: =COUNT(F13:Q13) -> 0
B14: 10 | D14: =SUM(F14:Q14) -> 0 | E14: =COUNT(F14:Q14) -> 0
B15: 11 | D15: =SUM(F15:Q15) -> 0 | E15: =COUNT(F15:Q15) -> 0
B16: 12 | D16: =SUM(F16:Q16) -> 0 | E16: =COUNT(F16:Q16) -> 0
... B27: 23 | D27: =SUM(F27:Q27) -> 0 | E27: =COUNT(F27:Q27) -> 0
B30: TOTAL | D30: =SUBTOTAL(9,D5:D29) -> 0 | E30: =SUBTOTAL(9,E5:E29) -> 0 | F30: =SUBTOTAL(9,F5:F29) -> 0 | G30: =SUBTOTAL(9,G5:G29) -> 0 | H30: =SUBTOTAL(9,H5:H29) -> 0 | I30: =SUBTOTAL(9,I5:I29) -> 0 | J30: =SUBTOTAL(9,J5:J29) -> 0 | K30: =SUBTOTAL(9,K5:K29) -> 0 | ... Q30: =SUBTOTAL(9,Q5:Q29) -> 0
B31: COUNT | D31: =COUNTIF(D5:D29,">0") -> 0 | E31: =COUNTIF(E5:E29,">0") -> 0 | F31: =COUNTIF(F5:F29,">0") -> 0 | G31: =COUNTIF(G5:G29,">0") -> 0 | H31: =COUNTIF(H5:H29,">0") -> 0 | I31: =COUNTIF(I5:I29,">0") -> 0 | J31: =COUNTIF(J5:J29,">0") -> 0 | K31: =COUNTIF(K5:K29,">0") -> 0 | ... Q31: =COUNTIF(Q5:Q29,">0") -> 0

Sheet  SPECIAL LEVY FEES
B2: SPECIAL LEVY FEES
A4: ` | B4: NO. | C4: NAME | D4: TOTAL | E4: ELD. ISAAC DARKO | F4: ELD. SAMUEL NKANSAH | G4: ELD. SAMUEL NKANSAH | H4: ELD. JOHN OFOSUHENE ASARE | I4: ELD JONATHAN DANSO SIAW | J4: ELD PRINCE AHWIREN ASANTE
B5: 1 | C5: Alex Ackah | D5: =SUM(E5:N5) -> 700 | E5: 0 | F5: 0 | G5: 200 | H5: 200 | I5: 200 | J5: 100
B6: 2 | C6: Danso Kingsley | D6: =SUM(E6:N6) -> 100 | E6: 0 | F6: 0 | G6: 0 | H6: 0 | I6: 0 | J6: 100
B7: 3 | C7: Fanuel Hagan | D7: =SUM(E7:N7) -> 1000 | E7: 200 | F7: 100 | G7: 200 | H7: 200 | I7: 200 | J7: 100
B8: 4 | C8: Frederick Wortey Tawiah | D8: =SUM(E8:N8) -> 1000 | E8: 200 | F8: 100 | G8: 200 | H8: 200 | I8: 200 | J8: 100
B9: 5 | C9: George Yeboah | D9: =SUM(E9:N9) -> 100 | E9: 0 | F9: 0 | G9: 0 | H9: 0 | I9: 0 | J9: 100
B10: 6 | C10: Isaac Darko | D10: =SUM(E10:N10) -> 800 | E10: 0 | F10: 100 | G10: 200 | H10: 200 | I10: 200 | J10: 100
B11: 7 | C11: Isaac Donkor | D11: =SUM(E11:N11) -> 100 | E11: 0 | F11: 0 | G11: 0 | H11: 0 | I11: 0 | J11: 100
B12: 8 | C12: John Aidoo | D12: =SUM(E12:N12) -> 0 | E12: 0 | F12: 0 | G12: 0 | H12: 0 | I12: 0 | J12: 0
B13: 9 | C13: John Darbo | D13: =SUM(E13:N13) -> 100 | E13: 0 | F13: 0 | G13: 0 | H13: 0 | I13: 0 | J13: 100
B14: 10 | C14: John Ofosuhene Asare | D14: =SUM(E14:N14) -> 800 | E14: 200 | F14: 100 | G14: 200 | H14: 0 | I14: 200 | J14: 100
B15: 11 | C15: Johnson Wood | D15: =SUM(E15:N15) -> 1000 | E15: 200 | F15: 100 | G15: 200 | H15: 200 | I15: 200 | J15: 100
B16: 12 | C16: Jonas Wereko | D16: =SUM(E16:N16) -> 1000 | E16: 200 | F16: 100 | G16: 200 | H16: 200 | I16: 200 | J16: 100
... B28: 24 | C28: William Kojo Anane | D28: =SUM(E28:N28) -> 1000 | E28: 200 | F28: 100 | G28: 200 | H28: 200 | I28: 200 | J28: 100
B30: TOTAL | D30: =SUBTOTAL(9,D5:D28) -> 18100 | E30: =SUBTOTAL(9,E5:E28) -> 3400 | F30: =SUBTOTAL(9,F5:F28) -> 1700 | G30: =SUBTOTAL(9,G5:G28) -> 3600 | H30: =SUBTOTAL(9,H5:H28) -> 3600 | I30: =SUBTOTAL(9,I5:I28) -> 3600 | J30: =SUBTOTAL(9,J5:J28) -> 2200 | K30: =SUBTOTAL(9,K5:K28) -> 0 | ... N30: =SUBTOTAL(9,N5:N28) -> 0
B31: TOTAL MEMBERS PAID | D31: =COUNTIF(D5:D28,">0") -> 23 | E31: =COUNTIF(E5:E28,">0") -> 17 | F31: =COUNTIF(F5:F28,">0") -> 17 | G31: =COUNTIF(G5:G28,">0") -> 18 | H31: =COUNTIF(H5:H28,">0") -> 18 | I31: =COUNTIF(I5:I28,">0") -> 18 | J31: =COUNTIF(J5:J28,">0") -> 22 | K31: =COUNTIF(K5:K28,">0") -> 0 | ... N31: =COUNTIF(N5:N28,">0") -> 0
B32: TOTAL MEMBERS NOT PAID | D32: =COUNTIF(D5:D28,0) -> 1 | E32: =COUNTIF(E5:E28,0) -> 7 | F32: =COUNTIF(F5:F28,0) -> 7 | G32: =COUNTIF(G5:G28,0) -> 6 | H32: =COUNTIF(H5:H28,0) -> 6 | I32: =COUNTIF(I5:I28,0) -> 6 | J32: =COUNTIF(J5:J28,0) -> 2 | K32: =COUNTIF(K5:K28,0) -> 0 | ... N32: =COUNTIF(N5:N28,0) -> 0

Sheet SPECIAL LEVY
B2: SPECIAL LEVY
A3: ` | B3: NO. | C3: NAME | D3: TOTAL | E3: ELD. ISAAC DARKO | F3: ELD. SAMUEL NKANSAH | G3: ELD. SAMUEL NKANSAH | H3: ELD. JOHN OFOSUHENE ASARE | I3: ELD JONATHAN DANSO SIAW | J3: ELD PRINCE AHWIREN ASANTE
B4: 1 | C4: Alex Ackah | D4: =SUM(E4:N4) -> 700 | E4: 0 | F4: 0 | G4: 200 | H4: 200 | I4: 200 | J4: 100
B5: 2 | C5: Danso Kingsley | D5: =SUM(E5:N5) -> 100 | E5: 0 | F5: 0 | G5: 0 | H5: 0 | I5: 0 | J5: 100
B6: 3 | C6: Fanuel Hagan | D6: =SUM(E6:N6) -> 1000 | E6: 200 | F6: 100 | G6: 200 | H6: 200 | I6: 200 | J6: 100
B7: 4 | C7: Frederick Wortey Tawiah | D7: =SUM(E7:N7) -> 1000 | E7: 200 | F7: 100 | G7: 200 | H7: 200 | I7: 200 | J7: 100
B8: 5 | C8: George Yeboah | D8: =SUM(E8:N8) -> 100 | E8: 0 | F8: 0 | G8: 0 | H8: 0 | I8: 0 | J8: 100
B9: 6 | C9: Isaac Darko | D9: =SUM(E9:N9) -> 800 | E9: 0 | F9: 100 | G9: 200 | H9: 200 | I9: 200 | J9: 100
B10: 7 | C10: Isaac Donkor | D10: =SUM(E10:N10) -> 100 | E10: 0 | F10: 0 | G10: 0 | H10: 0 | I10: 0 | J10: 100
B11: 8 | C11: John Aidoo | D11: =SUM(E11:N11) -> 0 | E11: 0 | F11: 0 | G11: 0 | H11: 0 | I11: 0 | J11: 0
B12: 9 | C12: John Darbo | D12: =SUM(E12:N12) -> 100 | E12: 0 | F12: 0 | G12: 0 | H12: 0 | I12: 0 | J12: 100
B13: 10 | C13: John Ofosuhene Asare | D13: =SUM(E13:N13) -> 800 | E13: 200 | F13: 100 | G13: 200 | H13: 0 | I13: 200 | J13: 100
B14: 11 | C14: Johnson Wood | D14: =SUM(E14:N14) -> 1000 | E14: 200 | F14: 100 | G14: 200 | H14: 200 | I14: 200 | J14: 100
B15: 12 | C15: Jonas Wereko | D15: =SUM(E15:N15) -> 1000 | E15: 200 | F15: 100 | G15: 200 | H15: 200 | I15: 200 | J15: 100
... B27: 24 | C27: William Kojo Anane | D27: =SUM(E27:N27) -> 1000 | E27: 200 | F27: 100 | G27: 200 | H27: 200 | I27: 200 | J27: 100
B29: TOTAL | D29: =SUBTOTAL(9,D4:D27) -> 18100 | E29: =SUBTOTAL(9,E4:E27) -> 3400 | F29: =SUBTOTAL(9,F4:F27) -> 1700 | G29: =SUBTOTAL(9,G4:G27) -> 3600 | H29: =SUBTOTAL(9,H4:H27) -> 3600 | I29: =SUBTOTAL(9,I4:I27) -> 3600 | J29: =SUBTOTAL(9,J4:J27) -> 2200 | K29: =SUBTOTAL(9,K4:K27) -> 0 | ... N29: =SUBTOTAL(9,N4:N27) -> 0
B30: TOTAL MEMBERS PAID | D30: =COUNTIF(D4:D27,">0") -> 23 | E30: =COUNTIF(E4:E27,">0") -> 17 | F30: =COUNTIF(F4:F27,">0") -> 17 | G30: =COUNTIF(G4:G27,">0") -> 18 | H30: =COUNTIF(H4:H27,">0") -> 18 | I30: =COUNTIF(I4:I27,">0") -> 18 | J30: =COUNTIF(J4:J27,">0") -> 22 | K30: =COUNTIF(K4:K27,">0") -> 0 | ... N30: =COUNTIF(N4:N27,">0") -> 0
B31: TOTAL MEMBERS NOT PAID | D31: =COUNTIF(D4:D27,0) -> 1 | E31: =COUNTIF(E4:E27,0) -> 7 | F31: =COUNTIF(F4:F27,0) -> 7 | G31: =COUNTIF(G4:G27,0) -> 6 | H31: =COUNTIF(H4:H27,0) -> 6 | I31: =COUNTIF(I4:I27,0) -> 6 | J31: =COUNTIF(J4:J27,0) -> 2 | K31: =COUNTIF(K4:K27,0) -> 0 | ... N31: =COUNTIF(N4:N27,0) -> 0

Sheet LEVY DISBURSMENT
B2: DISBURSEMENT | N2: TRAIL BALANCE
A3: 1 | B3: ELD. ISAAC DARKO (FUNERAL)
B4: DATE | C4: FIRST CONTRIBUTION | D4: INCOME | E4: EXPENSES | F4: BALANCE
B5: 45157 | C5: Total Contribution | D5: ='SPECIAL LEVY'!E29 -> 3400 | F5: =D5 -> 3400
B6: 45158 | C6: Loan from Dues | D6: 400 | F6: =F5+D6-E6 -> 3800
B7: 45158 | C7: Mother's Funeral Donation | E7: 3140 | F7: =F6+D7-E7 -> 660
B8: 45158 | C8: Transportation to Nsawam (2 Members) | E8: 600 | F8: =F7+D8-E8 -> 60
B9: 45158 | C9: Taxes on MoMo | E9: =F6*1.5% -> 57 | F9: =F8+D9-E9 -> 3
B10: 45158 | C10: Balance C/F | F10: =F9+D10-E10 -> 3
B11: TOTAL & BALANCE | D11: =SUM(D5:D10) -> 3800 | E11: =SUM(E5:E10) -> 3797 | F11: =D11-E11 -> 3
A14: 2 | B14: ELD. SAMUEL YAW NKANSAH (CHILD NAMING)
B15: DATE | C15: SECOND CONTRIBUTION | D15: INCOME | E15: EXPENSES | F15: BALANCE
B16: =B10 -> 45158 | C16: Balance C/D | D16: =F10 -> 3 | F16: =D16 -> 3
B17: 45268 | C17: Total Contribution | D17: ='SPECIAL LEVY'!F29 -> 1700 | F17: =F16+D17-E17 -> 1703
B18: 45269 | C18: Child Naming Ceremony | E18: 1015 | F18: =F17+D18-E18 -> 688
B19: 45269 | C19: Transportation to Darkoman (2 Members) | E19: 400 | F19: =F18+D19-E19 -> 288
B20: 45269 | C20: Taxes on MoMo | E20: =1400*1.5% -> 21 | F20: =F19+D20-E20 -> 267
B21: 45269 | C21: Balance C/F | F21: =F20+D21-E21 -> 267
B22: TOTAL & BALANCE | D22: =SUM(D16:D21) -> 1703 | E22: =SUM(E16:E21) -> 1436 | F22: =D22-E22 -> 267
A25: 3 | B25: ELD. SAMUEL YAW NKANSAH (FUNERAL)
B26: DATE | C26: THIRD CONTRIBUTION | D26: INCOME | E26: EXPENSES | F26: BALANCE
B27: =B21 -> 45269 | C27: Balance C/D | D27: =F21 -> 267 | F27: =D27 -> 267
B28: 45594 | C28: Total Contribution | D28: ='SPECIAL LEVY'!G29 -> 3600 | F28: =F27+D28-E28 -> 3867
B29: 45595 | C29: Father's Funeral Donation | E29: 3040 | F29: =F28+D29-E29 -> 827
B30: 45595 | C30: Transportation to Akim Oda (2 Members) | E30: 600 | F30: =F29+D30-E30 -> 227
B31: 45595 | C31: Taxes on MoMo | E31: =3600*1.5% -> 54 | F31: =F30+D31-E31 -> 173
B32: 45595 | C32: Balance C/F | F32: =F31+D32-E32 -> 173
B33: TOTAL & BALANCE | D33: =SUM(D27:D32) -> 3867 | E33: =SUM(E27:E32) -> 3694 | F33: =D33-E33 -> 173
A36: 4 | B36: ELD. JOHN OFOSUHENE ASARE (FUNERAL)
B37: DATE | C37: FOURTH CONTRIBUTION | D37: INCOME | E37: EXPENSES | F37: BALANCE
B38: =B32 -> 45595 | C38: Balance C/D | D38: =F32 -> 173 | F38: =D38 -> 173
B39: 45615 | C39: Total Contribution | D39: ='SPECIAL LEVY'!H29 -> 3600 | F39: =F38+D39-E39 -> 3773
B40: 45616 | C40: Father's Funeral Donation | E40: 3040 | F40: =F39+D40-E40 -> 733
B41: 45616 | C41: Transportation to Akim Asuom (2 Members) | E41: 600 | F41: =F40+D41-E41 -> 133
B42: 45616 | C42: Taxes on MoMo | E42: =3600*1.5% -> 54 | F42: =F41+D42-E42 -> 79
B43: 45616 | C43: Balance C/F | F43: =F42+D43-E43 -> 79
B44: TOTAL & BALANCE | D44: =SUM(D38:D43) -> 3773 | E44: =SUM(E38:E43) -> 3694 | F44: =D44-E44 -> 79
A47: 5 | B47: ELD JONATHAN DANSO SIAW (FUNERAL)
B48: DATE | C48: FIFTH CONTRIBUTION | D48: INCOME | E48: EXPENSES | F48: BALANCE
B49: =B43 -> 45616 | C49: Balance C/D | D49: =F44 -> 79 | F49: =D49 -> 79
B50: 45647 | C50: Total Contribution | D50: ='SPECIAL LEVY'!I29 -> 3600 | F50: =F49+D50-E50 -> 3679
B51: 45648 | C51: Father's Funeral Donation | E51: 3040 | F51: =F50+D51-E51 -> 639
B52: 45648 | C52: Taxes on MoMo | E52: =3400*1.5% -> 51 | F52: =F51+D52-E52 -> 588
B53: 45648 | C53: Balance C/F | F53: =F52+D53-E53 -> 588
B54: TOTAL & BALANCE | D54: =SUM(D49:D53) -> 3679 | E54: =SUM(E49:E53) -> 3091 | F54: =D54-E54 -> 588
A57: 6 | B57: ELD PRINCE AHWIREN ASANTE (CHILD NAMING)
B58: DATE | C58: SIXTH CONTRIBUTION | D58: INCOME | E58: EXPENSES | F58: BALANCE
B59: =B53 -> 45648 | C59: Balance C/D | D59: =F54 -> 588 | F59: =D59 -> 588
B60: 45806 | C60: Total Contribution | D60: ='SPECIAL LEVY'!J29 -> 2200 | F60: =F59+D60-E60 -> 2788
B61: 45807 | C61: Child Naming Ceremony | E61: 1015 | F61: =F60+D61-E61 -> 1773
B62: 45807 | C62: Transportation to Darkoman (2 Members) | E62: 500 | F62: =F61+D62-E62 -> 1273
B63: 45807 | C63: Taxes on MoMo | E63: =1500*1.5% -> 22.5 | F63: =F62+D63-E63 -> 1250.5
B64: 45807 | C64: Balance C/F | F64: =F63+D64-E64 -> 1250.5
B65: TOTAL & BALANCE | D65: =SUM(D59:D64) -> 2788 | E65: =SUM(E59:E64) -> 1537.5 | F65: =D65-E65 -> 1250.5
A68: 7 | B68: =#REF! -> #REF!
B69: DATE | C69: SEVENTH CONTRIBUTION | D69: INCOME | E69: EXPENSES | F69: BALANCE
B70: =B64 -> 45807 | C70: Balance C/D | D70: =F65 -> 1250.5 | F70: =D70 -> 1250.5
C71: Total Contribution | D71: ='SPECIAL LEVY'!K29 -> 0 | F71: =F70+D71-E71 -> 1250.5
F72: =F71+D72-E72 -> 1250.5
C73: Transportation to Darkoman (2 Members) | F73: =F72+D73-E73 -> 1250.5
C74: Taxes on MoMo | F74: =F73+D74-E74 -> 1250.5
C75: Balance C/F | F75: =F74+D75-E75 -> 1250.5
B76: TOTAL & BALANCE | D76: =SUM(D70:D75) -> 1250.5 | E76: =SUM(E70:E75) -> 0 | F76: =D76-E76 -> 1250.5
A79: 8 | B79: =#REF! -> #REF!
B80: DATE | C80: EIGHTH CONTRIBUTION | D80: INCOME | E80: EXPENSES | F80: BALANCE
C81: Balance C/D | F81: =D81 -> 0
C82: Total Contribution | F82: =F81+D82-E82 -> 0
F83: =F82+D83-E83 -> 0
C84: Transportation to Darkoman (2 Members) | F84: =F83+D84-E84 -> 0
C85: Taxes on MoMo | F85: =F84+D85-E85 -> 0
C86: Balance C/F | F86: =F85+D86-E86 -> 0
B87: TOTAL & BALANCE | D87: =SUM(D81:D86) -> 0 | E87: =SUM(E81:E86) -> 0 | F87: =D87-E87 -> 0
A90: 9 | B90: =#REF! -> #REF!
B91: DATE | C91: NINETH CONTRIBUTION | D91: INCOME | E91: EXPENSES | F91: BALANCE
C92: Balance C/D | F92: =D92 -> 0
C93: Total Contribution | F93: =F92+D93-E93 -> 0
F94: =F93+D94-E94 -> 0
C95: Transportation to Darkoman (2 Members) | F95: =F94+D95-E95 -> 0
C96: Taxes on MoMo | F96: =F95+D96-E96 -> 0
C97: Balance C/F | F97: =F96+D97-E97 -> 0
B98: TOTAL & BALANCE | D98: =SUM(D92:D97) -> 0 | E98: =SUM(E92:E97) -> 0 | F98: =D98-E98 -> 0
A101: 10 | B101: =#REF! -> #REF!
B102: DATE | C102: TENTH CONTRIBUTION | D102: INCOME | E102: EXPENSES | F102: BALANCE
C103: Balance C/D | F103: =D103 -> 0
C104: Total Contribution | F104: =F103+D104-E104 -> 0
F105: =F104+D105-E105 -> 0
C106: Transportation to Darkoman (2 Members) | F106: =F105+D106-E106 -> 0
C107: Taxes on MoMo | F107: =F106+D107-E107 -> 0
C108: Balance C/F | F108: =F107+D108-E108 -> 0
B109: TOTAL & BALANCE | D109: =SUM(D103:D108) -> 0 | E109: =SUM(E103:E108) -> 0 | F109: =D109-E109 -> 0

Sheet LEVY ACCOUNT
B2: DISBURSEMENT OF ACCOUNT
B3: DATE | C3: PARTICULARS | D3: INCOME | E3: EXPENSES | F3: BALANCE | G3: FUNERAL | H3: CHILD NAMING | I3: T & T | J3: MOMO TAXES
B4: ='LEVY DISBURSMENT'!B6 -> 45158 | C4: ELD. ISAAC DARKO (FUNERAL) | D4: ='LEVY DISBURSMENT'!F6 -> 3800 | E4: =SUM(G4:K4) -> 3797 | F4: =D4-E4 -> 3 | G4: ='LEVY DISBURSMENT'!E7 -> 3140 | I4: ='LEVY DISBURSMENT'!E8 -> 600 | J4: ='LEVY DISBURSMENT'!E9 -> 57
B5: ='LEVY DISBURSMENT'!B18 -> 45269 | C5: ELD. SAMUEL YAW NKANSAH (CHILD NAMING) | D5: ='LEVY DISBURSMENT'!D17 -> 1700 | E5: =SUM(G5:K5) -> 1436 | F5: =F4+D5-E5 -> 267 | H5: ='LEVY DISBURSMENT'!E18 -> 1015 | I5: ='LEVY DISBURSMENT'!E19 -> 400 | J5: ='LEVY DISBURSMENT'!E20 -> 21
B6: ='LEVY DISBURSMENT'!B29 -> 45595 | C6: ELD. SAMUEL YAW NKANSAH (FUNERAL) | D6: ='LEVY DISBURSMENT'!D28 -> 3600 | E6: =SUM(G6:K6) -> 3694 | F6: =F5+D6-E6 -> 173 | G6: ='LEVY DISBURSMENT'!E29 -> 3040 | I6: ='LEVY DISBURSMENT'!E30 -> 600 | J6: ='LEVY DISBURSMENT'!E31 -> 54
B7: ='LEVY DISBURSMENT'!B40 -> 45616 | C7: ELD. JOHN OFOSUHENE ASARE (FUNERAL) | D7: ='LEVY DISBURSMENT'!D39 -> 3600 | E7: =SUM(G7:K7) -> 3694 | F7: =F6+D7-E7 -> 79 | G7: ='LEVY DISBURSMENT'!E40 -> 3040 | I7: ='LEVY DISBURSMENT'!E41 -> 600 | J7: ='LEVY DISBURSMENT'!E42 -> 54
B8: ='LEVY DISBURSMENT'!B51 -> 45648 | C8: ELD JONATHAN DANSO SIAW (FUNERAL) | D8: ='LEVY DISBURSMENT'!D50 -> 3600 | E8: =SUM(G8:K8) -> 3091 | F8: =F7+D8-E8 -> 588 | G8: ='LEVY DISBURSMENT'!E51 -> 3040 | J8: ='LEVY DISBURSMENT'!E52 -> 51
B9: ='LEVY DISBURSMENT'!B61 -> 45807 | C9: ELD PRINCE AHWIREN ASANTE (CHILD NAMING) | D9: ='LEVY DISBURSMENT'!D60 -> 2200 | E9: =SUM(G9:K9) -> 1537.5 | F9: =F8+D9-E9 -> 1250.5 | H9: ='LEVY DISBURSMENT'!E61 -> 1015 | I9: ='LEVY DISBURSMENT'!E62 -> 500 | J9: ='LEVY DISBURSMENT'!E63 -> 22.5
E10: =SUM(G10:K10) -> 0 | F10: =F9+D10-E10 -> 1250.5
E11: =SUM(G11:K11) -> 0 | F11: =F10+D11-E11 -> 1250.5
E12: =SUM(G12:K12) -> 0 | F12: =F11+D12-E12 -> 1250.5
E13: =SUM(G13:K13) -> 0 | F13: =F12+D13-E13 -> 1250.5
E14: =SUM(G14:K14) -> 0 | F14: =F13+D14-E14 -> 1250.5
E15: =SUM(G15:K15) -> 0 | F15: =F14+D15-E15 -> 1250.5
E16: =SUM(G16:K16) -> 0 | F16: =F15+D16-E16 -> 1250.5
E17: =SUM(G17:K17) -> 0 | F17: =F16+D17-E17 -> 1250.5
E18: =SUM(G18:K18) -> 0 | F18: =F17+D18-E18 -> 1250.5
E19: =SUM(G19:K19) -> 0 | F19: =F18+D19-E19 -> 1250.5
E20: =SUM(G20:K20) -> 0 | F20: =F19+D20-E20 -> 1250.5
E21: =SUM(G21:K21) -> 0 | F21: =F20+D21-E21 -> 1250.5
... E23: =SUM(G23:K23) -> 0 | F23: =F22+D23-E23 -> 1250.5
B24: TOTAL | D24: =SUM(D4:D23) -> 18500 | E24: =SUM(E4:E23) -> 17249.5 | F24: =D24-E24 -> 1250.5 | G24: =SUM(G4:G23) -> 12260 | H24: =SUM(H4:H23) -> 2030 | I24: =SUM(I4:I23) -> 2700 | J24: =SUM(J4:J23) -> 259.5 | K24: =SUM(K4:K23) -> 0

Sheet LEVY TRAIL BALANCE
B2: TRAIL BALANCE
B3: PARTICULARS | C3: INCOME | D3: EXPENCES
C4: ¢ | D4: ¢
B5: Special Levy No 1 | C5: ='LEVY ACCOUNT'!D4 -> 3800
B6: Special Levy No 2 | C6: ='LEVY ACCOUNT'!D5 -> 1700
B7: Special Levy No 3 | C7: ='LEVY ACCOUNT'!D6 -> 3600
B8: Special Levy No 4 | C8: ='LEVY ACCOUNT'!D7 -> 3600
B9: Special Levy No 5 | C9: ='LEVY ACCOUNT'!D8 -> 3600
B10: Special Levy No 6 | C10: ='LEVY ACCOUNT'!D9 -> 2200
B11: Funeral Donations | D11: ='LEVY ACCOUNT'!G24 -> 12260
B12: Child Naming Donations | D12: ='LEVY ACCOUNT'!H24 -> 2030
B13: Transportations | D13: ='LEVY ACCOUNT'!I24 -> 2700
B14: MoMo Charges | D14: ='LEVY ACCOUNT'!J24 -> 259.5
B15: Balance on MoMo Account | D15: ='LEVY ACCOUNT'!F24 -> 1250.5
B18: TOTAL | C18: =SUM(C5:C17) -> 18500 | D18: =SUM(D5:D16) -> 18500

Sheet MTN MOMO ACCOUNT
B2: MTN MOMO ACCOUNTS
B3: DATE | C3: PARTICULARS | D3: INCOME | E3: EXPENSES | F3: BALANCE | G3: REGISTRATION FEE | H3: DUES 2023 | I3: DUES 2024 | J3: DUES 2025 | K3: DUES 2026 | L3: DUES 2027 | M3: SPECIAL LEVY 1 | N3: SPECIAL LEVY 2 | O3: SPECIAL LEVY 3 | P3: SPECIAL LEVY 4 | Q3: SPECIAL LEVY 5 | R3: SPECIAL LEVY 6 | S3: MOMO INTREST | T3: BANK WITHDRAWAL | U3: LEVY BALANCE | V3: SPECIAL CONTRIBUTION | W3: DUES ACCOUNTS | X3: LEVY ACCOUNT
B4: 1044 | C4: MOMO: '0530486443 - MECHANT: 293658 | D4: ¢ | E4: ¢ | F4: ¢ | G4: ¢ | H4: ¢ | I4: ¢ | J4: ¢ | K4: ¢ | M4: ¢ | N4: ¢ | O4: ¢ | P4: ¢ | Q4: ¢ | R4: ¢ | S4: ¢ | W4: ¢ | X4: ¢ | Y4: ¢
B5: 1 | C5: Alex Ackah | D5: =SUM(G5:V5) -> 3900 | F5: =D5 -> 3900 | G5: =IFERROR(VLOOKUP($C5,'MEMBERS LIST'!$D$5:$AT$28,32,0),0) -> 200 | H5: =IFERROR(VLOOKUP($C5,'MONTHLY DUES 2023'!$C$5:$D$23,2,0),0) -> 0 | I5: =IFERROR(VLOOKUP($C5,'MONTHLY DUES 2024'!$C$5:$D$25,2,0),0) -> 900 | J5: =IFERROR(VLOOKUP($C5,'MONTHLY DUES 2025'!$C$5:$D$26,2,0),0) -> 1200 | K5: =IFERROR(VLOOKUP($C5,'MONTHLY DUES 2026'!$C$5:$D$23,2,0),0) -> 900 | M5: =IFERROR(VLOOKUP($C5,'SPECIAL LEVY'!$C$4:$N$27,3,0),0) -> 0 | N5: =IFERROR(VLOOKUP($C5,'SPECIAL LEVY'!$C$4:$N$27,4,0),0) -> 0 | O5: =IFERROR(VLOOKUP($C5,'SPECIAL LEVY'!$C$4:$N$27,5,0),0) -> 200 | P5: =IFERROR(VLOOKUP($C5,'SPECIAL LEVY'!$C$4:$N$27,6,0),0) -> 200 | Q5: =IFERROR(VLOOKUP($C5,'SPECIAL LEVY'!$C$4:$N$27,7,0),0) -> 200 | R5: =IFERROR(VLOOKUP($C5,'SPECIAL LEVY'!$C$4:$J$27,8,0),0) -> 100
B6: 2 | C6: Danso Kingsley | D6: =SUM(G6:V6) -> 1800 | E6: =SUM(W6:Y6) -> 0 | F6: =F5+D6-E6 -> 5700 | G6: =IFERROR(VLOOKUP($C6,'MEMBERS LIST'!$D$5:$AT$28,32,0),0) -> 200 | H6: =IFERROR(VLOOKUP($C6,'MONTHLY DUES 2023'!$C$5:$D$23,2,0),0) -> 0 | I6: =IFERROR(VLOOKUP($C6,'MONTHLY DUES 2024'!$C$5:$D$25,2,0),0) -> 0 | J6: =IFERROR(VLOOKUP($C6,'MONTHLY DUES 2025'!$C$5:$D$26,2,0),0) -> 1200 | K6: =IFERROR(VLOOKUP($C6,'MONTHLY DUES 2026'!$C$5:$D$23,2,0),0) -> 300 | M6: =IFERROR(VLOOKUP($C6,'SPECIAL LEVY'!$C$4:$N$27,3,0),0) -> 0 | N6: =IFERROR(VLOOKUP($C6,'SPECIAL LEVY'!$C$4:$N$27,4,0),0) -> 0 | O6: =IFERROR(VLOOKUP($C6,'SPECIAL LEVY'!$C$4:$N$27,5,0),0) -> 0 | P6: =IFERROR(VLOOKUP($C6,'SPECIAL LEVY'!$C$4:$N$27,6,0),0) -> 0 | Q6: =IFERROR(VLOOKUP($C6,'SPECIAL LEVY'!$C$4:$N$27,7,0),0) -> 0 | R6: =IFERROR(VLOOKUP($C6,'SPECIAL LEVY'!$C$4:$J$27,8,0),0) -> 100
B7: 3 | C7: Fanuel Hagan | D7: =SUM(G7:V7) -> 4600 | E7: =SUM(W7:Y7) -> 0 | F7: =F6+D7-E7 -> 10300 | G7: =IFERROR(VLOOKUP($C7,'MEMBERS LIST'!$D$5:$AT$28,32,0),0) -> 200 | H7: =IFERROR(VLOOKUP($C7,'MONTHLY DUES 2023'!$C$5:$D$23,2,0),0) -> 600 | I7: =IFERROR(VLOOKUP($C7,'MONTHLY DUES 2024'!$C$5:$D$25,2,0),0) -> 900 | J7: =IFERROR(VLOOKUP($C7,'MONTHLY DUES 2025'!$C$5:$D$26,2,0),0) -> 1200 | K7: =IFERROR(VLOOKUP($C7,'MONTHLY DUES 2026'!$C$5:$D$23,2,0),0) -> 700 | M7: =IFERROR(VLOOKUP($C7,'SPECIAL LEVY'!$C$4:$N$27,3,0),0) -> 200 | N7: =IFERROR(VLOOKUP($C7,'SPECIAL LEVY'!$C$4:$N$27,4,0),0) -> 100 | O7: =IFERROR(VLOOKUP($C7,'SPECIAL LEVY'!$C$4:$N$27,5,0),0) -> 200 | P7: =IFERROR(VLOOKUP($C7,'SPECIAL LEVY'!$C$4:$N$27,6,0),0) -> 200 | Q7: =IFERROR(VLOOKUP($C7,'SPECIAL LEVY'!$C$4:$N$27,7,0),0) -> 200 | R7: =IFERROR(VLOOKUP($C7,'SPECIAL LEVY'!$C$4:$J$27,8,0),0) -> 100
B8: 4 | C8: Frederick Wortey Tawiah | D8: =SUM(G8:V8) -> 4600 | E8: =SUM(W8:Y8) -> 0 | F8: =F7+D8-E8 -> 14900 | G8: =IFERROR(VLOOKUP($C8,'MEMBERS LIST'!$D$5:$AT$28,32,0),0) -> 200 | H8: =IFERROR(VLOOKUP($C8,'MONTHLY DUES 2023'!$C$5:$D$23,2,0),0) -> 600 | I8: =IFERROR(VLOOKUP($C8,'MONTHLY DUES 2024'!$C$5:$D$25,2,0),0) -> 900 | J8: =IFERROR(VLOOKUP($C8,'MONTHLY DUES 2025'!$C$5:$D$26,2,0),0) -> 1200 | K8: =IFERROR(VLOOKUP($C8,'MONTHLY DUES 2026'!$C$5:$D$23,2,0),0) -> 700 | M8: =IFERROR(VLOOKUP($C8,'SPECIAL LEVY'!$C$4:$N$27,3,0),0) -> 200 | N8: =IFERROR(VLOOKUP($C8,'SPECIAL LEVY'!$C$4:$N$27,4,0),0) -> 100 | O8: =IFERROR(VLOOKUP($C8,'SPECIAL LEVY'!$C$4:$N$27,5,0),0) -> 200 | P8: =IFERROR(VLOOKUP($C8,'SPECIAL LEVY'!$C$4:$N$27,6,0),0) -> 200 | Q8: =IFERROR(VLOOKUP($C8,'SPECIAL LEVY'!$C$4:$N$27,7,0),0) -> 200 | R8: =IFERROR(VLOOKUP($C8,'SPECIAL LEVY'!$C$4:$J$27,8,0),0) -> 100
B9: 5 | C9: George Yeboah | D9: =SUM(G9:V9) -> 500 | E9: =SUM(W9:Y9) -> 0 | F9: =F8+D9-E9 -> 15400 | G9: =IFERROR(VLOOKUP($C9,'MEMBERS LIST'!$D$5:$AT$28,32,0),0) -> 200 | H9: =IFERROR(VLOOKUP($C9,'MONTHLY DUES 2023'!$C$5:$D$23,2,0),0) -> 0 | I9: =IFERROR(VLOOKUP($C9,'MONTHLY DUES 2024'!$C$5:$D$25,2,0),0) -> 0 | J9: =IFERROR(VLOOKUP($C9,'MONTHLY DUES 2025'!$C$5:$D$26,2,0),0) -> 200 | K9: =IFERROR(VLOOKUP($C9,'MONTHLY DUES 2026'!$C$5:$D$23,2,0),0) -> 0 | M9: =IFERROR(VLOOKUP($C9,'SPECIAL LEVY'!$C$4:$N$27,3,0),0) -> 0 | N9: =IFERROR(VLOOKUP($C9,'SPECIAL LEVY'!$C$4:$N$27,4,0),0) -> 0 | O9: =IFERROR(VLOOKUP($C9,'SPECIAL LEVY'!$C$4:$N$27,5,0),0) -> 0 | P9: =IFERROR(VLOOKUP($C9,'SPECIAL LEVY'!$C$4:$N$27,6,0),0) -> 0 | Q9: =IFERROR(VLOOKUP($C9,'SPECIAL LEVY'!$C$4:$N$27,7,0),0) -> 0 | R9: =IFERROR(VLOOKUP($C9,'SPECIAL LEVY'!$C$4:$J$27,8,0),0) -> 100
B10: 6 | C10: Isaac Darko | D10: =SUM(G10:V10) -> 4900 | E10: =SUM(W10:Y10) -> 0 | F10: =F9+D10-E10 -> 20300 | G10: =IFERROR(VLOOKUP($C10,'MEMBERS LIST'!$D$5:$AT$28,32,0),0) -> 200 | H10: =IFERROR(VLOOKUP($C10,'MONTHLY DUES 2023'!$C$5:$D$23,2,0),0) -> 600 | I10: =IFERROR(VLOOKUP($C10,'MONTHLY DUES 2024'!$C$5:$D$25,2,0),0) -> 900 | J10: =IFERROR(VLOOKUP($C10,'MONTHLY DUES 2025'!$C$5:$D$26,2,0),0) -> 1200 | K10: =IFERROR(VLOOKUP($C10,'MONTHLY DUES 2026'!$C$5:$D$23,2,0),0) -> 1200 | M10: =IFERROR(VLOOKUP($C10,'SPECIAL LEVY'!$C$4:$N$27,3,0),0) -> 0 | N10: =IFERROR(VLOOKUP($C10,'SPECIAL LEVY'!$C$4:$N$27,4,0),0) -> 100 | O10: =IFERROR(VLOOKUP($C10,'SPECIAL LEVY'!$C$4:$N$27,5,0),0) -> 200 | P10: =IFERROR(VLOOKUP($C10,'SPECIAL LEVY'!$C$4:$N$27,6,0),0) -> 200 | Q10: =IFERROR(VLOOKUP($C10,'SPECIAL LEVY'!$C$4:$N$27,7,0),0) -> 200 | R10: =IFERROR(VLOOKUP($C10,'SPECIAL LEVY'!$C$4:$J$27,8,0),0) -> 100
B11: 7 | C11: Isaac Donkor | D11: =SUM(G11:V11) -> 3600 | E11: =SUM(W11:Y11) -> 0 | F11: =F10+D11-E11 -> 23900 | G11: =IFERROR(VLOOKUP($C11,'MEMBERS LIST'!$D$5:$AT$28,32,0),0) -> 200 | H11: =IFERROR(VLOOKUP($C11,'MONTHLY DUES 2023'!$C$5:$D$23,2,0),0) -> 0 | I11: =IFERROR(VLOOKUP($C11,'MONTHLY DUES 2024'!$C$5:$D$25,2,0),0) -> 900 | J11: =IFERROR(VLOOKUP($C11,'MONTHLY DUES 2025'!$C$5:$D$26,2,0),0) -> 1200 | K11: =IFERROR(VLOOKUP($C11,'MONTHLY DUES 2026'!$C$5:$D$23,2,0),0) -> 1200 | M11: =IFERROR(VLOOKUP($C11,'SPECIAL LEVY'!$C$4:$N$27,3,0),0) -> 0 | N11: =IFERROR(VLOOKUP($C11,'SPECIAL LEVY'!$C$4:$N$27,4,0),0) -> 0 | O11: =IFERROR(VLOOKUP($C11,'SPECIAL LEVY'!$C$4:$N$27,5,0),0) -> 0 | P11: =IFERROR(VLOOKUP($C11,'SPECIAL LEVY'!$C$4:$N$27,6,0),0) -> 0 | Q11: =IFERROR(VLOOKUP($C11,'SPECIAL LEVY'!$C$4:$N$27,7,0),0) -> 0 | R11: =IFERROR(VLOOKUP($C11,'SPECIAL LEVY'!$C$4:$J$27,8,0),0) -> 100
B12: 8 | C12: John Aidoo | D12: =SUM(G12:V12) -> 1100 | E12: =SUM(W12:Y12) -> 0 | F12: =F11+D12-E12 -> 25000 | G12: =IFERROR(VLOOKUP($C12,'MEMBERS LIST'!$D$5:$AT$28,32,0),0) -> 200 | H12: =IFERROR(VLOOKUP($C12,'MONTHLY DUES 2023'!$C$5:$D$23,2,0),0) -> 0 | I12: =IFERROR(VLOOKUP($C12,'MONTHLY DUES 2024'!$C$5:$D$25,2,0),0) -> 0 | J12: =IFERROR(VLOOKUP($C12,'MONTHLY DUES 2025'!$C$5:$D$26,2,0),0) -> 0 | K12: =IFERROR(VLOOKUP($C12,'MONTHLY DUES 2026'!$C$5:$D$23,2,0),0) -> 900 | M12: =IFERROR(VLOOKUP($C12,'SPECIAL LEVY'!$C$4:$N$27,3,0),0) -> 0 | N12: =IFERROR(VLOOKUP($C12,'SPECIAL LEVY'!$C$4:$N$27,4,0),0) -> 0 | O12: =IFERROR(VLOOKUP($C12,'SPECIAL LEVY'!$C$4:$N$27,5,0),0) -> 0 | P12: =IFERROR(VLOOKUP($C12,'SPECIAL LEVY'!$C$4:$N$27,6,0),0) -> 0 | Q12: =IFERROR(VLOOKUP($C12,'SPECIAL LEVY'!$C$4:$N$27,7,0),0) -> 0 | R12: =IFERROR(VLOOKUP($C12,'SPECIAL LEVY'!$C$4:$J$27,8,0),0) -> 0
B13: 9 | C13: John Darbo | D13: =SUM(G13:V13) -> 650 | E13: =SUM(W13:Y13) -> 0 | F13: =F12+D13-E13 -> 25650 | G13: =IFERROR(VLOOKUP($C13,'MEMBERS LIST'!$D$5:$AT$28,32,0),0) -> 200 | H13: =IFERROR(VLOOKUP($C13,'MONTHLY DUES 2023'!$C$5:$D$23,2,0),0) -> 0 | I13: =IFERROR(VLOOKUP($C13,'MONTHLY DUES 2024'!$C$5:$D$25,2,0),0) -> 0 | J13: =IFERROR(VLOOKUP($C13,'MONTHLY DUES 2025'!$C$5:$D$26,2,0),0) -> 350 | K13: =IFERROR(VLOOKUP($C13,'MONTHLY DUES 2026'!$C$5:$D$23,2,0),0) -> 0 | M13: =IFERROR(VLOOKUP($C13,'SPECIAL LEVY'!$C$4:$N$27,3,0),0) -> 0 | N13: =IFERROR(VLOOKUP($C13,'SPECIAL LEVY'!$C$4:$N$27,4,0),0) -> 0 | O13: =IFERROR(VLOOKUP($C13,'SPECIAL LEVY'!$C$4:$N$27,5,0),0) -> 0 | P13: =IFERROR(VLOOKUP($C13,'SPECIAL LEVY'!$C$4:$N$27,6,0),0) -> 0 | Q13: =IFERROR(VLOOKUP($C13,'SPECIAL LEVY'!$C$4:$N$27,7,0),0) -> 0 | R13: =IFERROR(VLOOKUP($C13,'SPECIAL LEVY'!$C$4:$J$27,8,0),0) -> 100
B14: 10 | C14: John Ofosuhene Asare | D14: =SUM(G14:V14) -> 4400 | E14: =SUM(W14:Y14) -> 0 | F14: =F13+D14-E14 -> 30050 | G14: =IFERROR(VLOOKUP($C14,'MEMBERS LIST'!$D$5:$AT$28,32,0),0) -> 200 | H14: =IFERROR(VLOOKUP($C14,'MONTHLY DUES 2023'!$C$5:$D$23,2,0),0) -> 600 | I14: =IFERROR(VLOOKUP($C14,'MONTHLY DUES 2024'!$C$5:$D$25,2,0),0) -> 900 | J14: =IFERROR(VLOOKUP($C14,'MONTHLY DUES 2025'!$C$5:$D$26,2,0),0) -> 1200 | K14: =IFERROR(VLOOKUP($C14,'MONTHLY DUES 2026'!$C$5:$D$23,2,0),0) -> 700 | M14: =IFERROR(VLOOKUP($C14,'SPECIAL LEVY'!$C$4:$N$27,3,0),0) -> 200 | N14: =IFERROR(VLOOKUP($C14,'SPECIAL LEVY'!$C$4:$N$27,4,0),0) -> 100 | O14: =IFERROR(VLOOKUP($C14,'SPECIAL LEVY'!$C$4:$N$27,5,0),0) -> 200 | P14: =IFERROR(VLOOKUP($C14,'SPECIAL LEVY'!$C$4:$N$27,6,0),0) -> 0 | Q14: =IFERROR(VLOOKUP($C14,'SPECIAL LEVY'!$C$4:$N$27,7,0),0) -> 200 | R14: =IFERROR(VLOOKUP($C14,'SPECIAL LEVY'!$C$4:$J$27,8,0),0) -> 100
B15: 11 | C15: Johnson Wood | D15: =SUM(G15:V15) -> 4700 | E15: =SUM(W15:Y15) -> 0 | F15: =F14+D15-E15 -> 34750 | G15: =IFERROR(VLOOKUP($C15,'MEMBERS LIST'!$D$5:$AT$28,32,0),0) -> 200 | H15: =IFERROR(VLOOKUP($C15,'MONTHLY DUES 2023'!$C$5:$D$23,2,0),0) -> 600 | I15: =IFERROR(VLOOKUP($C15,'MONTHLY DUES 2024'!$C$5:$D$25,2,0),0) -> 900 | J15: =IFERROR(VLOOKUP($C15,'MONTHLY DUES 2025'!$C$5:$D$26,2,0),0) -> 1200 | K15: =IFERROR(VLOOKUP($C15,'MONTHLY DUES 2026'!$C$5:$D$23,2,0),0) -> 800 | M15: =IFERROR(VLOOKUP($C15,'SPECIAL LEVY'!$C$4:$N$27,3,0),0) -> 200 | N15: =IFERROR(VLOOKUP($C15,'SPECIAL LEVY'!$C$4:$N$27,4,0),0) -> 100 | O15: =IFERROR(VLOOKUP($C15,'SPECIAL LEVY'!$C$4:$N$27,5,0),0) -> 200 | P15: =IFERROR(VLOOKUP($C15,'SPECIAL LEVY'!$C$4:$N$27,6,0),0) -> 200 | Q15: =IFERROR(VLOOKUP($C15,'SPECIAL LEVY'!$C$4:$N$27,7,0),0) -> 200 | R15: =IFERROR(VLOOKUP($C15,'SPECIAL LEVY'!$C$4:$J$27,8,0),0) -> 100
B16: 12 | C16: Jonas Wereko | D16: =SUM(G16:V16) -> 4800 | E16: =SUM(W16:Y16) -> 0 | F16: =F15+D16-E16 -> 39550 | G16: =IFERROR(VLOOKUP($C16,'MEMBERS LIST'!$D$5:$AT$28,32,0),0) -> 200 | H16: =IFERROR(VLOOKUP($C16,'MONTHLY DUES 2023'!$C$5:$D$23,2,0),0) -> 600 | I16: =IFERROR(VLOOKUP($C16,'MONTHLY DUES 2024'!$C$5:$D$25,2,0),0) -> 900 | J16: =IFERROR(VLOOKUP($C16,'MONTHLY DUES 2025'!$C$5:$D$26,2,0),0) -> 1200 | K16: =IFERROR(VLOOKUP($C16,'MONTHLY DUES 2026'!$C$5:$D$23,2,0),0) -> 900 | M16: =IFERROR(VLOOKUP($C16,'SPECIAL LEVY'!$C$4:$N$27,3,0),0) -> 200 | N16: =IFERROR(VLOOKUP($C16,'SPECIAL LEVY'!$C$4:$N$27,4,0),0) -> 100 | O16: =IFERROR(VLOOKUP($C16,'SPECIAL LEVY'!$C$4:$N$27,5,0),0) -> 200 | P16: =IFERROR(VLOOKUP($C16,'SPECIAL LEVY'!$C$4:$N$27,6,0),0) -> 200 | Q16: =IFERROR(VLOOKUP($C16,'SPECIAL LEVY'!$C$4:$N$27,7,0),0) -> 200 | R16: =IFERROR(VLOOKUP($C16,'SPECIAL LEVY'!$C$4:$J$27,8,0),0) -> 100
B17: 13 | C17: Jonathan Danso Siaw | D17: =SUM(G17:V17) -> 6900 | E17: =SUM(W17:Y17) -> 0 | F17: =F16+D17-E17 -> 46450 | G17: =IFERROR(VLOOKUP($C17,'MEMBERS LIST'!$D$5:$AT$28,32,0),0) -> 200 | H17: =IFERROR(VLOOKUP($C17,'MONTHLY DUES 2023'!$C$5:$D$23,2,0),0) -> 600 | I17: =IFERROR(VLOOKUP($C17,'MONTHLY DUES 2024'!$C$5:$D$25,2,0),0) -> 900 | J17: =IFERROR(VLOOKUP($C17,'MONTHLY DUES 2025'!$C$5:$D$26,2,0),0) -> 1200 | K17: =IFERROR(VLOOKUP($C17,'MONTHLY DUES 2026'!$C$5:$D$23,2,0),0) -> 1200 | M17: =IFERROR(VLOOKUP($C17,'SPECIAL LEVY'!$C$4:$N$27,3,0),0) -> 200 | N17: =IFERROR(VLOOKUP($C17,'SPECIAL LEVY'!$C$4:$N$27,4,0),0) -> 100 | O17: =IFERROR(VLOOKUP($C17,'SPECIAL LEVY'!$C$4:$N$27,5,0),0) -> 200 | P17: =IFERROR(VLOOKUP($C17,'SPECIAL LEVY'!$C$4:$N$27,6,0),0) -> 200 | Q17: =IFERROR(VLOOKUP($C17,'SPECIAL LEVY'!$C$4:$N$27,7,0),0) -> 0 | R17: =IFERROR(VLOOKUP($C17,'SPECIAL LEVY'!$C$4:$J$27,8,0),0) -> 100 | V17: 2000
B18: 14 | C18: Joseph Kofi Amanfo | D18: =SUM(G18:V18) -> 2200 | E18: =SUM(W18:Y18) -> 0 | F18: =F17+D18-E18 -> 48650 | G18: =IFERROR(VLOOKUP($C18,'MEMBERS LIST'!$D$5:$AT$28,32,0),0) -> 200 | H18: =IFERROR(VLOOKUP($C18,'MONTHLY DUES 2023'!$C$5:$D$23,2,0),0) -> 600 | I18: =IFERROR(VLOOKUP($C18,'MONTHLY DUES 2024'!$C$5:$D$25,2,0),0) -> 400 | J18: =IFERROR(VLOOKUP($C18,'MONTHLY DUES 2025'!$C$5:$D$26,2,0),0) -> 0 | K18: =IFERROR(VLOOKUP($C18,'MONTHLY DUES 2026'!$C$5:$D$23,2,0),0) -> 0 | M18: =IFERROR(VLOOKUP($C18,'SPECIAL LEVY'!$C$4:$N$27,3,0),0) -> 200 | N18: =IFERROR(VLOOKUP($C18,'SPECIAL LEVY'!$C$4:$N$27,4,0),0) -> 100 | O18: =IFERROR(VLOOKUP($C18,'SPECIAL LEVY'!$C$4:$N$27,5,0),0) -> 200 | P18: =IFERROR(VLOOKUP($C18,'SPECIAL LEVY'!$C$4:$N$27,6,0),0) -> 200 | Q18: =IFERROR(VLOOKUP($C18,'SPECIAL LEVY'!$C$4:$N$27,7,0),0) -> 200 | R18: =IFERROR(VLOOKUP($C18,'SPECIAL LEVY'!$C$4:$J$27,8,0),0) -> 100
B19: 15 | C19: Justice Kojo Acheampong | D19: =SUM(G19:V19) -> 4200 | E19: =SUM(W19:Y19) -> 0 | F19: =F18+D19-E19 -> 52850 | G19: =IFERROR(VLOOKUP($C19,'MEMBERS LIST'!$D$5:$AT$28,32,0),0) -> 200 | H19: =IFERROR(VLOOKUP($C19,'MONTHLY DUES 2023'!$C$5:$D$23,2,0),0) -> 600 | I19: =IFERROR(VLOOKUP($C19,'MONTHLY DUES 2024'!$C$5:$D$25,2,0),0) -> 900 | J19: =IFERROR(VLOOKUP($C19,'MONTHLY DUES 2025'!$C$5:$D$26,2,0),0) -> 1200 | K19: =IFERROR(VLOOKUP($C19,'MONTHLY DUES 2026'!$C$5:$D$23,2,0),0) -> 300 | M19: =IFERROR(VLOOKUP($C19,'SPECIAL LEVY'!$C$4:$N$27,3,0),0) -> 200 | N19: =IFERROR(VLOOKUP($C19,'SPECIAL LEVY'!$C$4:$N$27,4,0),0) -> 100 | O19: =IFERROR(VLOOKUP($C19,'SPECIAL LEVY'!$C$4:$N$27,5,0),0) -> 200 | P19: =IFERROR(VLOOKUP($C19,'SPECIAL LEVY'!$C$4:$N$27,6,0),0) -> 200 | Q19: =IFERROR(VLOOKUP($C19,'SPECIAL LEVY'!$C$4:$N$27,7,0),0) -> 200 | R19: =IFERROR(VLOOKUP($C19,'SPECIAL LEVY'!$C$4:$J$27,8,0),0) -> 100
B20: 16 | C20: Just-Mark Kwabena Quansah | D20: =SUM(G20:V20) -> 4200 | E20: =SUM(W20:Y20) -> 0 | F20: =F19+D20-E20 -> 57050 | G20: =IFERROR(VLOOKUP($C20,'MEMBERS LIST'!$D$5:$AT$28,32,0),0) -> 200 | H20: =IFERROR(VLOOKUP($C20,'MONTHLY DUES 2023'!$C$5:$D$23,2,0),0) -> 600 | I20: =IFERROR(VLOOKUP($C20,'MONTHLY DUES 2024'!$C$5:$D$25,2,0),0) -> 900 | J20: =IFERROR(VLOOKUP($C20,'MONTHLY DUES 2025'!$C$5:$D$26,2,0),0) -> 1200 | K20: =IFERROR(VLOOKUP($C20,'MONTHLY DUES 2026'!$C$5:$D$23,2,0),0) -> 300 | M20: =IFERROR(VLOOKUP($C20,'SPECIAL LEVY'!$C$4:$N$27,3,0),0) -> 200 | N20: =IFERROR(VLOOKUP($C20,'SPECIAL LEVY'!$C$4:$N$27,4,0),0) -> 100 | O20: =IFERROR(VLOOKUP($C20,'SPECIAL LEVY'!$C$4:$N$27,5,0),0) -> 200 | P20: =IFERROR(VLOOKUP($C20,'SPECIAL LEVY'!$C$4:$N$27,6,0),0) -> 200 | Q20: =IFERROR(VLOOKUP($C20,'SPECIAL LEVY'!$C$4:$N$27,7,0),0) -> 200 | R20: =IFERROR(VLOOKUP($C20,'SPECIAL LEVY'!$C$4:$J$27,8,0),0) -> 100
B21: 17 | C21: Maxwell Ofei Siaw | D21: =SUM(G21:V21) -> 4900 | E21: =SUM(W21:Y21) -> 0 | F21: =F20+D21-E21 -> 61950 | G21: =IFERROR(VLOOKUP($C21,'MEMBERS LIST'!$D$5:$AT$28,32,0),0) -> 200 | H21: =IFERROR(VLOOKUP($C21,'MONTHLY DUES 2023'!$C$5:$D$23,2,0),0) -> 600 | I21: =IFERROR(VLOOKUP($C21,'MONTHLY DUES 2024'!$C$5:$D$25,2,0),0) -> 900 | J21: =IFERROR(VLOOKUP($C21,'MONTHLY DUES 2025'!$C$5:$D$26,2,0),0) -> 1200 | K21: =IFERROR(VLOOKUP($C21,'MONTHLY DUES 2026'!$C$5:$D$23,2,0),0) -> 1000 | M21: =IFERROR(VLOOKUP($C21,'SPECIAL LEVY'!$C$4:$N$27,3,0),0) -> 200 | N21: =IFERROR(VLOOKUP($C21,'SPECIAL LEVY'!$C$4:$N$27,4,0),0) -> 100 | O21: =IFERROR(VLOOKUP($C21,'SPECIAL LEVY'!$C$4:$N$27,5,0),0) -> 200 | P21: =IFERROR(VLOOKUP($C21,'SPECIAL LEVY'!$C$4:$N$27,6,0),0) -> 200 | Q21: =IFERROR(VLOOKUP($C21,'SPECIAL LEVY'!$C$4:$N$27,7,0),0) -> 200 | R21: =IFERROR(VLOOKUP($C21,'SPECIAL LEVY'!$C$4:$J$27,8,0),0) -> 100
B22: 18 | C22: Moses Oduro | D22: =SUM(G22:V22) -> 5100 | E22: =SUM(W22:Y22) -> 0 | F22: =F21+D22-E22 -> 67050 | G22: =IFERROR(VLOOKUP($C22,'MEMBERS LIST'!$D$5:$AT$28,32,0),0) -> 200 | H22: =IFERROR(VLOOKUP($C22,'MONTHLY DUES 2023'!$C$5:$D$23,2,0),0) -> 600 | I22: =IFERROR(VLOOKUP($C22,'MONTHLY DUES 2024'!$C$5:$D$25,2,0),0) -> 900 | J22: =IFERROR(VLOOKUP($C22,'MONTHLY DUES 2025'!$C$5:$D$26,2,0),0) -> 1200 | K22: =IFERROR(VLOOKUP($C22,'MONTHLY DUES 2026'!$C$5:$D$23,2,0),0) -> 1200 | M22: =IFERROR(VLOOKUP($C22,'SPECIAL LEVY'!$C$4:$N$27,3,0),0) -> 200 | N22: =IFERROR(VLOOKUP($C22,'SPECIAL LEVY'!$C$4:$N$27,4,0),0) -> 100 | O22: =IFERROR(VLOOKUP($C22,'SPECIAL LEVY'!$C$4:$N$27,5,0),0) -> 200 | P22: =IFERROR(VLOOKUP($C22,'SPECIAL LEVY'!$C$4:$N$27,6,0),0) -> 200 | Q22: =IFERROR(VLOOKUP($C22,'SPECIAL LEVY'!$C$4:$N$27,7,0),0) -> 200 | R22: =IFERROR(VLOOKUP($C22,'SPECIAL LEVY'!$C$4:$J$27,8,0),0) -> 100
B23: 19 | C23: Osei Kwame | D23: =SUM(G23:V23) -> 6700 | E23: =SUM(W23:Y23) -> 0 | F23: =F22+D23-E23 -> 73750 | G23: =IFERROR(VLOOKUP($C23,'MEMBERS LIST'!$D$5:$AT$28,32,0),0) -> 200 | H23: =IFERROR(VLOOKUP($C23,'MONTHLY DUES 2023'!$C$5:$D$23,2,0),0) -> 600 | I23: =IFERROR(VLOOKUP($C23,'MONTHLY DUES 2024'!$C$5:$D$25,2,0),0) -> 900 | J23: =IFERROR(VLOOKUP($C23,'MONTHLY DUES 2025'!$C$5:$D$26,2,0),0) -> 1200 | K23: =IFERROR(VLOOKUP($C23,'MONTHLY DUES 2026'!$C$5:$D$23,2,0),0) -> 800 | M23: =IFERROR(VLOOKUP($C23,'SPECIAL LEVY'!$C$4:$N$27,3,0),0) -> 200 | N23: =IFERROR(VLOOKUP($C23,'SPECIAL LEVY'!$C$4:$N$27,4,0),0) -> 100 | O23: =IFERROR(VLOOKUP($C23,'SPECIAL LEVY'!$C$4:$N$27,5,0),0) -> 200 | P23: =IFERROR(VLOOKUP($C23,'SPECIAL LEVY'!$C$4:$N$27,6,0),0) -> 200 | Q23: =IFERROR(VLOOKUP($C23,'SPECIAL LEVY'!$C$4:$N$27,7,0),0) -> 200 | R23: =IFERROR(VLOOKUP($C23,'SPECIAL LEVY'!$C$4:$J$27,8,0),0) -> 100 | V23: 2000
B24: 20 | C24: Peter Kingsford Nkrumah | D24: =SUM(G24:V24) -> 2100 | E24: =SUM(W24:Y24) -> 0 | F24: =F23+D24-E24 -> 75850 | G24: =IFERROR(VLOOKUP($C24,'MEMBERS LIST'!$D$5:$AT$28,32,0),0) -> 200 | H24: =IFERROR(VLOOKUP($C24,'MONTHLY DUES 2023'!$C$5:$D$23,2,0),0) -> 600 | I24: =IFERROR(VLOOKUP($C24,'MONTHLY DUES 2024'!$C$5:$D$25,2,0),0) -> 300 | J24: =IFERROR(VLOOKUP($C24,'MONTHLY DUES 2025'!$C$5:$D$26,2,0),0) -> 0 | K24: =IFERROR(VLOOKUP($C24,'MONTHLY DUES 2026'!$C$5:$D$23,2,0),0) -> 0 | M24: =IFERROR(VLOOKUP($C24,'SPECIAL LEVY'!$C$4:$N$27,3,0),0) -> 200 | N24: =IFERROR(VLOOKUP($C24,'SPECIAL LEVY'!$C$4:$N$27,4,0),0) -> 100 | O24: =IFERROR(VLOOKUP($C24,'SPECIAL LEVY'!$C$4:$N$27,5,0),0) -> 200 | P24: =IFERROR(VLOOKUP($C24,'SPECIAL LEVY'!$C$4:$N$27,6,0),0) -> 200 | Q24: =IFERROR(VLOOKUP($C24,'SPECIAL LEVY'!$C$4:$N$27,7,0),0) -> 200 | R24: =IFERROR(VLOOKUP($C24,'SPECIAL LEVY'!$C$4:$J$27,8,0),0) -> 100
B25: 21 | C25: Prince Asante Ahwireng | D25: =SUM(G25:V25) -> 4400 | E25: =SUM(W25:Y25) -> 0 | F25: =F24+D25-E25 -> 80250 | G25: =IFERROR(VLOOKUP($C25,'MEMBERS LIST'!$D$5:$AT$28,32,0),0) -> 200 | H25: =IFERROR(VLOOKUP($C25,'MONTHLY DUES 2023'!$C$5:$D$23,2,0),0) -> 600 | I25: =IFERROR(VLOOKUP($C25,'MONTHLY DUES 2024'!$C$5:$D$25,2,0),0) -> 900 | J25: =IFERROR(VLOOKUP($C25,'MONTHLY DUES 2025'!$C$5:$D$26,2,0),0) -> 1200 | K25: =IFERROR(VLOOKUP($C25,'MONTHLY DUES 2026'!$C$5:$D$23,2,0),0) -> 600 | M25: =IFERROR(VLOOKUP($C25,'SPECIAL LEVY'!$C$4:$N$27,3,0),0) -> 200 | N25: =IFERROR(VLOOKUP($C25,'SPECIAL LEVY'!$C$4:$N$27,4,0),0) -> 100 | O25: =IFERROR(VLOOKUP($C25,'SPECIAL LEVY'!$C$4:$N$27,5,0),0) -> 200 | P25: =IFERROR(VLOOKUP($C25,'SPECIAL LEVY'!$C$4:$N$27,6,0),0) -> 200 | Q25: =IFERROR(VLOOKUP($C25,'SPECIAL LEVY'!$C$4:$N$27,7,0),0) -> 200 | R25: =IFERROR(VLOOKUP($C25,'SPECIAL LEVY'!$C$4:$J$27,8,0),0) -> 0
B26: 22 | C26: Samuel Yaw Nkansah | D26: =SUM(G26:V26) -> 2600 | E26: =SUM(W26:Y26) -> 0 | F26: =F25+D26-E26 -> 82850 | G26: =IFERROR(VLOOKUP($C26,'MEMBERS LIST'!$D$5:$AT$28,32,0),0) -> 200 | H26: =IFERROR(VLOOKUP($C26,'MONTHLY DUES 2023'!$C$5:$D$23,2,0),0) -> 600 | I26: =IFERROR(VLOOKUP($C26,'MONTHLY DUES 2024'!$C$5:$D$25,2,0),0) -> 900 | J26: =IFERROR(VLOOKUP($C26,'MONTHLY DUES 2025'!$C$5:$D$26,2,0),0) -> 200 | K26: =IFERROR(VLOOKUP($C26,'MONTHLY DUES 2026'!$C$5:$D$23,2,0),0) -> 0 | M26: =IFERROR(VLOOKUP($C26,'SPECIAL LEVY'!$C$4:$N$27,3,0),0) -> 200 | N26: =IFERROR(VLOOKUP($C26,'SPECIAL LEVY'!$C$4:$N$27,4,0),0) -> 0 | O26: =IFERROR(VLOOKUP($C26,'SPECIAL LEVY'!$C$4:$N$27,5,0),0) -> 0 | P26: =IFERROR(VLOOKUP($C26,'SPECIAL LEVY'!$C$4:$N$27,6,0),0) -> 200 | Q26: =IFERROR(VLOOKUP($C26,'SPECIAL LEVY'!$C$4:$N$27,7,0),0) -> 200 | R26: =IFERROR(VLOOKUP($C26,'SPECIAL LEVY'!$C$4:$J$27,8,0),0) -> 100
B27: 23 | C27: Vincent Agamatey | D27: =SUM(G27:V27) -> 4900 | E27: =SUM(W27:Y27) -> 0 | F27: =F26+D27-E27 -> 87750 | G27: =IFERROR(VLOOKUP($C27,'MEMBERS LIST'!$D$5:$AT$28,32,0),0) -> 200 | H27: =IFERROR(VLOOKUP($C27,'MONTHLY DUES 2023'!$C$5:$D$23,2,0),0) -> 600 | I27: =IFERROR(VLOOKUP($C27,'MONTHLY DUES 2024'!$C$5:$D$25,2,0),0) -> 900 | J27: =IFERROR(VLOOKUP($C27,'MONTHLY DUES 2025'!$C$5:$D$26,2,0),0) -> 1200 | K27: =IFERROR(VLOOKUP($C27,'MONTHLY DUES 2026'!$C$5:$D$23,2,0),0) -> 1000 | M27: =IFERROR(VLOOKUP($C27,'SPECIAL LEVY'!$C$4:$N$27,3,0),0) -> 200 | N27: =IFERROR(VLOOKUP($C27,'SPECIAL LEVY'!$C$4:$N$27,4,0),0) -> 100 | O27: =IFERROR(VLOOKUP($C27,'SPECIAL LEVY'!$C$4:$N$27,5,0),0) -> 200 | P27: =IFERROR(VLOOKUP($C27,'SPECIAL LEVY'!$C$4:$N$27,6,0),0) -> 200 | Q27: =IFERROR(VLOOKUP($C27,'SPECIAL LEVY'!$C$4:$N$27,7,0),0) -> 200 | R27: =IFERROR(VLOOKUP($C27,'SPECIAL LEVY'!$C$4:$J$27,8,0),0) -> 100
B28: 24 | C28: William Kojo Anane | D28: =SUM(G28:V28) -> 5100 | E28: =SUM(W28:Y28) -> 0 | F28: =F27+D28-E28 -> 92850 | G28: =IFERROR(VLOOKUP($C28,'MEMBERS LIST'!$D$5:$AT$28,32,0),0) -> 200 | H28: =IFERROR(VLOOKUP($C28,'MONTHLY DUES 2023'!$C$5:$D$23,2,0),0) -> 600 | I28: =IFERROR(VLOOKUP($C28,'MONTHLY DUES 2024'!$C$5:$D$25,2,0),0) -> 900 | J28: =IFERROR(VLOOKUP($C28,'MONTHLY DUES 2025'!$C$5:$D$26,2,0),0) -> 1200 | K28: =IFERROR(VLOOKUP($C28,'MONTHLY DUES 2026'!$C$5:$D$23,2,0),0) -> 1200 | M28: =IFERROR(VLOOKUP($C28,'SPECIAL LEVY'!$C$4:$N$27,3,0),0) -> 200 | N28: =IFERROR(VLOOKUP($C28,'SPECIAL LEVY'!$C$4:$N$27,4,0),0) -> 100 | O28: =IFERROR(VLOOKUP($C28,'SPECIAL LEVY'!$C$4:$N$27,5,0),0) -> 200 | P28: =IFERROR(VLOOKUP($C28,'SPECIAL LEVY'!$C$4:$N$27,6,0),0) -> 200 | Q28: =IFERROR(VLOOKUP($C28,'SPECIAL LEVY'!$C$4:$N$27,7,0),0) -> 200 | R28: =IFERROR(VLOOKUP($C28,'SPECIAL LEVY'!$C$4:$J$27,8,0),0) -> 100
C29: Levy Balance | D29: =SUM(G29:V29) -> 1250.5 | E29: =SUM(W29:Y29) -> 0 | F29: =F28+D29-E29 -> 94100.5 | U29: ='LEVY ACCOUNT'!F24 -> 1250.5
B30: 45066 | C30: Momo sent to Dues Payment Voucher Number 1. | D30: =SUM(G30:V30) -> 0 | E30: =SUM(W30:Y30) -> 5813 | F30: =F29+D30-E30 -> 88287.5 | Q30: =IFERROR(VLOOKUP($C30,'SPECIAL LEVY'!$C$4:$N$27,7,0),0) -> 0 | W30: ='PAYMENT VOUCHERS'!E14 -> 5813
B31: 45157 | C31: Momo sent to Levy Payment Voucher Number 1. | E31: =SUM(X31:Y31) -> 3400 | F31: =F30+D31-E31 -> 84887.5 | X31: ='LEVY DISBURSMENT'!D5 -> 3400
B32: 45158 | C32: Momo sent to Payment Voucher Number 2. | D32: =SUM(G32:V32) -> 0 | E32: =SUM(X32:Y32) -> 400 | F32: =F31+D32-E32 -> 84487.5 | Q32: =IFERROR(VLOOKUP($C32,'SPECIAL LEVY'!$C$4:$N$27,7,0),0) -> 0 | X32: ='PAYMENT VOUCHERS'!E20 -> 400
B33: 45205 | C33: Momo sent to Payment Voucher Number 3. | D33: =SUM(G33:V33) -> 0 | E33: =SUM(W33:Y33) -> 1734 | F33: =F32+D33-E33 -> 82753.5 | K33: =IFERROR(VLOOKUP($C33,'[1]MONTHLY DUES 2026'!$C$7:$D$30,2,0),0) -> 0 | Q33: =IFERROR(VLOOKUP($C33,'SPECIAL LEVY'!$C$4:$N$27,7,0),0) -> 0 | W33: ='PAYMENT VOUCHERS'!E32 -> 1734
B34: 45268 | C34: Momo sent to Levy Payment Voucher Number 2. | D34: =SUM(G34:V34) -> 0 | E34: =SUM(W34:Y34) -> 1700 | F34: =F33+D34-E34 -> 81053.5 | X34: ='LEVY DISBURSMENT'!D17 -> 1700
B35: 45657 | C35: Intrest on MoMo | D35: =SUM(G35:V35) -> 151.33 | E35: =SUM(W35:Y35) -> 0 | F35: =F34+D35-E35 -> 81204.83 | Q35: =IFERROR(VLOOKUP($C35,'SPECIAL LEVY'!$C$4:$N$27,7,0),0) -> 0 | S35: 151.33
B36: 45349 | C36: Momo sent to Payment Voucher Number 4. | D36: =SUM(G36:V36) -> 0 | E36: =SUM(W36:Y36) -> 153 | F36: =F35+D36-E36 -> 81051.83 | Q36: =IFERROR(VLOOKUP($C36,'SPECIAL LEVY'!$C$4:$N$27,7,0),0) -> 0 | W36: ='PAYMENT VOUCHERS'!E40 -> 153
B37: 45349 | C37: From Tema Bank to MoMo | D37: =SUM(G37:V37) -> 5400 | E37: =SUM(W37:Y37) -> 0 | F37: =F36+D37-E37 -> 86451.83 | K37: =IFERROR(VLOOKUP($C37,'[1]MONTHLY DUES 2026'!$C$7:$D$30,2,0),0) -> 0 | Q37: =IFERROR(VLOOKUP($C37,'SPECIAL LEVY'!$C$4:$N$27,7,0),0) -> 0 | U37: ='BANK ACCOUNT TEMA'!G7 -> 5400
B38: 45398 | C38: Momo sent to Payment Voucher Number 5. | D38: =SUM(G38:V38) -> 0 | E38: =SUM(W38:Y38) -> 1581 | F38: =F37+D38-E38 -> 84870.83 | K38: =IFERROR(VLOOKUP($C38,'[1]MONTHLY DUES 2026'!$C$7:$D$30,2,0),0) -> 0 | Q38: =IFERROR(VLOOKUP($C38,'SPECIAL LEVY'!$C$4:$N$27,7,0),0) -> 0 | W38: ='PAYMENT VOUCHERS'!E55 -> 1581
B39: 45420 | C39: Momo sent to Payment Voucher Number 6. | D39: =SUM(G39:V39) -> 0 | E39: =SUM(W39:Y39) -> 16610.7 | F39: =F38+D39-E39 -> 68260.13 | K39: =IFERROR(VLOOKUP($C39,'[1]MONTHLY DUES 2026'!$C$7:$D$30,2,0),0) -> 0 | Q39: =IFERROR(VLOOKUP($C39,'SPECIAL LEVY'!$C$4:$N$27,7,0),0) -> 0 | W39: ='PAYMENT VOUCHERS'!E74 -> 16610.7
B40: 45467 | C40: Momo sent to Payment Voucher Number 7. | D40: =SUM(G40:V40) -> 0 | E40: =SUM(W40:Y40) -> 2652 | F40: =F39+D40-E40 -> 65608.13 | K40: =IFERROR(VLOOKUP($C40,'[1]MONTHLY DUES 2026'!$C$7:$D$30,2,0),0) -> 0 | Q40: =IFERROR(VLOOKUP($C40,'SPECIAL LEVY'!$C$4:$N$27,7,0),0) -> 0 | W40: ='PAYMENT VOUCHERS'!E82 -> 2652
B41: 45464 | C41: Momo sent to Payment Voucher Number 8. | D41: =SUM(G41:V41) -> 0 | E41: =SUM(W41:Y41) -> 3672 | F41: =F40+D41-E41 -> 61936.13 | K41: =IFERROR(VLOOKUP($C41,'[1]MONTHLY DUES 2026'!$C$7:$D$30,2,0),0) -> 0 | Q41: =IFERROR(VLOOKUP($C41,'SPECIAL LEVY'!$C$4:$N$27,7,0),0) -> 0 | W41: ='PAYMENT VOUCHERS'!E90 -> 3672
B42: 45594 | C42: Momo sent to Levy Payment Voucher Number 3. | D42: =SUM(G42:V42) -> 0 | E42: =SUM(W42:Y42) -> 3600 | F42: =F41+D42-E42 -> 58336.13 | X42: ='LEVY DISBURSMENT'!D28 -> 3600
B43: 45615 | C43: Momo sent to Levy Payment Voucher Number 4. | D43: =SUM(G43:V43) -> 0 | E43: =SUM(W43:Y43) -> 3600 | F43: =F42+D43-E43 -> 54736.13 | X43: ='LEVY DISBURSMENT'!D39 -> 3600
B44: 45647 | C44: Momo sent to Levy Payment Voucher Number 5. | D44: =SUM(G44:V44) -> 0 | E44: =SUM(W44:Y44) -> 3600 | F44: =F43+D44-E44 -> 51136.13 | X44: ='LEVY DISBURSMENT'!D50 -> 3600
B45: 45665 | C45: Momo sent to Payment Voucher Number 9. | D45: =SUM(G45:V45) -> 0 | E45: =SUM(W45:Y45) -> 3837 | F45: =F44+D45-E45 -> 47299.13 | K45: =IFERROR(VLOOKUP($C45,'[1]MONTHLY DUES 2026'!$C$7:$D$30,2,0),0) -> 0 | Q45: =IFERROR(VLOOKUP($C45,'SPECIAL LEVY'!$C$4:$N$27,7,0),0) -> 0 | W45: ='PAYMENT VOUCHERS'!E101 -> 3837
B46: 45691 | C46: Momo sent to Payment Voucher Number 10. | D46: =SUM(G46:V46) -> 0 | E46: =SUM(W46:Y46) -> 1717 | F46: =F45+D46-E46 -> 45582.13 | K46: =IFERROR(VLOOKUP($C46,'[1]MONTHLY DUES 2026'!$C$7:$D$30,2,0),0) -> 0 | Q46: =IFERROR(VLOOKUP($C46,'SPECIAL LEVY'!$C$4:$N$27,7,0),0) -> 0 | W46: ='PAYMENT VOUCHERS'!E110 -> 1717
B47: 45751 | C47: Momo sent to Payment Voucher Number 11. | D47: =SUM(G47:V47) -> 0 | E47: =SUM(W47:Y47) -> 4141 | F47: =F46+D47-E47 -> 41441.13 | K47: =IFERROR(VLOOKUP($C47,'[1]MONTHLY DUES 2026'!$C$7:$D$30,2,0),0) -> 0 | Q47: =IFERROR(VLOOKUP($C47,'SPECIAL LEVY'!$C$4:$N$27,7,0),0) -> 0 | W47: ='PAYMENT VOUCHERS'!E118 -> 4141
B48: 45799 | C48: Momo sent to Payment Voucher Number 12. | D48: =SUM(G48:V48) -> 0 | E48: =SUM(W48:Y48) -> 3039.1 | F48: =F47+D48-E48 -> 38402.03 | K48: =IFERROR(VLOOKUP($C48,'[1]MONTHLY DUES 2026'!$C$7:$D$30,2,0),0) -> 0 | Q48: =IFERROR(VLOOKUP($C48,'SPECIAL LEVY'!$C$4:$N$27,7,0),0) -> 0 | W48: ='PAYMENT VOUCHERS'!E129 -> 3039.1
B49: 45806 | C49: Momo sent to Levy Payment Voucher Number 6. | D49: =SUM(G49:V49) -> 0 | E49: =SUM(W49:Y49) -> 2200 | F49: =F48+D49-E49 -> 36202.03 | X49: ='LEVY DISBURSMENT'!D60 -> 2200
B50: 45824 | C50: Momo sent to Payment Voucher Number 13. | D50: =SUM(G50:V50) -> 0 | E50: =SUM(W50:Y50) -> 2434 | F50: =F49+D50-E50 -> 33768.03 | K50: =IFERROR(VLOOKUP($C50,'[1]MONTHLY DUES 2026'!$C$7:$D$30,2,0),0) -> 0 | Q50: =IFERROR(VLOOKUP($C50,'SPECIAL LEVY'!$C$4:$N$27,7,0),0) -> 0 | W50: ='PAYMENT VOUCHERS'!E137 -> 2434
B51: 45875 | C51: Momo sent to Payment Voucher Number 14. | D51: =SUM(G51:V51) -> 0 | E51: =SUM(W51:Y51) -> 2323 | F51: =F50+D51-E51 -> 31445.03 | K51: =IFERROR(VLOOKUP($C51,'[1]MONTHLY DUES 2026'!$C$7:$D$30,2,0),0) -> 0 | Q51: =IFERROR(VLOOKUP($C51,'SPECIAL LEVY'!$C$4:$N$27,7,0),0) -> 0 | W51: ='PAYMENT VOUCHERS'!E145 -> 2323
B52: 45904 | C52: Momo sent to Payment Voucher Number 15. | D52: =SUM(G52:V52) -> 0 | E52: =SUM(W52:Y52) -> 5156 | F52: =F51+D52-E52 -> 26289.03 | K52: =IFERROR(VLOOKUP($C52,'[1]MONTHLY DUES 2026'!$C$7:$D$30,2,0),0) -> 0 | Q52: =IFERROR(VLOOKUP($C52,'SPECIAL LEVY'!$C$4:$N$27,7,0),0) -> 0 | W52: ='PAYMENT VOUCHERS'!E153 -> 5156
B53: 46008 | C53: Momo sent to Payment Voucher Number 16. | D53: =SUM(G53:V53) -> 0 | E53: =SUM(W53:Y53) -> 3737 | F53: =F52+D53-E53 -> 22552.03 | K53: =IFERROR(VLOOKUP($C53,'[1]MONTHLY DUES 2026'!$C$7:$D$30,2,0),0) -> 0 | Q53: =IFERROR(VLOOKUP($C53,'SPECIAL LEVY'!$C$4:$N$27,7,0),0) -> 0 | W53: ='PAYMENT VOUCHERS'!E161 -> 3737
B54: 46041 | C54: Momo sent to Payment Voucher Number 17. | D54: =SUM(G54:V54) -> 0 | E54: =SUM(W54:Y54) -> 3134 | F54: =F53+D54-E54 -> 19418.03 | Q54: =IFERROR(VLOOKUP($C54,'SPECIAL LEVY'!$C$4:$N$27,7,0),0) -> 0 | W54: ='PAYMENT VOUCHERS'!E169 -> 3134
B55: 45824 | C55: From Fidelity Bank | D55: =SUM(G55:V55) -> 400 | E55: =SUM(W55:Y55) -> 0 | F55: =F54+D55-E55 -> 19818.03 | T55: 400
A56: 46086 | B56: 45824 | C56: Momo sent to Payment Voucher Number 18. | D56: =SUM(G56:V56) -> 0 | E56: =SUM(W56:Y56) -> 8945 | F56: =F55+D56-E56 -> 10873.03 | Q56: =IFERROR(VLOOKUP($C56,'SPECIAL LEVY'!$C$4:$N$27,7,0),0) -> 0 | W56: ='PAYMENT VOUCHERS'!E189 -> 8945
B57: 45865 | C57: Intrest on MoMo | D57: =SUM(G57:V57) -> 36.92 | E57: =SUM(W57:Y57) -> 0 | F57: =F56+D57-E57 -> 10909.95 | S57: 36.92
B58: 46129 | C58: Momo sent to Payment Voucher Number 19. | D58: =SUM(G58:V58) -> 0 | E58: =SUM(W58:Y58) -> 4141 | F58: =F57+D58-E58 -> 6768.95 | K58: =IFERROR(VLOOKUP($C58,'[1]MONTHLY DUES 2026'!$C$7:$D$30,2,0),0) -> 0 | Q58: =IFERROR(VLOOKUP($C58,'SPECIAL LEVY'!$C$4:$N$27,7,0),0) -> 0 | W58: ='PAYMENT VOUCHERS'!E197 -> 4141
B59: 46255 | C59: Momo sent to Payment Voucher Number 20. | D59: =SUM(G59:V59) -> 0 | E59: =SUM(W59:Y59) -> 4646 | F59: =F58+D59-E59 -> 2122.95 | W59: ='PAYMENT VOUCHERS'!E205 -> 4646
B60: 46289 | C60: Momo sent to Payment Voucher Number 21. | D60: =SUM(G60:V60) -> 0 | E60: =SUM(W60:Y60) -> 2121 | F60: =F59+D60-E60 -> 1.95 | W60: ='PAYMENT VOUCHERS'!E218 -> 2121
D61: =SUM(G61:V61) -> 0 | E61: =SUM(W61:Y61) -> 0 | F61: =F60+D61-E61 -> 1.95
D62: =SUM(G62:V62) -> 0 | E62: =SUM(W62:Y62) -> 0 | F62: =F61+D62-E62 -> 1.95
D63: =SUM(G63:V63) -> 0 | E63: =SUM(W63:Y63) -> 0 | F63: =F62+D63-E63 -> 1.95
D64: =SUM(G64:V64) -> 0 | E64: =SUM(W64:Y64) -> 0 | F64: =F63+D64-E64 -> 1.95 | K64: =IFERROR(VLOOKUP($C64,'[1]MONTHLY DUES 2026'!$C$7:$D$30,2,0),0) -> 0 | Q64: =IFERROR(VLOOKUP($C64,'SPECIAL LEVY'!$C$4:$N$27,7,0),0) -> 0
Q65: =IFERROR(VLOOKUP($C65,'SPECIAL LEVY'!$C$4:$N$27,7,0),0) -> 0
B66: =SUBTOTAL(3,B5:B65) -> 55 | C66: =SUBTOTAL(3,C5:C65) -> 56 | D66: =SUBTOTAL(9,D5:D65) -> 100088.75 | E66: =SUBTOTAL(9,E5:E65) -> 100086.8 | F66: =D66-E66 -> 1.95 | G66: =SUBTOTAL(9,G5:G65) -> 4800 | H66: =SUBTOTAL(9,H5:H65) -> 10800 | I66: =SUBTOTAL(9,I5:I65) -> 16900 | J66: =SUBTOTAL(9,J5:J65) -> 22350 | K66: =SUBTOTAL(9,K5:K65) -> 15900 | M66: =SUBTOTAL(9,M5:M65) -> 3400 | N66: =SUBTOTAL(9,N5:N65) -> 1700 | O66: =SUBTOTAL(9,O5:O65) -> 3600 | P66: =SUBTOTAL(9,P5:P65) -> 3600 | Q66: =SUBTOTAL(9,Q5:Q65) -> 3600 | R66: =SUBTOTAL(9,R5:R65) -> 2200 | S66: =SUBTOTAL(9,S5:S65) -> 188.25 | T66: =SUBTOTAL(9,T5:T65) -> 400 | ... Y66: =SUBTOTAL(9,Y5:Y65) -> 0

Sheet PAYMENT VOUCHERS
B2: PAYMENT VOUCHERS
B4: PAYMENT VOUCHER NO. 1 - FOR MAY 2023
B6: DATE | C6: NAME | D6: DISCRIPTION | E6: MOMO ACCOUNT | F6: BANK ACCOUNT
B7: 45066 | C7: NORTH TEMA CO-OPERATIVE CREDIT UNION LTD. | D7: Bank Deposit | E7: 5400
B8: 45066 | C8: NORTH TEMA CO-OPERATIVE CREDIT UNION LTD. | D8: Shares | E8: 100
B9: 45066 | C9: MTN | D9: Taxes on MoMo | E9: =5500*2% -> 110
B10: 45066 | C10: ELD. JUST-MARK QUANSAH | D10: T & T Ashaiman Bank & Back | E10: 50
B11: 45073 | C11: NORTH TEMA CO-OPERATIVE CREDIT UNION LTD. | D11: Bank Deposit | E11: 100
B12: 45073 | C12: MTN | D12: Taxes on MoMo | E12: =150*2% -> 3
B13: 45073 | C13: ELD. JUST-MARK QUANSAH | D13: T & T Ashaiman Bank & Back | E13: 50
B14: TOTAL | E14: =SUM(E7:E13) -> 5813 | F14: =SUM(F7:F11) -> 0
B16: PAYMENT VOUCHER NO. 2 - FOR AUGUST 2023
B18: DATE | C18: NAME | D18: DISCRIPTION | E18: MOMO ACCOUNT | F18: BANK ACCOUNT
B19: 45158 | C19: MoMo Transfare to Levy Account | D19: Mother Funeral Contribution | E19: 400
B20: TOTAL | E20: =SUM(E19:E19) -> 400 | F20: =SUM(F19:F19) -> 0
B22: PAYMENT VOUCHER NO. 3 - FOR OCTOBER 2023
B24: DATE | C24: NAME | D24: DISCRIPTION | E24: MOMO ACCOUNT | F24: BANK ACCOUNT
B25: 45205 | C25: REGISTER GENERAL DEPARTMENT ACCRA | D25: Registration of the Association | E25: 1300
B26: 45205 | C26: MTN | D26: Taxes on MoMo | E26: =1400*2% -> 28
B27: 45205 | C27: REGISTER GENERAL DEPARTMENT ACCRA | D27: T & T from Mampong - Accra & Back | E27: 100
B28: 45209 | C28: ELD JONATHN DANSO SIAW | D28: T & T from Mampong - MTN Head office Accra & Back | E28: 100
B29: 45209 | C29: MTN | D29: Taxes on MoMo | E29: =300*2% -> 6
B30: 45211 | C30: ELD JONATHN DANSO SIAW | D30: T & T from Mampong - MTN Head office Accra & Back | E30: 100
B31: 45212 | C31: ELD JONATHN DANSO SIAW | D31: T & T from Mampong - Odorkor & Back | E31: 100
B32: TOTAL | E32: =SUM(E25:E31) -> 1734 | F32: =SUM(F25:F31) -> 0
B34: PAYMENT VOUCHER NO. 4 - FOR DECEMBER 2023
B36: DATE | C36: NAME | D36: DISCRIPTION | E36: MOMO ACCOUNT | F36: BANK ACCOUNT
B37: 45349 | C37: ELD JONATHN DANSO SIAW | D37: T & T from Mampong - Ashaiman Bank & Back | E37: 100
B38: 45349 | C38: MTN | D38: Taxes on MoMo | E38: =150*2% -> 3
B39: 45349 | C39: ELD. JUST-MARK QUANSAH | D39: T & T Ashaiman Bank & Back | E39: 50
B40: TOTAL | E40: =SUM(E37:E39) -> 153 | F40: =SUM(F37:F39) -> 0
B42: PAYMENT VOUCHER NO. 5 - FOR FEBRUARY 2024
B44: DATE | C44: NAME | D44: DISCRIPTION | E44: MOMO ACCOUNT | F44: BANK ACCOUNT
B45: 45398 | C45: COMMUNICATION CENTER | D45: Printing of Documents to GCB Bank Accra | E45: 80
B46: 45398 | C46: PHOTO STIDIO | D46: Pictures to GCB Bank | E46: 120
B47: 45398 | C47: ELD MOSES ODURO | D47: T&T Noyem to Accra & back | E47: 300
B48: 45398 | C48: ELD. JONATHAN SIAW | D48: T&T Mampong to Accra & back | E48: 150
B49: 45398 | C49: ELD. JUST-MARK QUANSAH | D49: T&T Ashaiman to Accra & back | E49: 150
B50: 45398 | C50: MTN | D50: Taxes on MoMo | E50: =800*2% -> 16
B51: 45406 | C51: AUDITOR AT AWOSHIE | D51: Document from Auditor to GBC Bank | E51: 500
B52: 45406 | C52: MTN | D52: Taxes on MoMo | E52: =750*2% -> 15
B53: 45406 | C53: ELD. JONATHAN SIAW | D53: T&T Mampong-Awoshie-Circle & back | E53: 150
B54: 45406 | C54: ELD. MAXWELL OFEI | D54: T&T Oyibi - Awoshie-Circle & back | E54: 100
B55: TOTAL | E55: =SUM(E45:E54) -> 1581 | F55: =SUM(F45:F54) -> 0
B57: PAYMENT VOUCHER NO. 6 - FOR APRIL 2024
B59: DATE | C59: NAME | D59: DISCRIPTION | E59: MOMO ACCOUNT | F59: BANK ACCOUNT
B60: 45420 | C60: COMMUNICATION CENTER | D60: Printing of Documents to Fidelity Bank Accra | E60: 40
B61: 45420 | C61: ELD MOSES ODURO | D61: T&T Noyem to Accra & back | E61: 300
B62: 45420 | C62: ELD. JONATHAN SIAW | D62: T&T Mampong to Accra & back | E62: 150
B63: 45420 | C63: ELD. JUST-MARK QUANSAH | D63: T&T Ashaiman to Accra & back | E63: 150
B64: 45420 | C64: MTN | D64: Taxes on MoMo | E64: =640*2% -> 12.8
B65: 45422 | C65: FIDELITY BANK ACCRA | D65: Cash Deposit | E65: 15200
B66: 45422 | C66: MTN | D66: Taxes on MoMo | E66: =E65*2% -> 304
B67: 45440 | C67: ELD. JONATHAN SIAW | D67: T&T Mampong to Accra & back | E67: 100
B68: 45440 | C68: ELD. JUST-MARK QUANSAH | D68: T&T Ashaiman to Accra & back | E68: 100
B69: 45441 | C69: MTN | D69: Taxes on MoMo | E69: =200*2% -> 4
B70: 45441 | C70: COMMUNICATION CENTER | D70: Printing of Documents to Fidelity Bank Accra | E70: 45
B71: 45441 | C71: MTN | D71: Taxes on MoMo | E71: =245*2% -> 4.9
B72: 45441 | C72: ELD. JONATHAN SIAW | D72: T&T Mampong to Accra & back | E72: 100
B73: 45441 | C73: ELD. JUST-MARK QUANSAH | D73: T&T Ashaiman to Accra & back | E73: 100
B74: TOTAL | E74: =SUM(E60:E73) -> 16610.7 | F74: =SUM(F60:F73) -> 0
B76: PAYMENT VOUCHER NO. 7 - FOR MAY 2024
B78: DATE | C78: NAME | D78: DISCRIPTION | E78: MOMO ACCOUNT | F78: BANK ACCOUNT
B79: 45467 | C79: FIDELITY BANK ACCRA | D79: Cash Deposit | E79: 2500
B80: 45467 | C80: MTN | D80: Taxes on MoMo | E80: =2600*2% -> 52
B81: 45467 | C81: ELD. JONATHAN SIAW | D81: T&T Mampong to Accra & back | E81: 100
B82: TOTAL | E82: =SUM(E79:E81) -> 2652 | F82: =SUM(F79:F81) -> 0
B84: PAYMENT VOUCHER NO. 8 - FOR JUNE 2024
B86: DATE | C86: NAME | D86: DISCRIPTION | E86: MOMO ACCOUNT | F86: BANK ACCOUNT
B87: 45525 | C87: FIDELITY BANK ACCRA | D87: Cash Deposit | E87: 3500
B88: 45525 | C88: MTN | D88: Taxes on MoMo | E88: =3600*2% -> 72
B89: 45525 | C89: ELD. JONATHAN SIAW | D89: T&T Mampong to Accra & back | E89: 100
B90: TOTAL | E90: =SUM(E87:E89) -> 3672 | F90: =SUM(F87:F89) -> 0
B92: PAYMENT VOUCHER NO. 9 - FOR AUGUST 2024
B94: DATE | C94: NAME | D94: DISCRIPTION | E94: MOMO ACCOUNT | F94: BANK ACCOUNT
B95: 45665 | C95: FIDELITY BANK ACCRA | D95: Cash Deposit | E95: 2100
B96: 45665 | C96: ELD. JONATHAN SIAW | D96: T&T Mampong to Accra & back | E96: 100
B97: 45665 | C97: MTN | D97: Taxes on MoMo | E97: =2100*1% -> 21
B98: 45674 | C98: FIDELITY BANK ACCRA | D98: Cash Deposit | E98: 1500
B99: 45675 | C99: MTN | D99: Taxes on MoMo | E99: =1600*1% -> 16
B100: 45674 | C100: ELD. JONATHAN SIAW | D100: T&T Mampong to Accra & back | E100: 100
B101: TOTAL | E101: =SUM(E95:E100) -> 3837 | F101: =SUM(F95:F100) -> 0
B103: PAYMENT VOUCHER NO. 10 - FOR OCTOBER 2024
B105: DATE | C105: NAME | D105: DISCRIPTION | E105: MOMO ACCOUNT | F105: BANK ACCOUNT
B106: 45691 | C106: FIDELITY BANK ACCRA | D106: Cash Deposit | E106: 1500
B107: 45691 | C107: MTN | D107: Taxes on MoMo | E107: =1700*1% -> 17
B108: 45691 | C108: ELD. JONATHAN SIAW | D108: T&T Mampong to Accra & back | E108: 100
B109: 45691 | C109: ELD. JUST-MARK QUANSAH | D109: T&T Ashaiman to Accra & back | E109: 100
B110: TOTAL | E110: =SUM(E106:E109) -> 1717 | F110: =SUM(F106:F109) -> 0
B112: PAYMENT VOUCHER NO. 11 - FOR FEBRUARY 2025
B114: DATE | C114: NAME | D114: DISCRIPTION | E114: MOMO ACCOUNT | F114: BANK ACCOUNT
B115: 45751 | C115: FIDELITY BANK ACCRA | D115: Cash Deposit | E115: 4000
B116: 45751 | C116: MTN | D116: Taxes on MoMo | E116: =4100*1% -> 41
B117: 45751 | C117: ELD. JONATHAN SIAW | D117: T&T Mampong to Accra & back | E117: 100
B118: TOTAL | E118: =SUM(E115:E117) -> 4141 | F118: =SUM(F115:F117) -> 0
B120: PAYMENT VOUCHER NO. 12 - FOR APRIL 2025
B122: DATE | C122: NAME | D122: DISCRIPTION | E122: MOMO ACCOUNT | F122: BANK ACCOUNT
B123: 45799 | C123: ELD. JONATHAN SIAW | D123: T&T Mampong to Accra MTN Head office & back | E123: 100
B124: 45800 | C124: FIDELITY BANK ACCRA | D124: Cash Deposit | E124: 2000
B125: 45801 | C125: MTN | D125: Taxes on MoMo | E125: =2910*1% -> 29.1
...

Sheet PETTY CASH ACCOUNT
B2: PETTY cash ACCOUNT
B3: DATE | C3: PARTICULARS | D3: PAYMENT VOUCHER NOMBER | E3: INCOME | F3: EXPENSES | G3: BALANCE | J3: INCOME | P3: DUES EXPENSES
E4: ¢ | F4: ¢ | G4: ¢ | H4: MOMO CASH | I4: MOMO LEVY | J4: TEMA BANK INTREST | K4: FIDELETY BANK INTREST | L4: TEMA BANK | M4: TREASURER BILL | N4: LEVY ACCOUNT | O4: MOMO CHARGES | P4: FEDILITY DEPOSITS | Q4: BANK TEMA | R4: T & T DUES | S4: GENERAL EXPENSES | T4: PRINTING & STATIONERY | U4: DOCUMENTATION | V4: REGISREAL GENERAL | W4: DEPOSIT LEVY | X4: PURCHASE OFM VEHIVLE
B5: 45021 | C5: Withdraw cash from MoMo Account | D5: 1 | E5: =SUM(H5:N5) -> 5813 | G5: =E5 -> 5813 | H5: ='PAYMENT VOUCHERS'!E14 -> 5813
B6: 45066 | C6: Deposit Cash to Tema Bank | D6: 1 | E6: =SUM(H6:N6) -> 0 | F6: =SUM(O6:X6) -> 5400 | G6: =G5+E6-F6 -> 413 | Q6: ='PAYMENT VOUCHERS'!E7 -> 5400
B7: 45066 | C7: Bought Shares from Tema Bank | D7: 1 | E7: =SUM(H7:N7) -> 0 | F7: =SUM(O7:X7) -> 100 | G7: =G6+E7-F7 -> 313 | Q7: ='PAYMENT VOUCHERS'!E8 -> 100
B8: 45066 | C8: MTN Taxes on MoMo | D8: 1 | E8: =SUM(H8:N8) -> 0 | F8: =SUM(O8:X8) -> 110 | G8: =G7+E8-F8 -> 203 | O8: ='PAYMENT VOUCHERS'!E9 -> 110
B9: 45066 | C9: T & T Ashaiman Bank & Back | D9: 1 | E9: =SUM(H9:N9) -> 0 | F9: =SUM(O9:X9) -> 50 | G9: =G8+E9-F9 -> 153 | R9: ='PAYMENT VOUCHERS'!E10 -> 50
B10: 45073 | C10: Deposit Cash to Tema Bank | D10: 1 | E10: =SUM(H10:N10) -> 0 | F10: =SUM(O10:X10) -> 100 | G10: =G9+E10-F10 -> 53 | Q10: ='PAYMENT VOUCHERS'!E11 -> 100
B11: 45073 | C11: MTN Taxes on MoMo | D11: 1 | E11: =SUM(H11:N11) -> 0 | F11: =SUM(O11:X11) -> 3 | G11: =G10+E11-F11 -> 50 | O11: ='PAYMENT VOUCHERS'!E12 -> 3
B12: 45073 | C12: T & T Ashaiman Bank & Back | D12: 1 | E12: =SUM(H12:N12) -> 0 | F12: =SUM(O12:X12) -> 50 | G12: =G11+E12-F12 -> 0 | R12: ='PAYMENT VOUCHERS'!E13 -> 50
B13: 45158 | C13: Withdrawal from Dues Account | D13: 2 | E13: =SUM(H13:N13) -> 400 | F13: =SUM(O13:X13) -> 0 | G13: =G12+E13-F13 -> 400 | N13: ='MTN MOMO ACCOUNT'!E32 -> 400
B14: 45158 | C14: Sent to Levy Account | D14: 2 | E14: =SUM(H14:N14) -> 0 | F14: =SUM(O14:X14) -> 400 | G14: =G13+E14-F14 -> 0 | W14: ='MTN MOMO ACCOUNT'!E32 -> 400
B15: 45204 | C15: Withdraw cash from MoMo Account | D15: 3 | E15: =SUM(H15:N15) -> 1734 | F15: =SUM(O15:X15) -> 0 | G15: =G14+E15-F15 -> 1734 | H15: ='PAYMENT VOUCHERS'!E32 -> 1734
B16: 45205 | C16: Registration of the Association at RGD Accra | D16: 3 | E16: =SUM(H16:N16) -> 0 | F16: =SUM(O16:X16) -> 1300 | G16: =G15+E16-F16 -> 434 | V16: ='PAYMENT VOUCHERS'!E25 -> 1300
B17: 45205 | C17: MTN Taxes on MoMo | D17: 3 | E17: =SUM(H17:N17) -> 0 | F17: =SUM(O17:X17) -> 28 | G17: =G16+E17-F17 -> 406 | O17: ='PAYMENT VOUCHERS'!E26 -> 28
B18: 45205 | C18: T & T from Mampong to Registrar General Office | D18: 3 | E18: =SUM(H18:N18) -> 0 | F18: =SUM(O18:X18) -> 100 | G18: =G17+E18-F18 -> 306 | R18: ='PAYMENT VOUCHERS'!E27 -> 100
B19: 45208 | C19: T & T from Mampong to Madina MTN Office | D19: 3 | E19: =SUM(H19:N19) -> 0 | F19: =SUM(O19:X19) -> 100 | G19: =G18+E19-F19 -> 206 | R19: ='PAYMENT VOUCHERS'!E28 -> 100
B20: 45208 | C20: MTN Taxes on MoMo | D20: 3 | E20: =SUM(H20:N20) -> 0 | F20: =SUM(O20:X20) -> 6 | G20: =G19+E20-F20 -> 200 | O20: ='PAYMENT VOUCHERS'!E29 -> 6
B21: 45209 | C21: T & T from Mampong to Madina MTN Office | D21: 3 | E21: =SUM(H21:N21) -> 0 | F21: =SUM(O21:X21) -> 100 | G21: =G20+E21-F21 -> 100 | R21: ='PAYMENT VOUCHERS'!E30 -> 100
B22: 45211 | C22: T & T from Mampong to Odorkor | D22: 3 | E22: =SUM(H22:N22) -> 0 | F22: =SUM(O22:X22) -> 100 | G22: =G21+E22-F22 -> 0 | R22: ='PAYMENT VOUCHERS'!E31 -> 100
B23: 44957 | C23: Withdraw cash from MoMo Account | D23: 4 | E23: =SUM(H23:N23) -> 153 | F23: =SUM(O23:X23) -> 0 | G23: =G22+E23-F23 -> 153 | H23: ='PAYMENT VOUCHERS'!E40 -> 153
B24: 45349 | C24: T & T from Mampong - Ashaiman Bank & Back | D24: 4 | E24: =SUM(H24:N24) -> 0 | F24: =SUM(O24:X24) -> 100 | G24: =G23+E24-F24 -> 53 | R24: ='PAYMENT VOUCHERS'!E37 -> 100
B25: 45349 | C25: MTN Taxes on MoMo | D25: 4 | F25: =SUM(O25:X25) -> 0 | G25: =G24+E25-F25 -> 53
B26: 45349 | C26: T & T Ashaiman Bank & Back | D26: 4 | E26: =SUM(H26:N26) -> 0 | F26: =SUM(O26:X26) -> 50 | G26: =G25+E26-F26 -> 3 | R26: ='PAYMENT VOUCHERS'!E39 -> 50
B27: 45397 | C27: Withdraw cash from MoMo Account | D27: 5 | E27: =SUM(H27:N27) -> 1581 | F27: =SUM(O27:X27) -> 3 | G27: =G26+E27-F27 -> 1581 | H27: ='PAYMENT VOUCHERS'!E55 -> 1581 | O27: ='PAYMENT VOUCHERS'!E38 -> 3
B28: 45398 | C28: Printing of documents to GCB | D28: 5 | E28: =SUM(H28:N28) -> 0 | F28: =SUM(O28:X28) -> 80 | G28: =G27+E28-F28 -> 1501 | T28: ='PAYMENT VOUCHERS'!E45 -> 80
B29: 45398 | C29: Pictures to GCB | D29: 5 | E29: =SUM(H29:N29) -> 0 | F29: =SUM(O29:X29) -> 120 | G29: =G28+E29-F29 -> 1381 | T29: ='PAYMENT VOUCHERS'!E46 -> 120
B30: 45398 | C30: T&T Noyem to Accra & back | D30: 5 | E30: =SUM(H30:N30) -> 0 | F30: =SUM(O30:X30) -> 300 | G30: =G29+E30-F30 -> 1081 | R30: ='PAYMENT VOUCHERS'!E47 -> 300
B31: 45398 | C31: T&T Mampong to Accra & back | D31: 5 | E31: =SUM(H31:N31) -> 0 | F31: =SUM(O31:X31) -> 150 | G31: =G30+E31-F31 -> 931 | R31: ='PAYMENT VOUCHERS'!E48 -> 150
B32: 45398 | C32: T&T Ashaiman to Accra & back | D32: 5 | E32: =SUM(H32:N32) -> 0 | F32: =SUM(O32:X32) -> 150 | G32: =G31+E32-F32 -> 781 | R32: ='PAYMENT VOUCHERS'!E49 -> 150
B33: 45398 | C33: MTN Taxes on MoMo | D33: 5 | F33: =SUM(O33:X33) -> 16 | G33: =G32+E33-F33 -> 765 | O33: ='PAYMENT VOUCHERS'!E50 -> 16
B34: 45406 | C34: Document from Auditor to GBC Bank | D34: 5 | E34: =SUM(H34:N34) -> 0 | F34: =SUM(O34:X34) -> 500 | G34: =G33+E34-F34 -> 265 | U34: ='PAYMENT VOUCHERS'!E51 -> 500
B35: 45406 | C35: T&T Mampong-Awoshie-Circle & back | D35: 5 | E35: =SUM(H35:N35) -> 0 | F35: =SUM(O35:X35) -> 15 | G35: =G34+E35-F35 -> 250 | O35: ='PAYMENT VOUCHERS'!E52 -> 15
B36: 45406 | C36: MTN Taxes on MoMo | D36: 5 | F36: =SUM(O36:X36) -> 150 | G36: =G35+E36-F36 -> 100 | R36: ='PAYMENT VOUCHERS'!E53 -> 150
B37: 45406 | C37: T&T Oyibi,- Awoshie & back | D37: 5 | E37: =SUM(H37:N37) -> 0 | F37: =SUM(O37:X37) -> 100 | G37: =G36+E37-F37 -> 0 | R37: ='PAYMENT VOUCHERS'!E54 -> 100
B38: 45419 | C38: Withdraw cash from MoMo Account | D38: 6 | E38: =SUM(H38:N38) -> 16610.7 | F38: =SUM(O38:X38) -> 0 | G38: =G37+E38-F38 -> 16610.7 | H38: ='PAYMENT VOUCHERS'!E74 -> 16610.7
B39: 45420 | C39: Printing of documents | D39: 6 | E39: =SUM(H39:N39) -> 0 | F39: =SUM(O39:X39) -> 40 | G39: =G38+E39-F39 -> 16570.7 | T39: ='PAYMENT VOUCHERS'!E60 -> 40
B40: 45420 | C40: T&T Noyem to Accra & back | D40: 6 | E40: =SUM(H40:N40) -> 0 | F40: =SUM(O40:X40) -> 300 | G40: =G39+E40-F40 -> 16270.7 | R40: ='PAYMENT VOUCHERS'!E61 -> 300
B41: 45420 | C41: T&T Mampong to Accra & back | D41: 6 | E41: =SUM(H41:N41) -> 0 | F41: =SUM(O41:X41) -> 150 | G41: =G40+E41-F41 -> 16120.7 | R41: ='PAYMENT VOUCHERS'!E62 -> 150
B42: 45420 | C42: T&T Ashaiman to Accra & back | D42: 6 | E42: =SUM(H42:N42) -> 0 | F42: =SUM(O42:X42) -> 150 | G42: =G41+E42-F42 -> 15970.7 | R42: ='PAYMENT VOUCHERS'!E63 -> 150
B43: 45420 | C43: MTN Taxes on MoMo | D43: 6 | F43: =SUM(O43:X43) -> 12.8 | G43: =G42+E43-F43 -> 15957.9 | O43: ='PAYMENT VOUCHERS'!E64 -> 12.8
B44: 45421 | C44: Cash Deposit to Fidelity Bank | D44: 6 | E44: =SUM(H44:N44) -> 0 | F44: =SUM(O44:X44) -> 15200 | G44: =G43+E44-F44 -> 757.9 | P44: ='PAYMENT VOUCHERS'!E65 -> 15200
B45: 45421 | C45: MTN Taxes on MoMo | D45: 6 | E45: =SUM(H45:N45) -> 0 | F45: =SUM(O45:X45) -> 304 | G45: =G44+E45-F45 -> 453.9 | O45: ='PAYMENT VOUCHERS'!E66 -> 304
B46: 45421 | C46: T&T Mampong to Accra & back | D46: 6 | E46: =SUM(H46:N46) -> 0 | F46: =SUM(O46:X46) -> 100 | G46: =G45+E46-F46 -> 353.9 | R46: ='PAYMENT VOUCHERS'!E67 -> 100
B47: 45421 | C47: T&T Ashaiman to Accra & back | D47: 6 | E47: =SUM(H47:N47) -> 0 | F47: =SUM(O47:X47) -> 100 | G47: =G46+E47-F47 -> 253.9 | R47: ='PAYMENT VOUCHERS'!E68 -> 100
B48: 45421 | C48: MTN Taxes on MoMo | D48: 6 | F48: =SUM(O48:X48) -> 4 | G48: =G47+E48-F48 -> 249.9 | O48: ='PAYMENT VOUCHERS'!E69 -> 4
B49: 45440 | C49: Printing of documents | D49: 6 | E49: =SUM(H49:N49) -> 0 | F49: =SUM(O49:X49) -> 45 | G49: =G48+E49-F49 -> 204.9 | T49: ='PAYMENT VOUCHERS'!E70 -> 45
B50: 45440 | C50: MTN Taxes on MoMo | D50: 6 | E50: =SUM(H50:N50) -> 0 | F50: =SUM(O50:X50) -> 4.9 | G50: =G49+E50-F50 -> 200 | O50: ='PAYMENT VOUCHERS'!E71 -> 4.9
B51: 45440 | C51: T&T Ashaiman to Accra & back | D51: 6 | E51: =SUM(H51:N51) -> 0 | F51: =SUM(O51:X51) -> 100 | G51: =G50+E51-F51 -> 100 | R51: ='PAYMENT VOUCHERS'!E72 -> 100
B52: 45440 | C52: T&T Mampong to Accra & back | D52: 6 | E52: =SUM(H52:N52) -> 0 | F52: =SUM(O52:X52) -> 100 | G52: =G51+E52-F52 -> 1.4495072e-12 | R52: ='PAYMENT VOUCHERS'!E73 -> 100
B53: 45466 | C53: Withdraw cash from MoMo Account | D53: 7 | E53: =SUM(H53:N53) -> 2652 | F53: =SUM(O53:X53) -> 0 | G53: =G52+E53-F53 -> 2652 | H53: ='PAYMENT VOUCHERS'!E82 -> 2652
B54: 45467 | C54: Cash Deposit to Fidelity Bank | D54: 7 | E54: =SUM(H54:N54) -> 0 | F54: =SUM(O54:X54) -> 2500 | G54: =G53+E54-F54 -> 152 | P54: ='PAYMENT VOUCHERS'!E79 -> 2500
B55: 45467 | C55: MTN Taxes on MoMo | D55: 7 | E55: =SUM(H55:N55) -> 0 | F55: =SUM(O55:X55) -> 52 | G55: =G54+E55-F55 -> 100 | O55: ='PAYMENT VOUCHERS'!E80 -> 52
B56: 45467 | C56: T&T Mampong to Accra & back | D56: 7 | E56: =SUM(H56:N56) -> 0 | F56: =SUM(O56:X56) -> 100 | G56: =G55+E56-F56 -> 1.3642421e-12 | R56: ='PAYMENT VOUCHERS'!E81 -> 100
B57: 45524 | C57: Withdraw cash from MoMo Account | D57: 8 | E57: =SUM(H57:N57) -> 3672 | F57: =SUM(O57:X57) -> 0 | G57: =G56+E57-F57 -> 3672 | H57: ='PAYMENT VOUCHERS'!E90 -> 3672
B58: 45525 | C58: Cash Deposit to Fidelity Bank | D58: 8 | E58: =SUM(H58:N58) -> 0 | F58: =SUM(O58:X58) -> 3500 | G58: =G57+E58-F58 -> 172 | P58: ='PAYMENT VOUCHERS'!E87 -> 3500
B59: 45525 | C59: MTN Taxes on MoMo | D59: 8 | F59: =SUM(O59:X59) -> 72 | G59: =G58+E59-F59 -> 100 | O59: ='PAYMENT VOUCHERS'!E88 -> 72
B60: 45525 | C60: T&T Mampong to Accra & back | D60: 8 | E60: =SUM(H60:N60) -> 0 | F60: =SUM(O60:X60) -> 100 | G60: =G59+E60-F60 -> 1.3642421e-12 | R60: ='PAYMENT VOUCHERS'!E89 -> 100
B61: 45664 | C61: Withdraw cash from MoMo Account | D61: 9 | E61: =SUM(H61:N61) -> 3837 | F61: =SUM(O61:X61) -> 0 | G61: =G60+E61-F61 -> 3837 | H61: ='PAYMENT VOUCHERS'!E101 -> 3837
B62: 45665 | C62: Cash Deposit to Fidelity Bank | D62: 9 | E62: =SUM(H62:N62) -> 0 | F62: =SUM(O62:X62) -> 2100 | G62: =G61+E62-F62 -> 1737 | P62: ='PAYMENT VOUCHERS'!E95 -> 2100
B63: 45665 | C63: T&T Mampong to Accra & back | D63: 9 | E63: =SUM(H63:N63) -> 0 | F63: =SUM(O63:X63) -> 100 | G63: =G62+E63-F63 -> 1637 | R63: ='PAYMENT VOUCHERS'!E96 -> 100
B64: 45665 | C64: MTN Taxes on MoMo | D64: 9 | F64: =SUM(O64:X64) -> 21 | G64: =G63+E64-F64 -> 1616 | O64: ='PAYMENT VOUCHERS'!E97 -> 21
B65: 45674 | C65: Cash Deposit to Fidelity Bank | D65: 9 | E65: =SUM(H65:N65) -> 0 | F65: =SUM(O65:X65) -> 1500 | G65: =G64+E65-F65 -> 116 | P65: ='PAYMENT VOUCHERS'!E98 -> 1500
B66: 45674 | C66: MTN Taxes on MoMo | D66: 9 | F66: =SUM(O66:X66) -> 16 | G66: =G65+E66-F66 -> 100 | O66: ='PAYMENT VOUCHERS'!E99 -> 16
B67: 45674 | C67: T&T Mampong to Accra & back | D67: 9 | E67: =SUM(H67:N67) -> 0 | F67: =SUM(O67:X67) -> 100 | G67: =G66+E67-F67 -> 1.3642421e-12 | R67: ='PAYMENT VOUCHERS'!E100 -> 100
B68: 45690 | C68: Withdraw cash from MoMo Account | D68: 10 | E68: =SUM(H68:N68) -> 1717 | F68: =SUM(O68:X68) -> 0 | G68: =G67+E68-F68 -> 1717 | H68: ='PAYMENT VOUCHERS'!E110 -> 1717
B69: 45691 | C69: Cash Deposit to Fidelity Bank | D69: 10 | E69: =SUM(H69:N69) -> 0 | F69: =SUM(O69:X69) -> 1500 | G69: =G68+E69-F69 -> 217 | P69: ='PAYMENT VOUCHERS'!E106 -> 1500
B70: 45691 | C70: MTN Taxes on MoMo | D70: 10 | E70: =SUM(H70:N70) -> 0 | F70: =SUM(O70:X70) -> 17 | G70: =G69+E70-F70 -> 200 | O70: ='PAYMENT VOUCHERS'!E107 -> 17
B71: 45691 | C71: T&T Mampong to Accra & back | D71: 10 | E71: =SUM(H71:N71) -> 0 | F71: =SUM(O71:X71) -> 100 | G71: =G70+E71-F71 -> 100 | R71: ='PAYMENT VOUCHERS'!E108 -> 100
B72: 45691 | C72: T&T Ashaiman to Accra & back | D72: 10 | E72: =SUM(H72:N72) -> 0 | F72: =SUM(O72:X72) -> 100 | G72: =G71+E72-F72 -> 1.3642421e-12 | R72: ='PAYMENT VOUCHERS'!E109 -> 100
B73: 45750 | C73: Withdraw cash from MoMo Account | D73: 11 | E73: =SUM(H73:N73) -> 4141 | F73: =SUM(O73:X73) -> 0 | G73: =G72+E73-F73 -> 4141 | H73: ='PAYMENT VOUCHERS'!E118 -> 4141
B74: 45751 | C74: Cash Deposit to Fidelity Bank | D74: 11 | E74: =SUM(H74:N74) -> 0 | F74: =SUM(O74:X74) -> 4000 | G74: =G73+E74-F74 -> 141 | P74: ='PAYMENT VOUCHERS'!E115 -> 4000
B75: 45751 | C75: MTN Taxes on MoMo | D75: 11 | E75: =SUM(H75:N75) -> 0 | F75: =SUM(O75:X75) -> 41 | G75: =G74+E75-F75 -> 100 | O75: ='PAYMENT VOUCHERS'!E116 -> 41
B76: 45751 | C76: T&T Mampong to Accra & back | D76: 11 | E76: =SUM(H76:N76) -> 0 | F76: =SUM(O76:X76) -> 100 | G76: =G75+E76-F76 -> 1.8189894e-12 | R76: ='PAYMENT VOUCHERS'!E117 -> 100
B77: 45798 | C77: Withdraw cash from MoMo Account | D77: 12 | E77: =SUM(H77:N77) -> 3039.1 | F77: =SUM(O77:X77) -> 0 | G77: =G76+E77-F77 -> 3039.1 | H77: ='PAYMENT VOUCHERS'!E129 -> 3039.1
B78: 45799 | C78: T&T Mampong to Accra MTN Head office & back | D78: 12 | E78: =SUM(H78:N78) -> 0 | F78: =SUM(O78:X78) -> 100 | G78: =G77+E78-F78 -> 2939.1 | R78: ='PAYMENT VOUCHERS'!E123 -> 100
B79: 45799 | C79: Cash Deposit to Fidelity Bank | D79: 12 | E79: =SUM(H79:N79) -> 0 | F79: =SUM(O79:X79) -> 2000 | G79: =G78+E79-F79 -> 939.1 | P79: ='PAYMENT VOUCHERS'!E124 -> 2000
B80: 45799 | C80: MTN Taxes on MoMo | D80: 12 | E80: =SUM(H80:N80) -> 0 | F80: =SUM(O80:X80) -> 29.1 | G80: =G79+E80-F80 -> 910 | O80: ='PAYMENT VOUCHERS'!E125 -> 29.1
B81: 45799 | C81: T&T Mampong to Fidelity Bank Accra & back | D81: 12 | F81: =SUM(O81:X81) -> 100 | G81: =G80+E81-F81 -> 810 | R81: ='PAYMENT VOUCHERS'!E126 -> 100
B82: 45799 | C82: New Chip for Onuado Na Eye | D82: 12 | E82: =SUM(H82:N82) -> 0 | F82: =SUM(O82:X82) -> 10 | G82: =G81+E82-F82 -> 800 | S82: ='PAYMENT VOUCHERS'!E127 -> 10
B83: 45799 | C83: New Phone for Onuado | D83: 12 | E83: =SUM(H83:N83) -> 0 | F83: =SUM(O83:X83) -> 800 | G83: =G82+E83-F83 -> 1.7053026e-12 | S83: ='PAYMENT VOUCHERS'!E128 -> 800
B84: 45823 | C84: Withdraw cash from MoMo Account | D84: 13 | E84: =SUM(H84:N84) -> 2434 | F84: =SUM(O84:X84) -> 0 | G84: =G83+E84-F84 -> 2434 | H84: ='PAYMENT VOUCHERS'!E137 -> 2434
B85: 45824 | C85: Cash Deposit to Fidelity Bank | D85: 13 | E85: =SUM(H85:N85) -> 0 | F85: =SUM(O85:X85) -> 2300 | G85: =G84+E85-F85 -> 134 | P85: ='PAYMENT VOUCHERS'!E134 -> 2300
B86: 45824 | C86: MTN Taxes on MoMo | D86: 13 | F86: =SUM(O86:X86) -> 34 | G86: =G85+E86-F86 -> 100 | O86: ='PAYMENT VOUCHERS'!E135 -> 34
B87: 45824 | C87: T&T Mampong to Fidelity Bank Accra & back | D87: 13 | E87: =SUM(H87:N87) -> 0 | F87: =SUM(O87:X87) -> 100 | G87: =G86+E87-F87 -> 1.8189894e-12 | R87: ='PAYMENT VOUCHERS'!E136 -> 100
B88: 45874 | C88: Withdraw cash from MoMo Account | D88: 14 | E88: =SUM(H88:N88) -> 2323 | F88: =SUM(O88:X88) -> 0 | G88: =G87+E88-F88 -> 2323 | H88: ='PAYMENT VOUCHERS'!E145 -> 2323
B89: 45875 | C89: Cash Deposit to Fidelity Bank | D89: 14 | E89: =SUM(H89:N89) -> 0 | F89: =SUM(O89:X89) -> 2000 | G89: =G88+E89-F89 -> 323 | P89: ='PAYMENT VOUCHERS'!E141 -> 2000
B90: 45875 | C90: MTN Taxes on MoMo | D90: 14 | E90: =SUM(H90:N90) -> 0 | F90: =SUM(O90:X90) -> 23 | G90: =G89+E90-F90 -> 300 | O90: ='PAYMENT VOUCHERS'!E142 -> 23
B91: 45875 | C91: T&T Mampong to Accra & back | D91: 14 | E91: =SUM(H91:N91) -> 0 | F91: =SUM(O91:X91) -> 100 | G91: =G90+E91-F91 -> 200 | R91: ='PAYMENT VOUCHERS'!E143 -> 100
B92: 45875 | C92: T&T Ashaiman to Mampong / Accra & back | D92: 14 | E92: =SUM(H92:N92) -> 0 | F92: =SUM(O92:X92) -> 200 | G92: =G91+E92-F92 -> 1.8189894e-12 | R92: ='PAYMENT VOUCHERS'!E144 -> 200
B93: 45903 | C93: Withdraw cash from MoMo Account | D93: 15 | E93: =SUM(H93:N93) -> 5156 | F93: =SUM(O93:X93) -> 0 | G93: =G92+E93-F93 -> 5156 | H93: ='PAYMENT VOUCHERS'!E153 -> 5156
B94: 45904 | C94: Cash Deposit to Fidelity Bank | D94: 15 | E94: =SUM(H94:N94) -> 0 | F94: =SUM(O94:X94) -> 5000 | G94: =G93+E94-F94 -> 156 | P94: ='PAYMENT VOUCHERS'!E150 -> 5000
B95: 45904 | C95: MTN Taxes on MoMo | D95: 15 | E95: =SUM(H95:N95) -> 0 | F95: =SUM(O95:X95) -> 56 | G95: =G94+E95-F95 -> 100 | O95: ='PAYMENT VOUCHERS'!E151 -> 56
B96: 45904 | C96: T&T Mampong to Accra & back | D96: 15 | E96: =SUM(H96:N96) -> 0 | F96: =SUM(O96:X96) -> 100 | G96: =G95+E96-F96 -> 1.8189894e-12 | R96: ='PAYMENT VOUCHERS'!E152 -> 100
B97: 46008 | C97: Withdraw cash from MoMo Account | D97: 16 | E97: =SUM(H97:N97) -> 3737 | F97: =SUM(O97:X97) -> 0 | G97: =G96+E97-F97 -> 3737 | H97: ='PAYMENT VOUCHERS'!E161 -> 3737
B98: 46008 | C98: Cash Deposit to Fidelity Bank | D98: 16 | E98: =SUM(H98:N98) -> 0 | F98: =SUM(O98:X98) -> 3600 | G98: =G97+E98-F98 -> 137 | P98: ='PAYMENT VOUCHERS'!E158 -> 3600
B99: 46008 | C99: MTN Taxes on MoMo | D99: 16 | E99: =SUM(H99:N99) -> 0 | F99: =SUM(O99:X99) -> 37 | G99: =G98+E99-F99 -> 100 | O99: ='PAYMENT VOUCHERS'!E159 -> 37
B100: 46008 | C100: T&T Mampong to Accra & back | D100: 16 | E100: =SUM(H100:N100) -> 0 | F100: =SUM(O100:X100) -> 100 | G100: =G99+E100-F100 -> 1.8189894e-12 | R100: ='PAYMENT VOUCHERS'!E160 -> 100
B101: 46041 | C101: Withdraw cash from MoMo Account | D101: 17 | E101: =SUM(H101:N101) -> 3134 | F101: =SUM(O101:X101) -> 0 | G101: =G100+E101-F101 -> 3134 | H101: ='PAYMENT VOUCHERS'!E169 -> 3134
...

Sheet TRAIL BALANCE
B3: TRAIL BALANCE
B4: PARTICULARS | C4: INCOME | D4: EXPENDICTURE
C5: ¢ | D5: ¢
B6: REGISTRATION | C6: ='MEMBERS LIST'!AI30 -> 4800
B7: TOTAL MONTHLY DUES FOR 2023 | C7: ='MONTHLY DUES 2023'!D25 -> 10800
B8: TOTAL MONTHLY DUES FOR 2024 | C8: ='MONTHLY DUES 2024'!D27 -> 16900
B9: TOTAL MONTHLY DUES FOR 2025 | C9: ='MONTHLY DUES 2025'!D28 -> 22350
B10: TOTAL MONTHLY DUES FOR 2026 | C10: ='MONTHLY DUES 2026'!D26 -> 15900
B11: TREASURER BILL INTREST | C11: ='TREASURE BILL FOR MEMBERS'!D25 -> 10502.699
B12: LEVY BALANCE | C12: ='LEVY ACCOUNT'!F24 -> 1250.5
B13: SPECIAL CONTRIBUTIONS | C13: ='VEHICLE SHARES HOLDING'!D32 -> 4000
B14: BANK TEMA SHARES | D14: 100
B15: MOMO CHARGES | D15: ='PETTY CASH ACCOUNT'!O141 -> 1091.8
B16: FIDELITY BANK CHARGES | D16: ='FIDELITY BANK'!M67 -> 15
B17: TREASURER BILL CHARGES | D17: 34.34
B18: TRANPORTATIONS | D18: ='PETTY CASH ACCOUNT'!R141 -> 5100
B19: GENERAL EXPENSES | D19: ='PETTY CASH ACCOUNT'!S141 -> 1010
B20: PRINTING & STATIONERY | D20: ='PETTY CASH ACCOUNT'!T141 -> 285
B21: DOCUMENTATIONS | D21: ='PETTY CASH ACCOUNT'!U141 -> 500
B22: REGISREAL GENERAL | D22: ='PETTY CASH ACCOUNT'!V141 -> 1300
B23: BANK TEMA BALANCE | D23: ='BANK ACCOUNT TEMA'!F22 -> 366.24
B24: FIDELITY BANK BALANCE | D24: ='FIDELITY BANK'!F67 -> 10698.88
B25: MOMO BALANCE | D25: ='MTN MOMO ACCOUNT'!F66 -> 1.95
B26: TRANSFARE TO PURCHASES VEHICLE (Account) | D26: ='PETTY CASH VEHICLE'!E101 -> 66000
B27: TOTAL | C27: =SUM(C6:C26) -> 86503.199 | D27: =SUM(D6:D26) -> 86503.21
D28: =C27-D27 -> -0.010773004

Sheet FIDELITY BANK
B3: FIDELITY BANK
B4: DATE | C4: PARTICULARS | D4: INCOME | E4: EXPENSES | F4: BALANCE | G4: SAVINGS | H4: BANK INTREST | I4: TREASURER BILL | J4: TREASURER BILL INTREST | K4: TREASURER BILL BOG | L4: CASH WITHDRAWAL | M4: BANK CHARGES
C5: 2090182444410 | D5: ¢ | E5: ¢ | F5: ¢ | G5: ¢ | H5: ¢ | J5: ¢ | K5: ¢ | M5: ¢ | N5: ¢
B6: 45422 | C6: Cash Deposited | D6: =SUM(G6:J6) -> 200 | F6: =D6 -> 200 | G6: 200
B7: 45425 | C7: Cash Deposited | D7: =SUM(G7:J7) -> 13000 | F7: =F6+D7-E7 -> 13200 | G7: 13000
B8: 45440 | C8: Cash Deposited | D8: =SUM(G8:J8) -> 2000 | F8: =F7+D8-E8 -> 15200 | G8: 2000
B9: 45444 | C9: Interest for May 2024 | D9: =SUM(G9:J9) -> 7.08 | F9: =F8+D9-E9 -> 15207.08 | H9: 7.08
B10: 45449 | C10: Purchase of Treasure Bill | E10: =SUM(K10:N10) -> 15000 | F10: =F9+D10-E10 -> 207.08 | K10: 15000
B11: 45467 | C11: Cash Deposited | D11: =SUM(G11:J11) -> 2500 | F11: =F10+D11-E11 -> 2707.08 | G11: 2500
B12: 45471 | C12: Interest for June 2024 | D12: =SUM(G12:J12) -> 2.39 | F12: =F11+D12-E12 -> 2709.47 | H12: 2.39
B13: 45504 | C13: Interest for July 2024 | D13: =SUM(G13:J13) -> 1.15 | F13: =F12+D13-E13 -> 2710.62 | H13: 1.15
B14: 45525 | C14: Cash Deposited | D14: =SUM(G14:J14) -> 3500 | F14: =F13+D14-E14 -> 6210.62 | G14: 3500
B15: 45665 | C15: Interest for Aug- Dec 2024 | D15: =SUM(G15:J15) -> 23.35 | F15: =F14+D15-E15 -> 6233.97 | H15: 23.35
B16: 45665 | C16: Cash Deposited | D16: =SUM(G16:J16) -> 2000 | E16: =SUM(K16:N16) -> 0 | F16: =F15+D16-E16 -> 8233.97 | G16: 2000
B17: 45674 | C17: Cash Deposited | D17: =SUM(G17:J17) -> 1500 | E17: =SUM(K17:N17) -> 0 | F17: =F16+D17-E17 -> 9733.97 | G17: 1500
B18: 45691 | C18: Cash Deposited | D18: =SUM(G18:J18) -> 1500 | E18: =SUM(K18:N18) -> 0 | F18: =F17+D18-E18 -> 11233.97 | G18: 1500
B19: 45691 | C19: Interest for January 2025 | D19: =SUM(G19:J19) -> 7.23 | E19: =SUM(K19:N19) -> 0 | F19: =F18+D19-E19 -> 11241.2 | H19: 7.23
B20: 45692 | C20: Purchase of Treasure Bill | D20: =SUM(G20:J20) -> 0 | E20: =SUM(K20:N20) -> 11000 | F20: =F19+D20-E20 -> 241.2 | K20: 11000
B21: 45747 | C21: Interest for Feb & Mar 2025 | D21: =SUM(G21:J21) -> 1.33 | E21: =SUM(K21:N21) -> 0 | F21: =F20+D21-E21 -> 242.53 | H21: 1.33
B22: 45751 | C22: Cash Deposited | D22: =SUM(G22:J22) -> 4000 | E22: =SUM(K22:N22) -> 0 | F22: =F21+D22-E22 -> 4242.53 | G22: 4000
B23: 45777 | C23: Interest for April | D23: =SUM(G23:J23) -> 1.58 | E23: =SUM(K23:N23) -> 0 | F23: =F22+D23-E23 -> 4244.11 | H23: 1.58
B24: 45800 | C24: Cash Deposited | D24: =SUM(G24:J24) -> 2000 | E24: =SUM(K24:N24) -> 0 | F24: =F23+D24-E24 -> 6244.11 | G24: 2000
B25: 45800 | C25: Cash Deposited | D25: =SUM(G25:J25) -> 0.77 | E25: =SUM(K25:N25) -> 0 | F25: =F24+D25-E25 -> 6244.88 | H25: 0.77
B26: 45808 | C26: Interest for April 2025 | D26: =SUM(G26:J26) -> 2.82 | E26: =SUM(K26:N26) -> 0 | F26: =F25+D26-E26 -> 6247.7 | H26: 2.82
B27: 45824 | C27: Cash Deposited | D27: =SUM(G27:J27) -> 2300 | E27: =SUM(K27:N27) -> 0 | F27: =F26+D27-E27 -> 8547.7 | G27: 2300
B28: 45839 | C28: Interest for May 2025 | D28: =SUM(G28:J28) -> 6.09 | E28: =SUM(K28:N28) -> 0 | F28: =F27+D28-E28 -> 8553.79 | H28: 6.09
B29: 45870 | C29: Interest for June 2025 | D29: =SUM(G29:J29) -> 3.04 | E29: =SUM(K29:N29) -> 0 | F29: =F28+D29-E29 -> 8556.83 | H29: 3.04
B30: 45931 | C30: Interest for July 2025 | D30: =SUM(G30:J30) -> 7.27 | E30: =SUM(K30:N30) -> 0 | F30: =F29+D30-E30 -> 8564.1 | H30: 7.27
B31: 45902 | C31: Interest for August 2025 | D31: =SUM(G31:J31) -> 3.63 | E31: =SUM(K31:N31) -> 0 | F31: =F30+D31-E31 -> 8567.73 | H31: 3.63
B32: 45875 | C32: Cash Deposited | D32: =SUM(G32:J32) -> 2000 | E32: =SUM(K32:N32) -> 0 | F32: =F31+D32-E32 -> 10567.73 | G32: 2000
B33: 45875 | C33: Deposit of Treasurer Bill | D33: =SUM(G33:J33) -> 0 | E33: =SUM(K33:N33) -> 10000 | F33: =F32+D33-E33 -> 567.73 | K33: 10000
B34: 45901 | C34: Interest for September 2025 | D34: =SUM(G34:J34) -> 0.59 | F34: =F33+D34-E34 -> 568.32 | H34: 0.59
B35: 45904 | C35: Cash Deposited | D35: =SUM(G35:J35) -> 5000 | E35: =SUM(K35:N35) -> 0 | F35: =F34+D35-E35 -> 5568.32 | G35: ='PAYMENT VOUCHERS'!E150 -> 5000
B36: 45876 | C36: Purchase of Treasure Bill | D36: =SUM(G36:J36) -> 2.06 | E36: =SUM(K36:N36) -> 0 | F36: =F35+D36-E36 -> 5570.38 | H36: 2.06
B37: 45930 | C37: Interest for October 2025 | D37: =SUM(G37:J37) -> 2.36 | E37: =SUM(K37:N37) -> 0 | F37: =F36+D37-E37 -> 5572.74 | H37: 2.36
B38: 45961 | C38: Interest for November 2025 | D38: =SUM(G38:J38) -> 2.29 | E38: =SUM(K38:N38) -> 0 | F38: =F37+D38-E38 -> 5575.03 | H38: 2.29
B39: 46008 | C39: Cash Deposited | D39: =SUM(G39:J39) -> 3600 | E39: =SUM(K39:N39) -> 0 | F39: =F38+D39-E39 -> 9175.03 | G39: 3600
B40: 46022 | C40: Interest for December 2025 | D40: =SUM(G40:J40) -> 1.1 | E40: =SUM(K40:N40) -> 0 | F40: =F39+D40-E40 -> 9176.13 | H40: 1.1
B41: 46041 | C41: Cash Deposited | D41: =SUM(G41:J41) -> 3000 | E41: =SUM(K41:N41) -> 0 | F41: =F40+D41-E41 -> 12176.13 | G41: 3000
B42: 46081 | C42: Interest for January & February 2026 | D42: =SUM(G42:J42) -> 9.1 | E42: =SUM(K42:N42) -> 0 | F42: =F41+D42-E42 -> 12185.23 | H42: 9.1
B43: 46086 | C43: Cash Deposited | D43: =SUM(G43:J43) -> 2000 | E43: =SUM(K43:N43) -> 0 | F43: =F42+D43-E43 -> 14185.23 | G43: ='PAYMENT VOUCHERS'!E174 -> 2000
B44: 46092 | C44: Cash Deposited | D44: =SUM(G44:J44) -> 2000 | E44: =SUM(K44:N44) -> 0 | F44: =F43+D44-E44 -> 16185.23 | G44: 2000
B45: 46098 | C45: Deposit of Treasurer Bill | D45: =SUM(G45:J45) -> 0 | E45: =SUM(K45:N45) -> 16000 | F45: =F44+D45-E45 -> 185.23 | K45: 16000
B46: 46107 | C46: Reverse of all Treasurer Bill | D46: =SUM(G46:J46) -> 62425.51 | E46: =SUM(K46:N46) -> 0 | F46: =F45+D46-E46 -> 62610.74 | I46: 62425.51
B47: 46108 | C47: Cash Withdrawal to Purchases A/C | D47: =SUM(G47:J47) -> 0 | E47: =SUM(K47:N47) -> 62000 | F47: =F46+D47-E47 -> 610.74 | L47: 62000
B48: 46108 | C48: Cash Withdrawal to MoMo A/C | D48: =SUM(G48:J48) -> 0 | E48: =SUM(K48:N48) -> 400 | F48: =F47+D48-E48 -> 210.74 | L48: 400
B49: 46108 | C49: Bank Charges CCW | D49: =SUM(G49:J49) -> 0 | E49: =SUM(K49:N49) -> 15 | F49: =F48+D49-E49 -> 195.74 | M49: 15
B50: 46111 | C50: Interest for March 2026 | D50: =SUM(G50:J50) -> 3.14 | E50: =SUM(K50:N50) -> 0 | F50: =F49+D50-E50 -> 198.88 | H50: 3.14
B51: 46129 | C51: Cash Deposited | D51: =SUM(G51:J51) -> 4000 | E51: =SUM(K51:N51) -> 0 | F51: =F50+D51-E51 -> 4198.88 | G51: ='PAYMENT VOUCHERS'!E194 -> 4000
B52: 46260 | C52: Cash Deposited | D52: =SUM(G52:J52) -> 4500 | E52: =SUM(K52:N52) -> 0 | F52: =F51+D52-E52 -> 8698.88 | G52: ='PAYMENT VOUCHERS'!E202 -> 4500
B53: 46289 | C53: Cash Deposited | D53: =SUM(G53:J53) -> 2000 | E53: =SUM(K53:N53) -> 0 | F53: =F52+D53-E53 -> 10698.88 | G53: ='PAYMENT VOUCHERS'!E210 -> 2000
D54: =SUM(G54:J54) -> 0 | E54: =SUM(K54:N54) -> 0 | F54: =F53+D54-E54 -> 10698.88
D55: =SUM(G55:J55) -> 0 | E55: =SUM(K55:N55) -> 0 | F55: =F54+D55-E55 -> 10698.88
D56: =SUM(G56:J56) -> 0 | E56: =SUM(K56:N56) -> 0 | F56: =F55+D56-E56 -> 10698.88
D57: =SUM(G57:J57) -> 0 | E57: =SUM(K57:N57) -> 0 | F57: =F56+D57-E57 -> 10698.88
D58: =SUM(G58:J58) -> 0 | E58: =SUM(K58:N58) -> 0 | F58: =F57+D58-E58 -> 10698.88
D59: =SUM(G59:J59) -> 0 | E59: =SUM(K59:N59) -> 0 | F59: =F58+D59-E59 -> 10698.88
D60: =SUM(G60:J60) -> 0 | E60: =SUM(K60:N60) -> 0 | F60: =F59+D60-E60 -> 10698.88
D61: =SUM(G61:J61) -> 0 | E61: =SUM(K61:N61) -> 0 | F61: =F60+D61-E61 -> 10698.88
D62: =SUM(G62:J62) -> 0 | E62: =SUM(K62:N62) -> 0 | F62: =F61+D62-E62 -> 10698.88
D63: =SUM(G63:J63) -> 0 | E63: =SUM(K63:N63) -> 0 | F63: =F62+D63-E63 -> 10698.88
D64: =SUM(G64:J64) -> 0 | E64: =SUM(K64:N64) -> 0 | F64: =F63+D64-E64 -> 10698.88
D65: =SUM(G65:J65) -> 0 | E65: =SUM(K65:N65) -> 0 | F65: =F64+D65-E65 -> 10698.88
D66: =SUM(G66:J66) -> 0 | E66: =SUM(K66:N66) -> 0 | F66: =F65+D66-E66 -> 10698.88
B67: =SUBTOTAL(3,B6:B66) -> 48 | C67: =SUBTOTAL(3,C6:C66) -> 48 | D67: =SUBTOTAL(9,D6:D66) -> 125113.88 | E67: =SUBTOTAL(9,E6:E66) -> 114415 | F67: =D67-E67 -> 10698.88 | G67: =SUBTOTAL(9,G6:G66) -> 62600 | H67: =SUBTOTAL(9,H6:H66) -> 88.37 | I67: =SUBTOTAL(9,I6:I66) -> 62425.51 | J67: =SUBTOTAL(9,J6:J66) -> 0 | K67: =SUBTOTAL(9,K6:K66) -> 52000 | L67: =SUBTOTAL(9,L6:L66) -> 62400 | M67: =SUBTOTAL(9,M6:M66) -> 15 | N67: =SUBTOTAL(9,N6:N66) -> 0

Sheet BANK ACCOUNT TEMA
B3: NORTH TEMA CO-OPERATIVE CREDIT UNION LIMITED
B4: DATE | C4: PARTICULARS | D4: INCOME | E4: EXPENSES | F4: BALANCE | G4: SAVINGS | H4: SHARES | I4: BANK | J4: CURRENT | K4: WITHDRAWAL
C5: 2161006002421201 | I5: INTREST | J5: ACCOUNT
C6: 217xxxxxxxxxxx01 | D6: ¢ | E6: ¢ | F6: ¢ | G6: ¢ | H6: ¢ | I6: ¢ | J6: ¢ | K6: ¢ | N6: ¢
B7: 45022 | C7: Cash Deposited | D7: =SUM(G7:J7) -> 5400 | F7: =D7 -> 5400 | G7: 5400
B8: 45022 | C8: Shares from the Bank | D8: =SUM(G8:J8) -> 100 | F8: =F7+D8-E8 -> 5500 | H8: 100
B9: 45049 | C9: Cash Deposited | D9: =SUM(G9:J9) -> 100 | F9: =F8+D9-E9 -> 5600 | G9: 100
B10: 45291 | C10: Bank Interest for the year | D10: =SUM(G10:J10) -> 166.24 | F10: =F9+D10-E10 -> 5766.24 | I10: 166.24
B11: 45349 | C11: Cash Withdrawal | D11: =SUM(G11:J11) -> 0 | E11: =SUM(K11:N11) -> 5400 | F11: =F10+D11-E11 -> 366.24 | K11: 5400
D12: =SUM(G12:J12) -> 0 | E12: =SUM(K12:N12) -> 0 | F12: =F11+D12-E12 -> 366.24
D13: =SUM(G13:J13) -> 0 | E13: =SUM(K13:N13) -> 0 | F13: =F12+D13-E13 -> 366.24
E14: =SUM(K14:N14) -> 0 | F14: =F13+D14-E14 -> 366.24
E15: =SUM(K15:N15) -> 0 | F15: =F14+D15-E15 -> 366.24
E16: =SUM(K16:N16) -> 0 | F16: =F15+D16-E16 -> 366.24
E17: =SUM(K17:N17) -> 0 | F17: =F16+D17-E17 -> 366.24
E18: =SUM(K18:N18) -> 0 | F18: =F17+D18-E18 -> 366.24
E19: =SUM(K19:N19) -> 0 | F19: =F18+D19-E19 -> 366.24
E20: =SUM(K20:N20) -> 0 | F20: =F19+D20-E20 -> 366.24
B22: =SUBTOTAL(3,B7:B21) -> 5 | C22: =SUBTOTAL(3,C7:C21) -> 5 | D22: =SUBTOTAL(9,D7:D21) -> 5766.24 | E22: =SUBTOTAL(9,E7:E21) -> 5400 | F22: =D22-E22 -> 366.24 | G22: =SUBTOTAL(9,G7:G21) -> 5500 | H22: =SUBTOTAL(9,H7:H21) -> 100 | I22: =SUBTOTAL(9,I7:I21) -> 166.24 | J22: =SUBTOTAL(9,J7:J21) -> 0 | K22: =SUBTOTAL(9,K7:K21) -> 5400 | L22: =SUBTOTAL(9,L7:L21) -> 0 | M22: =SUBTOTAL(9,M7:M21) -> 0 | N22: =SUBTOTAL(9,N7:N21) -> 0

Sheet CHRCK YOUR DUES BALANCE
B1: -
C5: CHRCK YOUR DUES BALANCE
B6: NO. | C6: NAME | D6: CONTACT ADDRESS | E6: REMARKS | F6: DUES | G6: AMOUNT PAID | H6: BALANCE | I6: DUES 2023 | J6: DUES 2024 | K6: DUES 2025 | L6: DUES 2026 | M6: DUES 2027 | O6: 0546516913
F7: ¢ | G7: ¢ | H7: ¢ | I7: ¢ | J7: ¢ | K7: ¢
B8: 1 | C8: Isaac Darko | D8: =IFERROR(VLOOKUP($C8,'MEMBERS LIST'!$C$5:$I$29,7,0),0) -> 054 726 1159 | E8: =IF(H8>=2000,"REMOVED",IF(H8>=1000,"INACTIVE",IF(H8>=600,"PROBATION","ACTIVE"))) -> ACTIVE | F8: =IFERROR(VLOOKUP($C8,'YEARLY DUES FEES'!$C$5:$D$29,2,0),0) -> 3900 | G8: =SUM(I8:M8) -> 3900 | H8: =F8-G8 -> 0 | I8: =IFERROR(VLOOKUP($C8,'MONTHLY DUES 2023'!$C$5:$D$24,2,0),0) -> 600 | J8: =IFERROR(VLOOKUP($C8,'MONTHLY DUES 2024'!$C$5:$D$24,2,0),0) -> 900 | K8: =IFERROR(VLOOKUP($C8,'MONTHLY DUES 2025'!$C$5:$D$27,2,0),0) -> 1200 | L8: =IFERROR(VLOOKUP($C8,'MONTHLY DUES 2026'!$C$5:$D$25,2,0),0) -> 1200 | M8: =IFERROR(VLOOKUP($C8,'MONTHLY DUES 2027'!$C$5:$D$25,2,0),0) -> 0
B9: 2 | C9: Isaac Donkor | D9: =IFERROR(VLOOKUP($C9,'MEMBERS LIST'!$C$5:$I$29,7,0),0) -> 024 310 9072 | E9: =IF(H9>=2000,"REMOVED",IF(H9>=1000,"INACTIVE",IF(H9>=600,"PROBATION","ACTIVE"))) -> ACTIVE | F9: =IFERROR(VLOOKUP($C9,'YEARLY DUES FEES'!$C$5:$D$29,2,0),0) -> 3300 | G9: =SUM(I9:M9) -> 3300 | H9: =F9-G9 -> 0 | I9: =IFERROR(VLOOKUP($C9,'MONTHLY DUES 2023'!$C$5:$D$24,2,0),0) -> 0 | J9: =IFERROR(VLOOKUP($C9,'MONTHLY DUES 2024'!$C$5:$D$24,2,0),0) -> 900 | K9: =IFERROR(VLOOKUP($C9,'MONTHLY DUES 2025'!$C$5:$D$27,2,0),0) -> 1200 | L9: =IFERROR(VLOOKUP($C9,'MONTHLY DUES 2026'!$C$5:$D$25,2,0),0) -> 1200 | M9: =IFERROR(VLOOKUP($C9,'MONTHLY DUES 2027'!$C$5:$D$25,2,0),0) -> 0
B10: 3 | C10: Jonathan Danso Siaw | D10: =IFERROR(VLOOKUP($C10,'MEMBERS LIST'!$C$5:$I$29,7,0),0) -> 024 214 5516 | E10: =IF(H10>=2000,"REMOVED",IF(H10>=1000,"INACTIVE",IF(H10>=600,"PROBATION","ACTIVE"))) -> ACTIVE | F10: =IFERROR(VLOOKUP($C10,'YEARLY DUES FEES'!$C$5:$D$29,2,0),0) -> 3900 | G10: =SUM(I10:M10) -> 3900 | H10: =F10-G10 -> 0 | I10: =IFERROR(VLOOKUP($C10,'MONTHLY DUES 2023'!$C$5:$D$24,2,0),0) -> 600 | J10: =IFERROR(VLOOKUP($C10,'MONTHLY DUES 2024'!$C$5:$D$24,2,0),0) -> 900 | K10: =IFERROR(VLOOKUP($C10,'MONTHLY DUES 2025'!$C$5:$D$27,2,0),0) -> 1200 | L10: =IFERROR(VLOOKUP($C10,'MONTHLY DUES 2026'!$C$5:$D$25,2,0),0) -> 1200 | M10: =IFERROR(VLOOKUP($C10,'MONTHLY DUES 2027'!$C$5:$D$25,2,0),0) -> 0
B11: 4 | C11: Moses Oduro | D11: =IFERROR(VLOOKUP($C11,'MEMBERS LIST'!$C$5:$I$29,7,0),0) -> 020 354 1966 | E11: =IF(H11>=2000,"REMOVED",IF(H11>=1000,"INACTIVE",IF(H11>=600,"PROBATION","ACTIVE"))) -> ACTIVE | F11: =IFERROR(VLOOKUP($C11,'YEARLY DUES FEES'!$C$5:$D$29,2,0),0) -> 3900 | G11: =SUM(I11:M11) -> 3900 | H11: =F11-G11 -> 0 | I11: =IFERROR(VLOOKUP($C11,'MONTHLY DUES 2023'!$C$5:$D$24,2,0),0) -> 600 | J11: =IFERROR(VLOOKUP($C11,'MONTHLY DUES 2024'!$C$5:$D$24,2,0),0) -> 900 | K11: =IFERROR(VLOOKUP($C11,'MONTHLY DUES 2025'!$C$5:$D$27,2,0),0) -> 1200 | L11: =IFERROR(VLOOKUP($C11,'MONTHLY DUES 2026'!$C$5:$D$25,2,0),0) -> 1200 | M11: =IFERROR(VLOOKUP($C11,'MONTHLY DUES 2027'!$C$5:$D$25,2,0),0) -> 0
B12: 5 | C12: William Kojo Anane | D12: =IFERROR(VLOOKUP($C12,'MEMBERS LIST'!$C$5:$I$29,7,0),0) -> 026 956 3876 | E12: =IF(H12>=2000,"REMOVED",IF(H12>=1000,"INACTIVE",IF(H12>=600,"PROBATION","ACTIVE"))) -> ACTIVE | F12: =IFERROR(VLOOKUP($C12,'YEARLY DUES FEES'!$C$5:$D$29,2,0),0) -> 3900 | G12: =SUM(I12:M12) -> 3900 | H12: =F12-G12 -> 0 | I12: =IFERROR(VLOOKUP($C12,'MONTHLY DUES 2023'!$C$5:$D$24,2,0),0) -> 600 | J12: =IFERROR(VLOOKUP($C12,'MONTHLY DUES 2024'!$C$5:$D$24,2,0),0) -> 900 | K12: =IFERROR(VLOOKUP($C12,'MONTHLY DUES 2025'!$C$5:$D$27,2,0),0) -> 1200 | L12: =IFERROR(VLOOKUP($C12,'MONTHLY DUES 2026'!$C$5:$D$25,2,0),0) -> 1200 | M12: =IFERROR(VLOOKUP($C12,'MONTHLY DUES 2027'!$C$5:$D$25,2,0),0) -> 0
B13: 6 | C13: Maxwell Ofei Siaw | D13: =IFERROR(VLOOKUP($C13,'MEMBERS LIST'!$C$5:$I$29,7,0),0) -> 024 788 0895 | E13: =IF(H13>=2000,"REMOVED",IF(H13>=1000,"INACTIVE",IF(H13>=600,"PROBATION","ACTIVE"))) -> ACTIVE | F13: =IFERROR(VLOOKUP($C13,'YEARLY DUES FEES'!$C$5:$D$29,2,0),0) -> 3900 | G13: =SUM(I13:M13) -> 3700 | H13: =F13-G13 -> 200 | I13: =IFERROR(VLOOKUP($C13,'MONTHLY DUES 2023'!$C$5:$D$24,2,0),0) -> 600 | J13: =IFERROR(VLOOKUP($C13,'MONTHLY DUES 2024'!$C$5:$D$24,2,0),0) -> 900 | K13: =IFERROR(VLOOKUP($C13,'MONTHLY DUES 2025'!$C$5:$D$27,2,0),0) -> 1200 | L13: =IFERROR(VLOOKUP($C13,'MONTHLY DUES 2026'!$C$5:$D$25,2,0),0) -> 1000 | M13: =IFERROR(VLOOKUP($C13,'MONTHLY DUES 2027'!$C$5:$D$25,2,0),0) -> 0
B14: 7 | C14: Vincent Agamatey | D14: =IFERROR(VLOOKUP($C14,'MEMBERS LIST'!$C$5:$I$29,7,0),0) -> 024 406 7032 | E14: =IF(H14>=2000,"REMOVED",IF(H14>=1000,"INACTIVE",IF(H14>=600,"PROBATION","ACTIVE"))) -> ACTIVE | F14: =IFERROR(VLOOKUP($C14,'YEARLY DUES FEES'!$C$5:$D$29,2,0),0) -> 3900 | G14: =SUM(I14:M14) -> 3700 | H14: =F14-G14 -> 200 | I14: =IFERROR(VLOOKUP($C14,'MONTHLY DUES 2023'!$C$5:$D$24,2,0),0) -> 600 | J14: =IFERROR(VLOOKUP($C14,'MONTHLY DUES 2024'!$C$5:$D$24,2,0),0) -> 900 | K14: =IFERROR(VLOOKUP($C14,'MONTHLY DUES 2025'!$C$5:$D$27,2,0),0) -> 1200 | L14: =IFERROR(VLOOKUP($C14,'MONTHLY DUES 2026'!$C$5:$D$25,2,0),0) -> 1000 | M14: =IFERROR(VLOOKUP($C14,'MONTHLY DUES 2027'!$C$5:$D$25,2,0),0) -> 0
B15: 8 | C15: Alex Ackah | D15: =IFERROR(VLOOKUP($C15,'MEMBERS LIST'!$C$5:$I$29,7,0),0) -> 024 343 0617 | E15: =IF(H15>=2000,"REMOVED",IF(H15>=1000,"INACTIVE",IF(H15>=600,"PROBATION","ACTIVE"))) -> ACTIVE | F15: =IFERROR(VLOOKUP($C15,'YEARLY DUES FEES'!$C$5:$D$29,2,0),0) -> 3300 | G15: =SUM(I15:M15) -> 3000 | H15: =F15-G15 -> 300 | I15: =IFERROR(VLOOKUP($C15,'MONTHLY DUES 2023'!$C$5:$D$24,2,0),0) -> 0 | J15: =IFERROR(VLOOKUP($C15,'MONTHLY DUES 2024'!$C$5:$D$24,2,0),0) -> 900 | K15: =IFERROR(VLOOKUP($C15,'MONTHLY DUES 2025'!$C$5:$D$27,2,0),0) -> 1200 | L15: =IFERROR(VLOOKUP($C15,'MONTHLY DUES 2026'!$C$5:$D$25,2,0),0) -> 900 | M15: =IFERROR(VLOOKUP($C15,'MONTHLY DUES 2027'!$C$5:$D$25,2,0),0) -> 0
B16: 9 | C16: John Aidoo | D16: =IFERROR(VLOOKUP($C16,'MEMBERS LIST'!$C$5:$I$29,7,0),0) -> 024 312 9927 | E16: =IF(H16>=2000,"REMOVED",IF(H16>=1000,"INACTIVE",IF(H16>=600,"PROBATION","ACTIVE"))) -> ACTIVE | F16: =IFERROR(VLOOKUP($C16,'YEARLY DUES FEES'!$C$5:$D$29,2,0),0) -> 1200 | G16: =SUM(I16:M16) -> 900 | H16: =F16-G16 -> 300 | I16: =IFERROR(VLOOKUP($C16,'MONTHLY DUES 2023'!$C$5:$D$24,2,0),0) -> 0 | J16: =IFERROR(VLOOKUP($C16,'MONTHLY DUES 2024'!$C$5:$D$24,2,0),0) -> 0 | K16: =IFERROR(VLOOKUP($C16,'MONTHLY DUES 2025'!$C$5:$D$27,2,0),0) -> 0 | L16: =IFERROR(VLOOKUP($C16,'MONTHLY DUES 2026'!$C$5:$D$25,2,0),0) -> 900 | M16: =IFERROR(VLOOKUP($C16,'MONTHLY DUES 2027'!$C$5:$D$25,2,0),0) -> 0
B17: 10 | C17: Jonas Wereko | D17: =IFERROR(VLOOKUP($C17,'MEMBERS LIST'!$C$5:$I$29,7,0),0) -> 024 453 3372 | E17: =IF(H17>=2000,"REMOVED",IF(H17>=1000,"INACTIVE",IF(H17>=600,"PROBATION","ACTIVE"))) -> ACTIVE | F17: =IFERROR(VLOOKUP($C17,'YEARLY DUES FEES'!$C$5:$D$29,2,0),0) -> 3900 | G17: =SUM(I17:M17) -> 3600 | H17: =F17-G17 -> 300 | I17: =IFERROR(VLOOKUP($C17,'MONTHLY DUES 2023'!$C$5:$D$24,2,0),0) -> 600 | J17: =IFERROR(VLOOKUP($C17,'MONTHLY DUES 2024'!$C$5:$D$24,2,0),0) -> 900 | K17: =IFERROR(VLOOKUP($C17,'MONTHLY DUES 2025'!$C$5:$D$27,2,0),0) -> 1200 | L17: =IFERROR(VLOOKUP($C17,'MONTHLY DUES 2026'!$C$5:$D$25,2,0),0) -> 900 | M17: =IFERROR(VLOOKUP($C17,'MONTHLY DUES 2027'!$C$5:$D$25,2,0),0) -> 0
B18: 11 | C18: Johnson Wood | D18: =IFERROR(VLOOKUP($C18,'MEMBERS LIST'!$C$5:$I$29,7,0),0) -> 024 046 6830 | E18: =IF(H18>=2000,"REMOVED",IF(H18>=1000,"INACTIVE",IF(H18>=600,"PROBATION","ACTIVE"))) -> ACTIVE | F18: =IFERROR(VLOOKUP($C18,'YEARLY DUES FEES'!$C$5:$D$29,2,0),0) -> 3900 | G18: =SUM(I18:M18) -> 3500 | H18: =F18-G18 -> 400 | I18: =IFERROR(VLOOKUP($C18,'MONTHLY DUES 2023'!$C$5:$D$24,2,0),0) -> 600 | J18: =IFERROR(VLOOKUP($C18,'MONTHLY DUES 2024'!$C$5:$D$24,2,0),0) -> 900 | K18: =IFERROR(VLOOKUP($C18,'MONTHLY DUES 2025'!$C$5:$D$27,2,0),0) -> 1200 | L18: =IFERROR(VLOOKUP($C18,'MONTHLY DUES 2026'!$C$5:$D$25,2,0),0) -> 800 | M18: =IFERROR(VLOOKUP($C18,'MONTHLY DUES 2027'!$C$5:$D$25,2,0),0) -> 0
B19: 12 | C19: Osei Kwame | D19: =IFERROR(VLOOKUP($C19,'MEMBERS LIST'!$C$5:$I$29,7,0),0) -> 024 428 3224 | E19: =IF(H19>=2000,"REMOVED",IF(H19>=1000,"INACTIVE",IF(H19>=600,"PROBATION","ACTIVE"))) -> ACTIVE | F19: =IFERROR(VLOOKUP($C19,'YEARLY DUES FEES'!$C$5:$D$29,2,0),0) -> 3900 | G19: =SUM(I19:M19) -> 3500 | H19: =F19-G19 -> 400 | I19: =IFERROR(VLOOKUP($C19,'MONTHLY DUES 2023'!$C$5:$D$24,2,0),0) -> 600 | J19: =IFERROR(VLOOKUP($C19,'MONTHLY DUES 2024'!$C$5:$D$24,2,0),0) -> 900 | K19: =IFERROR(VLOOKUP($C19,'MONTHLY DUES 2025'!$C$5:$D$27,2,0),0) -> 1200 | L19: =IFERROR(VLOOKUP($C19,'MONTHLY DUES 2026'!$C$5:$D$25,2,0),0) -> 800 | M19: =IFERROR(VLOOKUP($C19,'MONTHLY DUES 2027'!$C$5:$D$25,2,0),0) -> 0
B20: 13 | C20: Fanuel Hagan | D20: =IFERROR(VLOOKUP($C20,'MEMBERS LIST'!$C$5:$I$29,7,0),0) -> 024 418 1735 | E20: =IF(H20>=2000,"REMOVED",IF(H20>=1000,"INACTIVE",IF(H20>=600,"PROBATION","ACTIVE"))) -> ACTIVE | F20: =IFERROR(VLOOKUP($C20,'YEARLY DUES FEES'!$C$5:$D$29,2,0),0) -> 3900 | G20: =SUM(I20:M20) -> 3400 | H20: =F20-G20 -> 500 | I20: =IFERROR(VLOOKUP($C20,'MONTHLY DUES 2023'!$C$5:$D$24,2,0),0) -> 600 | J20: =IFERROR(VLOOKUP($C20,'MONTHLY DUES 2024'!$C$5:$D$24,2,0),0) -> 900 | K20: =IFERROR(VLOOKUP($C20,'MONTHLY DUES 2025'!$C$5:$D$27,2,0),0) -> 1200 | L20: =IFERROR(VLOOKUP($C20,'MONTHLY DUES 2026'!$C$5:$D$25,2,0),0) -> 700 | M20: =IFERROR(VLOOKUP($C20,'MONTHLY DUES 2027'!$C$5:$D$25,2,0),0) -> 0
A21: ` | B21: 14 | C21: Frederick Wortey Tawiah | D21: =IFERROR(VLOOKUP($C21,'MEMBERS LIST'!$C$5:$I$29,7,0),0) -> 055 376 1600 | E21: =IF(H21>=2000,"REMOVED",IF(H21>=1000,"INACTIVE",IF(H21>=600,"PROBATION","ACTIVE"))) -> ACTIVE | F21: =IFERROR(VLOOKUP($C21,'YEARLY DUES FEES'!$C$5:$D$29,2,0),0) -> 3900 | G21: =SUM(I21:M21) -> 3400 | H21: =F21-G21 -> 500 | I21: =IFERROR(VLOOKUP($C21,'MONTHLY DUES 2023'!$C$5:$D$24,2,0),0) -> 600 | J21: =IFERROR(VLOOKUP($C21,'MONTHLY DUES 2024'!$C$5:$D$24,2,0),0) -> 900 | K21: =IFERROR(VLOOKUP($C21,'MONTHLY DUES 2025'!$C$5:$D$27,2,0),0) -> 1200 | L21: =IFERROR(VLOOKUP($C21,'MONTHLY DUES 2026'!$C$5:$D$25,2,0),0) -> 700 | M21: =IFERROR(VLOOKUP($C21,'MONTHLY DUES 2027'!$C$5:$D$25,2,0),0) -> 0
B22: 15 | C22: John Ofosuhene Asare | D22: =IFERROR(VLOOKUP($C22,'MEMBERS LIST'!$C$5:$I$29,7,0),0) -> 024 292 7915 | E22: =IF(H22>=2000,"REMOVED",IF(H22>=1000,"INACTIVE",IF(H22>=600,"PROBATION","ACTIVE"))) -> ACTIVE | F22: =IFERROR(VLOOKUP($C22,'YEARLY DUES FEES'!$C$5:$D$29,2,0),0) -> 3900 | G22: =SUM(I22:M22) -> 3400 | H22: =F22-G22 -> 500 | I22: =IFERROR(VLOOKUP($C22,'MONTHLY DUES 2023'!$C$5:$D$24,2,0),0) -> 600 | J22: =IFERROR(VLOOKUP($C22,'MONTHLY DUES 2024'!$C$5:$D$24,2,0),0) -> 900 | K22: =IFERROR(VLOOKUP($C22,'MONTHLY DUES 2025'!$C$5:$D$27,2,0),0) -> 1200 | L22: =IFERROR(VLOOKUP($C22,'MONTHLY DUES 2026'!$C$5:$D$25,2,0),0) -> 700 | M22: =IFERROR(VLOOKUP($C22,'MONTHLY DUES 2027'!$C$5:$D$25,2,0),0) -> 0
B23: 16 | C23: Prince Asante Ahwireng | D23: =IFERROR(VLOOKUP($C23,'MEMBERS LIST'!$C$5:$I$29,7,0),0) -> 054 864 5220 | E23: =IF(H23>=2000,"REMOVED",IF(H23>=1000,"INACTIVE",IF(H23>=600,"PROBATION","ACTIVE"))) -> PROBATION | F23: =IFERROR(VLOOKUP($C23,'YEARLY DUES FEES'!$C$5:$D$29,2,0),0) -> 3900 | G23: =SUM(I23:M23) -> 3300 | H23: =F23-G23 -> 600 | I23: =IFERROR(VLOOKUP($C23,'MONTHLY DUES 2023'!$C$5:$D$24,2,0),0) -> 600 | J23: =IFERROR(VLOOKUP($C23,'MONTHLY DUES 2024'!$C$5:$D$24,2,0),0) -> 900 | K23: =IFERROR(VLOOKUP($C23,'MONTHLY DUES 2025'!$C$5:$D$27,2,0),0) -> 1200 | L23: =IFERROR(VLOOKUP($C23,'MONTHLY DUES 2026'!$C$5:$D$25,2,0),0) -> 600 | M23: =IFERROR(VLOOKUP($C23,'MONTHLY DUES 2027'!$C$5:$D$25,2,0),0) -> 0
B24: 17 | C24: Danso Kingsley | D24: =IFERROR(VLOOKUP($C24,'MEMBERS LIST'!$C$5:$I$29,7,0),0) -> 024 499 1855 | E24: =IF(H24>=2000,"REMOVED",IF(H24>=1000,"INACTIVE",IF(H24>=600,"PROBATION","ACTIVE"))) -> PROBATION | F24: =IFERROR(VLOOKUP($C24,'YEARLY DUES FEES'!$C$5:$D$29,2,0),0) -> 2400 | G24: =SUM(I24:M24) -> 1500 | H24: =F24-G24 -> 900 | K24: =IFERROR(VLOOKUP($C24,'MONTHLY DUES 2025'!$C$5:$D$27,2,0),0) -> 1200 | L24: =IFERROR(VLOOKUP($C24,'MONTHLY DUES 2026'!$C$5:$D$25,2,0),0) -> 300 | M24: =IFERROR(VLOOKUP($C24,'MONTHLY DUES 2027'!$C$5:$D$25,2,0),0) -> 0
B25: 18 | C25: Just-Mark Kwabena Quansah | D25: =IFERROR(VLOOKUP($C25,'MEMBERS LIST'!$C$5:$I$29,7,0),0) -> 026 746 1029 | E25: =IF(H25>=2000,"REMOVED",IF(H25>=1000,"INACTIVE",IF(H25>=600,"PROBATION","ACTIVE"))) -> PROBATION | F25: =IFERROR(VLOOKUP($C25,'YEARLY DUES FEES'!$C$5:$D$29,2,0),0) -> 3900 | G25: =SUM(I25:M25) -> 3000 | H25: =F25-G25 -> 900 | I25: =IFERROR(VLOOKUP($C25,'MONTHLY DUES 2023'!$C$5:$D$24,2,0),0) -> 600 | J25: =IFERROR(VLOOKUP($C25,'MONTHLY DUES 2024'!$C$5:$D$24,2,0),0) -> 900 | K25: =IFERROR(VLOOKUP($C25,'MONTHLY DUES 2025'!$C$5:$D$27,2,0),0) -> 1200 | L25: =IFERROR(VLOOKUP($C25,'MONTHLY DUES 2026'!$C$5:$D$25,2,0),0) -> 300 | M25: =IFERROR(VLOOKUP($C25,'MONTHLY DUES 2027'!$C$5:$D$25,2,0),0) -> 0
B26: 19 | C26: Justice Kojo Acheampong | D26: =IFERROR(VLOOKUP($C26,'MEMBERS LIST'!$C$5:$I$29,7,0),0) -> 024 750 5280 | E26: =IF(H26>=2000,"REMOVED",IF(H26>=1000,"INACTIVE",IF(H26>=600,"PROBATION","ACTIVE"))) -> PROBATION | F26: =IFERROR(VLOOKUP($C26,'YEARLY DUES FEES'!$C$5:$D$29,2,0),0) -> 3900 | G26: =SUM(I26:M26) -> 3000 | H26: =F26-G26 -> 900 | I26: =IFERROR(VLOOKUP($C26,'MONTHLY DUES 2023'!$C$5:$D$24,2,0),0) -> 600 | J26: =IFERROR(VLOOKUP($C26,'MONTHLY DUES 2024'!$C$5:$D$24,2,0),0) -> 900 | K26: =IFERROR(VLOOKUP($C26,'MONTHLY DUES 2025'!$C$5:$D$27,2,0),0) -> 1200 | L26: =IFERROR(VLOOKUP($C26,'MONTHLY DUES 2026'!$C$5:$D$25,2,0),0) -> 300 | M26: =IFERROR(VLOOKUP($C26,'MONTHLY DUES 2027'!$C$5:$D$25,2,0),0) -> 0
B27: 20 | C27: John Darbo | D27: =IFERROR(VLOOKUP($C27,'MEMBERS LIST'!$C$5:$I$29,7,0),0) -> 055 733 6020 | E27: =IF(H27>=2000,"REMOVED",IF(H27>=1000,"INACTIVE",IF(H27>=600,"PROBATION","ACTIVE"))) -> REMOVED | F27: =IFERROR(VLOOKUP($C27,'YEARLY DUES FEES'!$C$5:$D$29,2,0),0) -> 2400 | G27: =SUM(I27:M27) -> 350 | H27: =F27-G27 -> 2050 | I27: =IFERROR(VLOOKUP($C27,'MONTHLY DUES 2023'!$C$5:$D$24,2,0),0) -> 0 | J27: =IFERROR(VLOOKUP($C27,'MONTHLY DUES 2024'!$C$5:$D$24,2,0),0) -> 0 | K27: =IFERROR(VLOOKUP($C27,'MONTHLY DUES 2025'!$C$5:$D$27,2,0),0) -> 350 | L27: =IFERROR(VLOOKUP($C27,'MONTHLY DUES 2026'!$C$5:$D$25,2,0),0) -> 0 | M27: =IFERROR(VLOOKUP($C27,'MONTHLY DUES 2027'!$C$5:$D$25,2,0),0) -> 0
B28: 21 | C28: George Yeboah | D28: =IFERROR(VLOOKUP($C28,'MEMBERS LIST'!$C$5:$I$29,7,0),0) -> 050 178 6106 | E28: =IF(H28>=2000,"REMOVED",IF(H28>=1000,"INACTIVE",IF(H28>=600,"PROBATION","ACTIVE"))) -> REMOVED | F28: =IFERROR(VLOOKUP($C28,'YEARLY DUES FEES'!$C$5:$D$29,2,0),0) -> 2400 | G28: =SUM(I28:M28) -> 200 | H28: =F28-G28 -> 2200 | I28: =IFERROR(VLOOKUP($C28,'MONTHLY DUES 2023'!$C$5:$D$24,2,0),0) -> 0 | J28: =IFERROR(VLOOKUP($C28,'MONTHLY DUES 2024'!$C$5:$D$24,2,0),0) -> 0 | K28: =IFERROR(VLOOKUP($C28,'MONTHLY DUES 2025'!$C$5:$D$27,2,0),0) -> 200 | L28: =IFERROR(VLOOKUP($C28,'MONTHLY DUES 2026'!$C$5:$D$25,2,0),0) -> 0 | M28: =IFERROR(VLOOKUP($C28,'MONTHLY DUES 2027'!$C$5:$D$25,2,0),0) -> 0
B29: 22 | C29: Samuel Yaw Nkansah | D29: =IFERROR(VLOOKUP($C29,'MEMBERS LIST'!$C$5:$I$29,7,0),0) -> 024 656 0312 | E29: =IF(H29>=2000,"REMOVED",IF(H29>=1000,"INACTIVE",IF(H29>=600,"PROBATION","ACTIVE"))) -> REMOVED | F29: =IFERROR(VLOOKUP($C29,'YEARLY DUES FEES'!$C$5:$D$29,2,0),0) -> 3900 | G29: =SUM(I29:M29) -> 1700 | H29: =F29-G29 -> 2200 | I29: =IFERROR(VLOOKUP($C29,'MONTHLY DUES 2023'!$C$5:$D$24,2,0),0) -> 600 | J29: =IFERROR(VLOOKUP($C29,'MONTHLY DUES 2024'!$C$5:$D$24,2,0),0) -> 900 | K29: =IFERROR(VLOOKUP($C29,'MONTHLY DUES 2025'!$C$5:$D$27,2,0),0) -> 200 | L29: =IFERROR(VLOOKUP($C29,'MONTHLY DUES 2026'!$C$5:$D$25,2,0),0) -> 0 | M29: =IFERROR(VLOOKUP($C29,'MONTHLY DUES 2027'!$C$5:$D$25,2,0),0) -> 0
B30: 23 | C30: Joseph Kofi Amanfo | D30: =IFERROR(VLOOKUP($C30,'MEMBERS LIST'!$C$5:$I$29,7,0),0) -> 026 871 3230 | E30: =IF(H30>=2000,"REMOVED",IF(H30>=1000,"INACTIVE",IF(H30>=600,"PROBATION","ACTIVE"))) -> REMOVED | F30: =IFERROR(VLOOKUP($C30,'YEARLY DUES FEES'!$C$5:$D$29,2,0),0) -> 3900 | G30: =SUM(I30:M30) -> 1000 | H30: =F30-G30 -> 2900 | I30: =IFERROR(VLOOKUP($C30,'MONTHLY DUES 2023'!$C$5:$D$24,2,0),0) -> 600 | J30: =IFERROR(VLOOKUP($C30,'MONTHLY DUES 2024'!$C$5:$D$24,2,0),0) -> 400 | K30: =IFERROR(VLOOKUP($C30,'MONTHLY DUES 2025'!$C$5:$D$27,2,0),0) -> 0 | L30: =IFERROR(VLOOKUP($C30,'MONTHLY DUES 2026'!$C$5:$D$25,2,0),0) -> 0 | M30: =IFERROR(VLOOKUP($C30,'MONTHLY DUES 2027'!$C$5:$D$25,2,0),0) -> 0
B31: 24 | C31: Peter Kingsford Nkrumah | D31: =IFERROR(VLOOKUP($C31,'MEMBERS LIST'!$C$5:$I$29,7,0),0) -> 054 338 2738 | E31: =IF(H31>=2000,"REMOVED",IF(H31>=1000,"INACTIVE",IF(H31>=600,"PROBATION","ACTIVE"))) -> REMOVED | F31: =IFERROR(VLOOKUP($C31,'YEARLY DUES FEES'!$C$5:$D$29,2,0),0) -> 3900 | G31: =SUM(I31:M31) -> 900 | H31: =F31-G31 -> 3000 | I31: =IFERROR(VLOOKUP($C31,'MONTHLY DUES 2023'!$C$5:$D$24,2,0),0) -> 600 | J31: =IFERROR(VLOOKUP($C31,'MONTHLY DUES 2024'!$C$5:$D$24,2,0),0) -> 300 | K31: =IFERROR(VLOOKUP($C31,'MONTHLY DUES 2025'!$C$5:$D$27,2,0),0) -> 0 | L31: =IFERROR(VLOOKUP($C31,'MONTHLY DUES 2026'!$C$5:$D$25,2,0),0) -> 0 | M31: =IFERROR(VLOOKUP($C31,'MONTHLY DUES 2027'!$C$5:$D$25,2,0),0) -> 0
B33: TOTAL | F33: =SUM(F8:F31) -> 85200 | G33: =SUM(G8:G31) -> 65950 | H33: =SUM(H8:H31) -> 19250 | I33: =SUM(I8:I31) -> 10800 | J33: =SUM(J8:J31) -> 16900 | K33: =SUM(K8:K31) -> 22350 | L33: =SUM(L8:L31) -> 15900

Sheet CHRCK YOUR LEVY BALANCE
B1: -
C5: CHRCK YOUR LEVY BALANCE
B6: NO. | C6: NAME | D6: CONTACT ADDRESS | E6: TOTAL LEVY | F6: PAID LEVY | G6: BALANCE | H6: REMARKS
E7: ¢ | F7: ¢ | G7: ¢
B8: 1 | C8: Alex Ackah | D8: =IFERROR(VLOOKUP($C8,'MEMBERS LIST'!$C$5:$I$29,5,0),0) -> Takoradi | E8: =IFERROR(VLOOKUP($C8,' SPECIAL LEVY FEES'!$C$5:$D$29,2,0),0) -> 700 | F8: =IFERROR(VLOOKUP($C8,'SPECIAL LEVY'!$C$4:$D$28,2,0),0) -> 700 | G8: =E8-F8 -> 0 | H8: =IF(G8>=1,"REMOVED","ACTIVE") -> ACTIVE
B9: 2 | C9: Danso Kingsley | D9: =IFERROR(VLOOKUP($C9,'MEMBERS LIST'!$C$5:$I$29,5,0),0) -> Mampong | E9: =IFERROR(VLOOKUP($C9,' SPECIAL LEVY FEES'!$C$5:$D$29,2,0),0) -> 100 | F9: =IFERROR(VLOOKUP($C9,'SPECIAL LEVY'!$C$4:$D$28,2,0),0) -> 100 | G9: =E9-F9 -> 0 | H9: =IF(G9>=1,"REMOVED","ACTIVE") -> ACTIVE
B10: 3 | C10: Fanuel Hagan | D10: =IFERROR(VLOOKUP($C10,'MEMBERS LIST'!$C$5:$I$29,5,0),0) -> Mankessim | E10: =IFERROR(VLOOKUP($C10,' SPECIAL LEVY FEES'!$C$5:$D$29,2,0),0) -> 1000 | F10: =IFERROR(VLOOKUP($C10,'SPECIAL LEVY'!$C$4:$D$28,2,0),0) -> 1000 | G10: =E10-F10 -> 0 | H10: =IF(G10>=1,"REMOVED","ACTIVE") -> ACTIVE
B11: 4 | C11: Frederick Wortey Tawiah | D11: =IFERROR(VLOOKUP($C11,'MEMBERS LIST'!$C$5:$I$29,5,0),0) -> Ashaiman | E11: =IFERROR(VLOOKUP($C11,' SPECIAL LEVY FEES'!$C$5:$D$29,2,0),0) -> 1000 | F11: =IFERROR(VLOOKUP($C11,'SPECIAL LEVY'!$C$4:$D$28,2,0),0) -> 1000 | G11: =E11-F11 -> 0 | H11: =IF(G11>=1,"REMOVED","ACTIVE") -> ACTIVE
B12: 5 | C12: Isaac Donkor | D12: =IFERROR(VLOOKUP($C12,'MEMBERS LIST'!$C$5:$I$29,5,0),0) -> Suame | E12: =IFERROR(VLOOKUP($C12,' SPECIAL LEVY FEES'!$C$5:$D$29,2,0),0) -> 100 | F12: =IFERROR(VLOOKUP($C12,'SPECIAL LEVY'!$C$4:$D$28,2,0),0) -> 100 | G12: =E12-F12 -> 0 | H12: =IF(G12>=1,"REMOVED","ACTIVE") -> ACTIVE
B13: 6 | C13: John Darbo | D13: =IFERROR(VLOOKUP($C13,'MEMBERS LIST'!$C$5:$I$29,5,0),0) -> Dansoman | E13: =IFERROR(VLOOKUP($C13,' SPECIAL LEVY FEES'!$C$5:$D$29,2,0),0) -> 100 | F13: =IFERROR(VLOOKUP($C13,'SPECIAL LEVY'!$C$4:$D$28,2,0),0) -> 100 | G13: =E13-F13 -> 0 | H13: =IF(G13>=1,"REMOVED","ACTIVE") -> ACTIVE
B14: 7 | C14: John Ofosuhene Asare | D14: =IFERROR(VLOOKUP($C14,'MEMBERS LIST'!$C$5:$I$29,5,0),0) -> Kotobabi | E14: =IFERROR(VLOOKUP($C14,' SPECIAL LEVY FEES'!$C$5:$D$29,2,0),0) -> 800 | F14: =IFERROR(VLOOKUP($C14,'SPECIAL LEVY'!$C$4:$D$28,2,0),0) -> 800 | G14: =E14-F14 -> 0 | H14: =IF(G14>=1,"REMOVED","ACTIVE") -> ACTIVE
B15: 8 | C15: Johnson Wood | D15: =IFERROR(VLOOKUP($C15,'MEMBERS LIST'!$C$5:$I$29,5,0),0) -> Takoradi | E15: =IFERROR(VLOOKUP($C15,' SPECIAL LEVY FEES'!$C$5:$D$29,2,0),0) -> 1000 | F15: =IFERROR(VLOOKUP($C15,'SPECIAL LEVY'!$C$4:$D$28,2,0),0) -> 1000 | G15: =E15-F15 -> 0 | H15: =IF(G15>=1,"REMOVED","ACTIVE") -> ACTIVE
B16: 9 | C16: Jonas Wereko | D16: =IFERROR(VLOOKUP($C16,'MEMBERS LIST'!$C$5:$I$29,5,0),0) -> Atonsu | E16: =IFERROR(VLOOKUP($C16,' SPECIAL LEVY FEES'!$C$5:$D$29,2,0),0) -> 1000 | F16: =IFERROR(VLOOKUP($C16,'SPECIAL LEVY'!$C$4:$D$28,2,0),0) -> 1000 | G16: =E16-F16 -> 0 | H16: =IF(G16>=1,"REMOVED","ACTIVE") -> ACTIVE
B17: 10 | C17: Jonathan Danso Siaw | D17: =IFERROR(VLOOKUP($C17,'MEMBERS LIST'!$C$5:$I$29,5,0),0) -> Aburi | E17: =IFERROR(VLOOKUP($C17,' SPECIAL LEVY FEES'!$C$5:$D$29,2,0),0) -> 800 | F17: =IFERROR(VLOOKUP($C17,'SPECIAL LEVY'!$C$4:$D$28,2,0),0) -> 800 | G17: =E17-F17 -> 0 | H17: =IF(G17>=1,"REMOVED","ACTIVE") -> ACTIVE
B18: 11 | C18: Justice Kojo Acheampong | D18: =IFERROR(VLOOKUP($C18,'MEMBERS LIST'!$C$5:$I$29,5,0),0) -> Kasoa | E18: =IFERROR(VLOOKUP($C18,' SPECIAL LEVY FEES'!$C$5:$D$29,2,0),0) -> 1000 | F18: =IFERROR(VLOOKUP($C18,'SPECIAL LEVY'!$C$4:$D$28,2,0),0) -> 1000 | G18: =E18-F18 -> 0 | H18: =IF(G18>=1,"REMOVED","ACTIVE") -> ACTIVE
B19: 12 | C19: Just-Mark Kwabena Quansah | D19: =IFERROR(VLOOKUP($C19,'MEMBERS LIST'!$C$5:$I$29,5,0),0) -> Ashaiman | E19: =IFERROR(VLOOKUP($C19,' SPECIAL LEVY FEES'!$C$5:$D$29,2,0),0) -> 1000 | F19: =IFERROR(VLOOKUP($C19,'SPECIAL LEVY'!$C$4:$D$28,2,0),0) -> 1000 | G19: =E19-F19 -> 0 | H19: =IF(G19>=1,"REMOVED","ACTIVE") -> ACTIVE
... B25: 18 | C25: William Kojo Anane | D25: =IFERROR(VLOOKUP($C25,'MEMBERS LIST'!$C$5:$I$29,5,0),0) -> Ashaiman | E25: =IFERROR(VLOOKUP($C25,' SPECIAL LEVY FEES'!$C$5:$D$29,2,0),0) -> 1000 | F25: =IFERROR(VLOOKUP($C25,'SPECIAL LEVY'!$C$4:$D$28,2,0),0) -> 1000 | G25: =E25-F25 -> 0 | H25: =IF(G25>=1,"REMOVED","ACTIVE") -> ACTIVE
B26: 19 | C26: George Yeboah | D26: =IFERROR(VLOOKUP($C26,'MEMBERS LIST'!$C$5:$I$29,5,0),0) -> Dansoman | E26: =IFERROR(VLOOKUP($C26,' SPECIAL LEVY FEES'!$C$5:$D$29,2,0),0) -> 100 | F26: =IFERROR(VLOOKUP($C26,'SPECIAL LEVY'!$C$4:$D$28,2,0),0) -> 100 | G26: =E26-F26 -> 0 | H26: REMOVED
B27: 20 | C27: Isaac Darko | D27: =IFERROR(VLOOKUP($C27,'MEMBERS LIST'!$C$5:$I$29,5,0),0) -> Nsawam | E27: =IFERROR(VLOOKUP($C27,' SPECIAL LEVY FEES'!$C$5:$D$29,2,0),0) -> 800 | F27: =IFERROR(VLOOKUP($C27,'SPECIAL LEVY'!$C$4:$D$28,2,0),0) -> 800 | G27: =E27-F27 -> 0 | H27: REMOVED
B28: 21 | C28: Joseph Kofi Amanfo | D28: =IFERROR(VLOOKUP($C28,'MEMBERS LIST'!$C$5:$I$29,5,0),0) -> Odorkor | E28: =IFERROR(VLOOKUP($C28,' SPECIAL LEVY FEES'!$C$5:$D$29,2,0),0) -> 1000 | F28: =IFERROR(VLOOKUP($C28,'SPECIAL LEVY'!$C$4:$D$28,2,0),0) -> 1000 | G28: =E28-F28 -> 0 | H28: REMOVED
B29: 22 | C29: Peter Kingsford Nkrumah | D29: =IFERROR(VLOOKUP($C29,'MEMBERS LIST'!$C$5:$I$29,5,0),0) -> Kasoa | E29: =IFERROR(VLOOKUP($C29,' SPECIAL LEVY FEES'!$C$5:$D$29,2,0),0) -> 1000 | F29: =IFERROR(VLOOKUP($C29,'SPECIAL LEVY'!$C$4:$D$28,2,0),0) -> 1000 | G29: =E29-F29 -> 0 | H29: REMOVED
B30: 23 | C30: Samuel Yaw Nkansah | D30: =IFERROR(VLOOKUP($C30,'MEMBERS LIST'!$C$5:$I$29,5,0),0) -> Darkuman | E30: =IFERROR(VLOOKUP($C30,' SPECIAL LEVY FEES'!$C$5:$D$29,2,0),0) -> 700 | F30: =IFERROR(VLOOKUP($C30,'SPECIAL LEVY'!$C$4:$D$28,2,0),0) -> 700 | G30: =E30-F30 -> 0 | H30: REMOVED
B32: TOTAL | E32: =SUM(E8:E23) -> 12500 | F32: =SUM(F8:F23) -> 12500 | G32: =SUM(G8:G23) -> 0

Sheet MEMBERS SHARES DEVIDENT
B3: SHARES DEVIDENTS ON DUES
B4: NO. | C4: NAME | D4: AMOUNT | E4: TOTAL | F4: SPECIAL | G4: 2023 | H4: 2024 | I4: 2025 | J4: 2026 | K4: 2027 | L4: 2028 | M4: 2029 | N4: 2030
D5: ='CASH FLOW'!C41 -> 66564.36 | E5: SHARES | F5: SHARES | G5: SHARES | H5: SHARES | I5: SHARES | J5: SHARES | K5: SHARES | L5: SHARES | M5: SHARES | N5: SHARES
B6: 1 | C6: ALEX ACKAH | D6: =$D$5/$E$26*E6 -> 3034.8492 | E6: =SUM(F6:O6) -> 60 | F6: =IFERROR(VLOOKUP($C6,'VEHICLE SHARES HOLDING'!$C$8:$E$31,3,0),0) -> 0 | G6: =IFERROR(VLOOKUP($C6,'MONTHLY DUES 2023'!$C$5:$E$24,3,0),0) -> 0 | H6: =IFERROR(VLOOKUP($C6,'MONTHLY DUES 2024'!$C$5:$E$24,3,0),0) -> 18 | I6: =IFERROR(VLOOKUP($C6,'MONTHLY DUES 2025'!$C$5:$E$24,3,0),0) -> 24 | J6: =IFERROR(VLOOKUP($C6,'MONTHLY DUES 2026'!$C$5:$E$25,3,0),0) -> 18 | K6: =IFERROR(VLOOKUP($C6,'MONTHLY DUES 2027'!$C$5:$E$24,3,0),0) -> 0 | L6: =IFERROR(VLOOKUP($C6,'MONTHLY DUES 2028'!$C$5:$E$24,3,0),0) -> 0 | M6: =IFERROR(VLOOKUP($C6,'MONTHLY DUES 2029'!$C$5:$E$24,3,0),0) -> 0 | N6: =IFERROR(VLOOKUP($C6,'MONTHLY DUES 2030'!$C$5:$E$24,3,0),0) -> 0
B7: 2 | C7: DANSO KINGSLEY | D7: =$D$5/$E$26*E7 -> 1517.4246 | E7: =SUM(F7:O7) -> 30 | F7: =IFERROR(VLOOKUP($C7,'VEHICLE SHARES HOLDING'!$C$8:$E$31,3,0),0) -> 0 | G7: =IFERROR(VLOOKUP($C7,'MONTHLY DUES 2023'!$C$5:$E$24,3,0),0) -> 0 | H7: =IFERROR(VLOOKUP($C7,'MONTHLY DUES 2024'!$C$5:$E$24,3,0),0) -> 0 | I7: =IFERROR(VLOOKUP($C7,'MONTHLY DUES 2025'!$C$5:$E$24,3,0),0) -> 24 | J7: =IFERROR(VLOOKUP($C7,'MONTHLY DUES 2026'!$C$5:$E$25,3,0),0) -> 6 | K7: =IFERROR(VLOOKUP($C7,'MONTHLY DUES 2027'!$C$5:$E$24,3,0),0) -> 0 | L7: =IFERROR(VLOOKUP($C7,'MONTHLY DUES 2028'!$C$5:$E$24,3,0),0) -> 0 | M7: =IFERROR(VLOOKUP($C7,'MONTHLY DUES 2029'!$C$5:$E$24,3,0),0) -> 0 | N7: =IFERROR(VLOOKUP($C7,'MONTHLY DUES 2030'!$C$5:$E$24,3,0),0) -> 0
B8: 3 | C8: FANUEL HAGAN | D8: =$D$5/$E$26*E8 -> 3439.4958 | E8: =SUM(F8:O8) -> 68 | F8: =IFERROR(VLOOKUP($C8,'VEHICLE SHARES HOLDING'!$C$8:$E$31,3,0),0) -> 0 | G8: =IFERROR(VLOOKUP($C8,'MONTHLY DUES 2023'!$C$5:$E$24,3,0),0) -> 12 | H8: =IFERROR(VLOOKUP($C8,'MONTHLY DUES 2024'!$C$5:$E$24,3,0),0) -> 18 | I8: =IFERROR(VLOOKUP($C8,'MONTHLY DUES 2025'!$C$5:$E$24,3,0),0) -> 24 | J8: =IFERROR(VLOOKUP($C8,'MONTHLY DUES 2026'!$C$5:$E$25,3,0),0) -> 14 | K8: =IFERROR(VLOOKUP($C8,'MONTHLY DUES 2027'!$C$5:$E$24,3,0),0) -> 0 | L8: =IFERROR(VLOOKUP($C8,'MONTHLY DUES 2028'!$C$5:$E$24,3,0),0) -> 0 | M8: =IFERROR(VLOOKUP($C8,'MONTHLY DUES 2029'!$C$5:$E$24,3,0),0) -> 0 | N8: =IFERROR(VLOOKUP($C8,'MONTHLY DUES 2030'!$C$5:$E$24,3,0),0) -> 0
B9: 4 | C9: FREDERICK WORTEY TAWIAH | D9: =$D$5/$E$26*E9 -> 3439.4958 | E9: =SUM(F9:O9) -> 68 | F9: =IFERROR(VLOOKUP($C9,'VEHICLE SHARES HOLDING'!$C$8:$E$31,3,0),0) -> 0 | G9: =IFERROR(VLOOKUP($C9,'MONTHLY DUES 2023'!$C$5:$E$24,3,0),0) -> 12 | H9: =IFERROR(VLOOKUP($C9,'MONTHLY DUES 2024'!$C$5:$E$24,3,0),0) -> 18 | I9: =IFERROR(VLOOKUP($C9,'MONTHLY DUES 2025'!$C$5:$E$24,3,0),0) -> 24 | J9: =IFERROR(VLOOKUP($C9,'MONTHLY DUES 2026'!$C$5:$E$25,3,0),0) -> 14 | K9: =IFERROR(VLOOKUP($C9,'MONTHLY DUES 2027'!$C$5:$E$24,3,0),0) -> 0 | L9: =IFERROR(VLOOKUP($C9,'MONTHLY DUES 2028'!$C$5:$E$24,3,0),0) -> 0 | M9: =IFERROR(VLOOKUP($C9,'MONTHLY DUES 2029'!$C$5:$E$24,3,0),0) -> 0 | N9: =IFERROR(VLOOKUP($C9,'MONTHLY DUES 2030'!$C$5:$E$24,3,0),0) -> 0
B10: 5 | C10: ISAAC DARKO | D10: =$D$5/$E$26*E10 -> 3945.304 | E10: =SUM(F10:O10) -> 78 | F10: =IFERROR(VLOOKUP($C10,'VEHICLE SHARES HOLDING'!$C$8:$E$31,3,0),0) -> 0 | G10: =IFERROR(VLOOKUP($C10,'MONTHLY DUES 2023'!$C$5:$E$24,3,0),0) -> 12 | H10: =IFERROR(VLOOKUP($C10,'MONTHLY DUES 2024'!$C$5:$E$24,3,0),0) -> 18 | I10: =IFERROR(VLOOKUP($C10,'MONTHLY DUES 2025'!$C$5:$E$24,3,0),0) -> 24 | J10: =IFERROR(VLOOKUP($C10,'MONTHLY DUES 2026'!$C$5:$E$25,3,0),0) -> 24 | K10: =IFERROR(VLOOKUP($C10,'MONTHLY DUES 2027'!$C$5:$E$24,3,0),0) -> 0 | L10: =IFERROR(VLOOKUP($C10,'MONTHLY DUES 2028'!$C$5:$E$24,3,0),0) -> 0 | M10: =IFERROR(VLOOKUP($C10,'MONTHLY DUES 2029'!$C$5:$E$24,3,0),0) -> 0 | N10: =IFERROR(VLOOKUP($C10,'MONTHLY DUES 2030'!$C$5:$E$24,3,0),0) -> 0
B11: 6 | C11: ISAAC DONKOR | D11: =$D$5/$E$26*E11 -> 3338.3342 | E11: =SUM(F11:O11) -> 66 | F11: =IFERROR(VLOOKUP($C11,'VEHICLE SHARES HOLDING'!$C$8:$E$31,3,0),0) -> 0 | G11: =IFERROR(VLOOKUP($C11,'MONTHLY DUES 2023'!$C$5:$E$24,3,0),0) -> 0 | H11: =IFERROR(VLOOKUP($C11,'MONTHLY DUES 2024'!$C$5:$E$24,3,0),0) -> 18 | I11: =IFERROR(VLOOKUP($C11,'MONTHLY DUES 2025'!$C$5:$E$24,3,0),0) -> 24 | J11: =IFERROR(VLOOKUP($C11,'MONTHLY DUES 2026'!$C$5:$E$25,3,0),0) -> 24 | K11: =IFERROR(VLOOKUP($C11,'MONTHLY DUES 2027'!$C$5:$E$24,3,0),0) -> 0 | L11: =IFERROR(VLOOKUP($C11,'MONTHLY DUES 2028'!$C$5:$E$24,3,0),0) -> 0 | M11: =IFERROR(VLOOKUP($C11,'MONTHLY DUES 2029'!$C$5:$E$24,3,0),0) -> 0 | N11: =IFERROR(VLOOKUP($C11,'MONTHLY DUES 2030'!$C$5:$E$24,3,0),0) -> 0
B12: 7 | C12: JOHN AIDOO | D12: =$D$5/$E$26*E12 -> 910.45477 | E12: =SUM(F12:O12) -> 18 | F12: =IFERROR(VLOOKUP($C12,'VEHICLE SHARES HOLDING'!$C$8:$E$31,3,0),0) -> 0 | G12: =IFERROR(VLOOKUP($C12,'MONTHLY DUES 2023'!$C$5:$E$24,3,0),0) -> 0 | H12: =IFERROR(VLOOKUP($C12,'MONTHLY DUES 2024'!$C$5:$E$24,3,0),0) -> 0 | I12: =IFERROR(VLOOKUP($C12,'MONTHLY DUES 2025'!$C$5:$E$24,3,0),0) -> 0 | J12: =IFERROR(VLOOKUP($C12,'MONTHLY DUES 2026'!$C$5:$E$25,3,0),0) -> 18 | K12: =IFERROR(VLOOKUP($C12,'MONTHLY DUES 2027'!$C$5:$E$24,3,0),0) -> 0 | L12: =IFERROR(VLOOKUP($C12,'MONTHLY DUES 2028'!$C$5:$E$24,3,0),0) -> 0 | M12: =IFERROR(VLOOKUP($C12,'MONTHLY DUES 2029'!$C$5:$E$24,3,0),0) -> 0 | N12: =IFERROR(VLOOKUP($C12,'MONTHLY DUES 2030'!$C$5:$E$24,3,0),0) -> 0
B13: 8 | C13: JOHN OFOSUHENE ASARE | D13: =$D$5/$E$26*E13 -> 3439.4958 | E13: =SUM(F13:O13) -> 68 | F13: =IFERROR(VLOOKUP($C13,'VEHICLE SHARES HOLDING'!$C$8:$E$31,3,0),0) -> 0 | G13: =IFERROR(VLOOKUP($C13,'MONTHLY DUES 2023'!$C$5:$E$24,3,0),0) -> 12 | H13: =IFERROR(VLOOKUP($C13,'MONTHLY DUES 2024'!$C$5:$E$24,3,0),0) -> 18 | I13: =IFERROR(VLOOKUP($C13,'MONTHLY DUES 2025'!$C$5:$E$24,3,0),0) -> 24 | J13: =IFERROR(VLOOKUP($C13,'MONTHLY DUES 2026'!$C$5:$E$25,3,0),0) -> 14 | K13: =IFERROR(VLOOKUP($C13,'MONTHLY DUES 2027'!$C$5:$E$24,3,0),0) -> 0 | L13: =IFERROR(VLOOKUP($C13,'MONTHLY DUES 2028'!$C$5:$E$24,3,0),0) -> 0 | M13: =IFERROR(VLOOKUP($C13,'MONTHLY DUES 2029'!$C$5:$E$24,3,0),0) -> 0 | N13: =IFERROR(VLOOKUP($C13,'MONTHLY DUES 2030'!$C$5:$E$24,3,0),0) -> 0
B14: 9 | C14: JOHNSON WOOD | D14: =$D$5/$E$26*E14 -> 3540.6574 | E14: =SUM(F14:O14) -> 70 | F14: =IFERROR(VLOOKUP($C14,'VEHICLE SHARES HOLDING'!$C$8:$E$31,3,0),0) -> 0 | G14: =IFERROR(VLOOKUP($C14,'MONTHLY DUES 2023'!$C$5:$E$24,3,0),0) -> 12 | H14: =IFERROR(VLOOKUP($C14,'MONTHLY DUES 2024'!$C$5:$E$24,3,0),0) -> 18 | I14: =IFERROR(VLOOKUP($C14,'MONTHLY DUES 2025'!$C$5:$E$24,3,0),0) -> 24 | J14: =IFERROR(VLOOKUP($C14,'MONTHLY DUES 2026'!$C$5:$E$25,3,0),0) -> 16 | K14: =IFERROR(VLOOKUP($C14,'MONTHLY DUES 2027'!$C$5:$E$24,3,0),0) -> 0 | L14: =IFERROR(VLOOKUP($C14,'MONTHLY DUES 2028'!$C$5:$E$24,3,0),0) -> 0 | M14: =IFERROR(VLOOKUP($C14,'MONTHLY DUES 2029'!$C$5:$E$24,3,0),0) -> 0 | N14: =IFERROR(VLOOKUP($C14,'MONTHLY DUES 2030'!$C$5:$E$24,3,0),0) -> 0
B15: 10 | C15: JONAS WEREKO | D15: =$D$5/$E$26*E15 -> 3641.8191 | E15: =SUM(F15:O15) -> 72 | F15: =IFERROR(VLOOKUP($C15,'VEHICLE SHARES HOLDING'!$C$8:$E$31,3,0),0) -> 0 | G15: =IFERROR(VLOOKUP($C15,'MONTHLY DUES 2023'!$C$5:$E$24,3,0),0) -> 12 | H15: =IFERROR(VLOOKUP($C15,'MONTHLY DUES 2024'!$C$5:$E$24,3,0),0) -> 18 | I15: =IFERROR(VLOOKUP($C15,'MONTHLY DUES 2025'!$C$5:$E$24,3,0),0) -> 24 | J15: =IFERROR(VLOOKUP($C15,'MONTHLY DUES 2026'!$C$5:$E$25,3,0),0) -> 18 | K15: =IFERROR(VLOOKUP($C15,'MONTHLY DUES 2027'!$C$5:$E$24,3,0),0) -> 0 | L15: =IFERROR(VLOOKUP($C15,'MONTHLY DUES 2028'!$C$5:$E$24,3,0),0) -> 0 | M15: =IFERROR(VLOOKUP($C15,'MONTHLY DUES 2029'!$C$5:$E$24,3,0),0) -> 0 | N15: =IFERROR(VLOOKUP($C15,'MONTHLY DUES 2030'!$C$5:$E$24,3,0),0) -> 0
B16: 11 | C16: JONATHAN DANSO SIAW | D16: =$D$5/$E$26*E16 -> 5968.5368 | E16: =SUM(F16:O16) -> 118 | F16: =IFERROR(VLOOKUP($C16,'VEHICLE SHARES HOLDING'!$C$8:$E$31,3,0),0) -> 40 | G16: =IFERROR(VLOOKUP($C16,'MONTHLY DUES 2023'!$C$5:$E$24,3,0),0) -> 12 | H16: =IFERROR(VLOOKUP($C16,'MONTHLY DUES 2024'!$C$5:$E$24,3,0),0) -> 18 | I16: =IFERROR(VLOOKUP($C16,'MONTHLY DUES 2025'!$C$5:$E$24,3,0),0) -> 24 | J16: =IFERROR(VLOOKUP($C16,'MONTHLY DUES 2026'!$C$5:$E$25,3,0),0) -> 24 | K16: =IFERROR(VLOOKUP($C16,'MONTHLY DUES 2027'!$C$5:$E$24,3,0),0) -> 0 | L16: =IFERROR(VLOOKUP($C16,'MONTHLY DUES 2028'!$C$5:$E$24,3,0),0) -> 0 | M16: =IFERROR(VLOOKUP($C16,'MONTHLY DUES 2029'!$C$5:$E$24,3,0),0) -> 0 | N16: =IFERROR(VLOOKUP($C16,'MONTHLY DUES 2030'!$C$5:$E$24,3,0),0) -> 0
B17: 12 | C17: JUSTICE KOJO ACHEAMPONG | D17: =$D$5/$E$26*E17 -> 3034.8492 | E17: =SUM(F17:O17) -> 60 | F17: =IFERROR(VLOOKUP($C17,'VEHICLE SHARES HOLDING'!$C$8:$E$31,3,0),0) -> 0 | G17: =IFERROR(VLOOKUP($C17,'MONTHLY DUES 2023'!$C$5:$E$24,3,0),0) -> 12 | H17: =IFERROR(VLOOKUP($C17,'MONTHLY DUES 2024'!$C$5:$E$24,3,0),0) -> 18 | I17: =IFERROR(VLOOKUP($C17,'MONTHLY DUES 2025'!$C$5:$E$24,3,0),0) -> 24 | J17: =IFERROR(VLOOKUP($C17,'MONTHLY DUES 2026'!$C$5:$E$25,3,0),0) -> 6 | K17: =IFERROR(VLOOKUP($C17,'MONTHLY DUES 2027'!$C$5:$E$24,3,0),0) -> 0 | L17: =IFERROR(VLOOKUP($C17,'MONTHLY DUES 2028'!$C$5:$E$24,3,0),0) -> 0 | M17: =IFERROR(VLOOKUP($C17,'MONTHLY DUES 2029'!$C$5:$E$24,3,0),0) -> 0 | N17: =IFERROR(VLOOKUP($C17,'MONTHLY DUES 2030'!$C$5:$E$24,3,0),0) -> 0
... B24: 19 | C24: WILLIAM KOJO ANANE | D24: =$D$5/$E$26*E24 -> 3945.304 | E24: =SUM(F24:O24) -> 78 | F24: =IFERROR(VLOOKUP($C24,'VEHICLE SHARES HOLDING'!$C$8:$E$31,3,0),0) -> 0 | G24: =IFERROR(VLOOKUP($C24,'MONTHLY DUES 2023'!$C$5:$E$24,3,0),0) -> 12 | H24: =IFERROR(VLOOKUP($C24,'MONTHLY DUES 2024'!$C$5:$E$24,3,0),0) -> 18 | I24: =IFERROR(VLOOKUP($C24,'MONTHLY DUES 2025'!$C$5:$E$24,3,0),0) -> 24 | J24: =IFERROR(VLOOKUP($C24,'MONTHLY DUES 2026'!$C$5:$E$25,3,0),0) -> 24 | K24: =IFERROR(VLOOKUP($C24,'MONTHLY DUES 2027'!$C$5:$E$24,3,0),0) -> 0 | L24: =IFERROR(VLOOKUP($C24,'MONTHLY DUES 2028'!$C$5:$E$24,3,0),0) -> 0 | M24: =IFERROR(VLOOKUP($C24,'MONTHLY DUES 2029'!$C$5:$E$24,3,0),0) -> 0 | N24: =IFERROR(VLOOKUP($C24,'MONTHLY DUES 2030'!$C$5:$E$24,3,0),0) -> 0
D25: =$D$5/$E$26*E25 -> 0 | F25: =IFERROR(VLOOKUP($C25,'VEHICLE SHARES HOLDING'!$C$8:$E$31,3,0),0) -> 0 | H25: =IFERROR(VLOOKUP($C25,'MONTHLY DUES 2024'!$C$7:$E$28,3,0),0) -> 0 | I25: =IFERROR(VLOOKUP($C25,'MONTHLY DUES 2025'!$C$7:$E$29,3,0),0) -> 0 | N25: =IFERROR(VLOOKUP($C25,'MONTHLY DUES 2026'!$C$8:$E$27,3,0),0) -> 0
B26: =SUBTOTAL(3,B6:B25) -> 19 | C26: =SUBTOTAL(3,C6:C25) -> 19 | D26: =SUBTOTAL(9,D6:D25) -> 66564.36 | E26: =SUM(E6:E25) -> 1316 | F26: =SUM(F6:F25) -> 80 | G26: =SUM(G6:G25) -> 180 | H26: =SUM(H6:H25) -> 306 | I26: =SUM(I6:I25) -> 432 | J26: =SUM(J6:J25) -> 318 | K26: =SUM(K6:K25) -> 0 | L26: =SUM(L6:L25) -> 0 | ... N26: =SUM(N6:N25) -> 0

Sheet CASH FLOW
B2: CASH FLOW
B3: PARTICULARS | C3: DUES
C4: INCOME | D4: EXPENSES
B5: REGISTRATION | C5: ='TRAIL BALANCE'!C6 -> 4800
B6: TOTAL MONTHLY DUES FOR 2023 | C6: ='TRAIL BALANCE'!C7 -> 10800
B7: TOTAL MONTHLY DUES FOR 2024 | C7: ='TRAIL BALANCE'!C8 -> 16900
B8: TOTAL MONTHLY DUES FOR 2025 | C8: ='TRAIL BALANCE'!C9 -> 22350
B9: TOTAL MONTHLY DUES FOR 2026 | C9: ='TRAIL BALANCE'!C10 -> 15900
B10: INTREST ON TREASURER BILL | C10: ='TRAIL BALANCE'!C11 -> 10502.699
B11: LEVY BALANCE | C11: ='TRAIL BALANCE'!C12 -> 1250.5
B12: SPECIAL CONTRIBUTIONS | C12: ='TRAIL BALANCE'!C13 -> 4000
B13: BANK TEMA BALANCE SHARES | D13: ='TRAIL BALANCE'!D14 -> 100
B14: MTN MOMO CHARGES DUES | D14: ='TRAIL BALANCE'!D15 -> 1091.8
B15: TRANPORTATIONS DUES | D15: ='TRAIL BALANCE'!D18 -> 5100
B16: GENERAL EXPENSES | D16: ='TRAIL BALANCE'!D19 -> 1010
B17: PRINTING & STATIONERY | D17: ='TRAIL BALANCE'!D20 -> 285
B18: DOCUMENTATIONS | D18: ='TRAIL BALANCE'!D21 -> 500
B19: REGISTRATION OF FELLOWSHIP | D19: ='TRAIL BALANCE'!D22 -> 1300
B20: FIDELITY BANK CHARGES | D20: ='TRAIL BALANCE'!D16 -> 15
B21: TREASURER BILL CHARGES | D21: ='TRAIL BALANCE'!D17 -> 34.34
B22: FIRST TOTAL LEVY
B23: SECOND TOTAL LEVY
B24: THIRD TOTAL LEVY
B25: FORTH TOTAL LEVY
B26: FIFTH TOTAL LEVY
B27: SIXTH TOTAL LEVY
B28: MTN MOMO CHARGES LEVY
B29: FUNERAL DONATIONS
B30: CHILD NAMING
B31: TRANPORTATIONS LEVY
B32: TOTAL | C32: =SUM(C5:C31) -> 86503.199 | D32: =SUM(D5:D31) -> 9436.14
B33: EXPENSES | C33: =D32 -> 9436.14
B34: TOTAL BALANCE B/D | C34: =C32-C33 -> 77067.059
B35: MTN MOMO ACCOUNT | D35: ='TRAIL BALANCE'!D25 -> 1.95
B36: BANK TEMA BALANCE | D36: ='TRAIL BALANCE'!D23 -> 366.24
B37: FIDELITY BANK BALANCE | D37: ='FIDELITY BANK'!F67 -> 10698.88
B38: PURCHESE OF VEHICLE ACCOUNT | D38: ='TRAIL BALANCE'!D26 -> 66000
B39: TOTAL | C39: =SUM(C34:C38) -> 77067.059 | D39: =SUM(D34:D38) -> 77067.07
D40: =C39-D39 -> -0.010773004
B41: DUES AND OTHER CONTRIBUTIONS | C41: =C43-C42 -> 66564.36
B42: INTREST ON TREASURER BILL | C42: =C10 -> 10502.699
B43: TOTAL BALANCE B/D | C43: =C34 -> 77067.059

Sheet TREASURE BILL FOR MEMBERS
B3: TREASURER BILL FOR QUALIFIED MEMBERS ONLY
B4: NO. | C4: ELDER | D4: TOTAL | E4: NO. 1 T/BILL | F4: NO. 2 T/BILL | G4: NO. 3 T/BILL | H4: NO. 4 T/BILL
D5: ¢ | E5: ¢ | F5: ¢ | G5: ¢ | H5: ¢
B6: 1 | C6: ALEX ACKAH | D6: =SUM(E6:H6) -> 2.1460892 | E6: =IFERROR(VLOOKUP($C6,'B O G SHARES DEVIDENT '!$C$8:$D$21,2,0),0) -> 0 | F6: =IFERROR(VLOOKUP($C6,'B O G SHARES DEVIDENT '!$C$30:$D$42,2,0),0) -> 0 | G6: =IFERROR(VLOOKUP($C6,'B O G SHARES DEVIDENT '!$C$50:$D$63,2,0),0) -> 0 | H6: =IFERROR(VLOOKUP($C6,'B O G SHARES DEVIDENT '!$C$71:$D$88,2,0),0) -> 2.1460892
B7: 2 | C7: DANSO KINGSLEY | D7: =SUM(E7:H7) -> 56.169082 | E7: =IFERROR(VLOOKUP($C7,'B O G SHARES DEVIDENT '!$C$8:$D$21,2,0),0) -> 0 | F7: =IFERROR(VLOOKUP($C7,'B O G SHARES DEVIDENT '!$C$30:$D$42,2,0),0) -> 0 | G7: =IFERROR(VLOOKUP($C7,'B O G SHARES DEVIDENT '!$C$50:$D$63,2,0),0) -> 54.022992 | H7: =IFERROR(VLOOKUP($C7,'B O G SHARES DEVIDENT '!$C$71:$D$88,2,0),0) -> 2.1460892
B8: 3 | C8: FANUEL HAGAN | D8: =SUM(E8:H8) -> 828.35526 | E8: =IFERROR(VLOOKUP($C8,'B O G SHARES DEVIDENT '!$C$8:$D$21,2,0),0) -> 497.68269 | F8: =IFERROR(VLOOKUP($C8,'B O G SHARES DEVIDENT '!$C$30:$D$42,2,0),0) -> 274.50348 | G8: =IFERROR(VLOOKUP($C8,'B O G SHARES DEVIDENT '!$C$50:$D$63,2,0),0) -> 54.022992 | H8: =IFERROR(VLOOKUP($C8,'B O G SHARES DEVIDENT '!$C$71:$D$88,2,0),0) -> 2.1460892
B9: 4 | C9: FREDERICK WORTEY TAWIAH | D9: =SUM(E9:H9) -> 828.35526 | E9: =IFERROR(VLOOKUP($C9,'B O G SHARES DEVIDENT '!$C$8:$D$21,2,0),0) -> 497.68269 | F9: =IFERROR(VLOOKUP($C9,'B O G SHARES DEVIDENT '!$C$30:$D$42,2,0),0) -> 274.50348 | G9: =IFERROR(VLOOKUP($C9,'B O G SHARES DEVIDENT '!$C$50:$D$63,2,0),0) -> 54.022992 | H9: =IFERROR(VLOOKUP($C9,'B O G SHARES DEVIDENT '!$C$71:$D$88,2,0),0) -> 2.1460892
B10: 5 | C10: ISAAC DARKO | D10: =SUM(E10:H10) -> 2.1460892 | E10: =IFERROR(VLOOKUP($C10,'B O G SHARES DEVIDENT '!$C$8:$D$21,2,0),0) -> 0 | F10: =IFERROR(VLOOKUP($C10,'B O G SHARES DEVIDENT '!$C$30:$D$42,2,0),0) -> 0 | G10: =IFERROR(VLOOKUP($C10,'B O G SHARES DEVIDENT '!$C$50:$D$63,2,0),0) -> 0 | H10: =IFERROR(VLOOKUP($C10,'B O G SHARES DEVIDENT '!$C$71:$D$88,2,0),0) -> 2.1460892
B11: 6 | C11: ISAAC DONKOR | D11: =SUM(E11:H11) -> 56.169082 | E11: =IFERROR(VLOOKUP($C11,'B O G SHARES DEVIDENT '!$C$8:$D$21,2,0),0) -> 0 | F11: =IFERROR(VLOOKUP($C11,'B O G SHARES DEVIDENT '!$C$30:$D$42,2,0),0) -> 0 | G11: =IFERROR(VLOOKUP($C11,'B O G SHARES DEVIDENT '!$C$50:$D$63,2,0),0) -> 54.022992 | H11: =IFERROR(VLOOKUP($C11,'B O G SHARES DEVIDENT '!$C$71:$D$88,2,0),0) -> 2.1460892
B12: 7 | C12: JOHN OFOSUHENE ASARE | D12: =SUM(E12:H12) -> 499.82878 | E12: =IFERROR(VLOOKUP($C12,'B O G SHARES DEVIDENT '!$C$8:$D$21,2,0),0) -> 497.68269 | F12: =IFERROR(VLOOKUP($C12,'B O G SHARES DEVIDENT '!$C$30:$D$42,2,0),0) -> 0 | G12: =IFERROR(VLOOKUP($C12,'B O G SHARES DEVIDENT '!$C$50:$D$63,2,0),0) -> 0 | H12: =IFERROR(VLOOKUP($C12,'B O G SHARES DEVIDENT '!$C$71:$D$88,2,0),0) -> 2.1460892
B13: 8 | C13: JOHNSON WOOD | D13: =SUM(E13:H13) -> 828.35526 | E13: =IFERROR(VLOOKUP($C13,'B O G SHARES DEVIDENT '!$C$8:$D$21,2,0),0) -> 497.68269 | F13: =IFERROR(VLOOKUP($C13,'B O G SHARES DEVIDENT '!$C$30:$D$42,2,0),0) -> 274.50348 | G13: =IFERROR(VLOOKUP($C13,'B O G SHARES DEVIDENT '!$C$50:$D$63,2,0),0) -> 54.022992 | H13: =IFERROR(VLOOKUP($C13,'B O G SHARES DEVIDENT '!$C$71:$D$88,2,0),0) -> 2.1460892
B14: 9 | C14: JONAS WEREKO | D14: =SUM(E14:H14) -> 2.1460892 | E14: =IFERROR(VLOOKUP($C14,'B O G SHARES DEVIDENT '!$C$8:$D$21,2,0),0) -> 0 | F14: =IFERROR(VLOOKUP($C14,'B O G SHARES DEVIDENT '!$C$30:$D$42,2,0),0) -> 0 | G14: =IFERROR(VLOOKUP($C14,'B O G SHARES DEVIDENT '!$C$50:$D$63,2,0),0) -> 0 | H14: =IFERROR(VLOOKUP($C14,'B O G SHARES DEVIDENT '!$C$71:$D$88,2,0),0) -> 2.1460892
B15: 10 | C15: JONATHAN DANSO SIAW | D15: =SUM(E15:H15) -> 828.35526 | E15: =IFERROR(VLOOKUP($C15,'B O G SHARES DEVIDENT '!$C$8:$D$21,2,0),0) -> 497.68269 | F15: =IFERROR(VLOOKUP($C15,'B O G SHARES DEVIDENT '!$C$30:$D$42,2,0),0) -> 274.50348 | G15: =IFERROR(VLOOKUP($C15,'B O G SHARES DEVIDENT '!$C$50:$D$63,2,0),0) -> 54.022992 | H15: =IFERROR(VLOOKUP($C15,'B O G SHARES DEVIDENT '!$C$71:$D$88,2,0),0) -> 2.1460892
B16: 11 | C16: JUSTICE KOJO ACHEAMPONG | D16: =SUM(E16:H16) -> 772.18618 | E16: =IFERROR(VLOOKUP($C16,'B O G SHARES DEVIDENT '!$C$8:$D$21,2,0),0) -> 497.68269 | F16: =IFERROR(VLOOKUP($C16,'B O G SHARES DEVIDENT '!$C$30:$D$42,2,0),0) -> 274.50348 | G16: =IFERROR(VLOOKUP($C16,'B O G SHARES DEVIDENT '!$C$50:$D$63,2,0),0) -> 0 | H16: =IFERROR(VLOOKUP($C16,'B O G SHARES DEVIDENT '!$C$71:$D$88,2,0),0) -> 0
B17: 12 | C17: JUST-MARK KWABENA QUANSAH | D17: =SUM(E17:H17) -> 828.35526 | E17: =IFERROR(VLOOKUP($C17,'B O G SHARES DEVIDENT '!$C$8:$D$21,2,0),0) -> 497.68269 | F17: =IFERROR(VLOOKUP($C17,'B O G SHARES DEVIDENT '!$C$30:$D$42,2,0),0) -> 274.50348 | G17: =IFERROR(VLOOKUP($C17,'B O G SHARES DEVIDENT '!$C$50:$D$63,2,0),0) -> 54.022992 | H17: =IFERROR(VLOOKUP($C17,'B O G SHARES DEVIDENT '!$C$71:$D$88,2,0),0) -> 2.1460892
... B23: 18 | C23: WILLIAM KOJO ANANE | D23: =SUM(E23:H23) -> 828.35526 | E23: =IFERROR(VLOOKUP($C23,'B O G SHARES DEVIDENT '!$C$8:$D$21,2,0),0) -> 497.68269 | F23: =IFERROR(VLOOKUP($C23,'B O G SHARES DEVIDENT '!$C$30:$D$42,2,0),0) -> 274.50348 | G23: =IFERROR(VLOOKUP($C23,'B O G SHARES DEVIDENT '!$C$50:$D$63,2,0),0) -> 54.022992 | H23: =IFERROR(VLOOKUP($C23,'B O G SHARES DEVIDENT '!$C$71:$D$88,2,0),0) -> 2.1460892
H24: =IFERROR(VLOOKUP($C24,'B O G SHARES DEVIDENT '!$C$71:$D$88,2,0),0) -> 0
B25: =SUBTOTAL(3,B6:B24) -> 18 | C25: =SUBTOTAL(3,C6:C24) -> 18 | D25: =SUM(D6:D23) -> 10502.699 | E25: =SUM(E6:E24) -> 6469.875 | F25: =SUM(F6:F24) -> 3294.0418 | G25: =SUM(G6:G24) -> 702.2989 | H25: =SUM(H6:H24) -> 36.483516
B26: COUNT | D26: =COUNTIF(D6:D24,">1") -> 18 | E26: =COUNTIF(E6:E24,">1") -> 13 | F26: =COUNTIF(F6:F24,">1") -> 12 | G26: =COUNTIF(G6:G24,">1") -> 13 | H26: =COUNTIF(H6:H24,">1") -> 17

Sheet SHARES HOLDINGS
B3: MEMBERS SHARES HOLDING
B4: NO. | C4: ELDER | D4: SHARES TOTAL | E4: TREASURER BILL TOTAL | F4: GRAND AMOUNT
B5: 1 | C5: ALEX ACKAH | D5: =IFERROR(VLOOKUP($C5,'MEMBERS SHARES DEVIDENT'!$C$6:$D$25,2,0),0) -> 3034.8492 | E5: =IFERROR(VLOOKUP($C5,'TREASURE BILL FOR MEMBERS'!$C$6:$D$24,2,0),0) -> 2.1460892 | F5: =SUM(D5:E5) -> 3036.9953
B6: 2 | C6: DANSO KINGSLEY | D6: =IFERROR(VLOOKUP($C6,'MEMBERS SHARES DEVIDENT'!$C$6:$D$25,2,0),0) -> 1517.4246 | E6: =IFERROR(VLOOKUP($C6,'TREASURE BILL FOR MEMBERS'!$C$6:$D$24,2,0),0) -> 56.169082 | F6: =SUM(D6:E6) -> 1573.5937
B7: 3 | C7: FANUEL HAGAN | D7: =IFERROR(VLOOKUP($C7,'MEMBERS SHARES DEVIDENT'!$C$6:$D$25,2,0),0) -> 3439.4958 | E7: =IFERROR(VLOOKUP($C7,'TREASURE BILL FOR MEMBERS'!$C$6:$D$24,2,0),0) -> 828.35526 | F7: =SUM(D7:E7) -> 4267.8511
B8: 4 | C8: FREDERICK WORTEY TAWIAH | D8: =IFERROR(VLOOKUP($C8,'MEMBERS SHARES DEVIDENT'!$C$6:$D$25,2,0),0) -> 3439.4958 | E8: =IFERROR(VLOOKUP($C8,'TREASURE BILL FOR MEMBERS'!$C$6:$D$24,2,0),0) -> 828.35526 | F8: =SUM(D8:E8) -> 4267.8511
B9: 5 | C9: ISAAC DARKO | D9: =IFERROR(VLOOKUP($C9,'MEMBERS SHARES DEVIDENT'!$C$6:$D$25,2,0),0) -> 3945.304 | E9: =IFERROR(VLOOKUP($C9,'TREASURE BILL FOR MEMBERS'!$C$6:$D$24,2,0),0) -> 2.1460892 | F9: =SUM(D9:E9) -> 3947.4501
B10: 6 | C10: ISAAC DONKOR | D10: =IFERROR(VLOOKUP($C10,'MEMBERS SHARES DEVIDENT'!$C$6:$D$25,2,0),0) -> 3338.3342 | E10: =IFERROR(VLOOKUP($C10,'TREASURE BILL FOR MEMBERS'!$C$6:$D$24,2,0),0) -> 56.169082 | F10: =SUM(D10:E10) -> 3394.5032
B11: 7 | C11: JOHN AIDOO | D11: =IFERROR(VLOOKUP($C11,'MEMBERS SHARES DEVIDENT'!$C$6:$D$25,2,0),0) -> 910.45477 | E11: =IFERROR(VLOOKUP($C11,'TREASURE BILL FOR MEMBERS'!$C$6:$D$24,2,0),0) -> 0 | F11: =SUM(D11:E11) -> 910.45477
B12: 8 | C12: JOHN OFOSUHENE ASARE | D12: =IFERROR(VLOOKUP($C12,'MEMBERS SHARES DEVIDENT'!$C$6:$D$25,2,0),0) -> 3439.4958 | E12: =IFERROR(VLOOKUP($C12,'TREASURE BILL FOR MEMBERS'!$C$6:$D$24,2,0),0) -> 499.82878 | F12: =SUM(D12:E12) -> 3939.3246
B13: 9 | C13: JOHNSON WOOD | D13: =IFERROR(VLOOKUP($C13,'MEMBERS SHARES DEVIDENT'!$C$6:$D$25,2,0),0) -> 3540.6574 | E13: =IFERROR(VLOOKUP($C13,'TREASURE BILL FOR MEMBERS'!$C$6:$D$24,2,0),0) -> 828.35526 | F13: =SUM(D13:E13) -> 4369.0127
B14: 10 | C14: JONAS WEREKO | D14: =IFERROR(VLOOKUP($C14,'MEMBERS SHARES DEVIDENT'!$C$6:$D$25,2,0),0) -> 3641.8191 | E14: =IFERROR(VLOOKUP($C14,'TREASURE BILL FOR MEMBERS'!$C$6:$D$24,2,0),0) -> 2.1460892 | F14: =SUM(D14:E14) -> 3643.9652
B15: 11 | C15: JONATHAN DANSO SIAW | D15: =IFERROR(VLOOKUP($C15,'MEMBERS SHARES DEVIDENT'!$C$6:$D$25,2,0),0) -> 5968.5368 | E15: =IFERROR(VLOOKUP($C15,'TREASURE BILL FOR MEMBERS'!$C$6:$D$24,2,0),0) -> 828.35526 | F15: =SUM(D15:E15) -> 6796.8921
B16: 12 | C16: JUSTICE KOJO ACHEAMPONG | D16: =IFERROR(VLOOKUP($C16,'MEMBERS SHARES DEVIDENT'!$C$6:$D$25,2,0),0) -> 3034.8492 | E16: =IFERROR(VLOOKUP($C16,'TREASURE BILL FOR MEMBERS'!$C$6:$D$24,2,0),0) -> 772.18618 | F16: =SUM(D16:E16) -> 3807.0354
... B23: 19 | C23: WILLIAM KOJO ANANE | D23: =IFERROR(VLOOKUP($C23,'MEMBERS SHARES DEVIDENT'!$C$6:$D$25,2,0),0) -> 3945.304 | E23: =IFERROR(VLOOKUP($C23,'TREASURE BILL FOR MEMBERS'!$C$6:$D$24,2,0),0) -> 828.35526 | F23: =SUM(D23:E23) -> 4773.6593
B25: =SUBTOTAL(3,B5:B24) -> 19 | C25: =SUBTOTAL(3,C5:C24) -> 19 | D25: =SUM(D5:D23) -> 66564.36 | E25: =SUM(E5:E23) -> 10502.699 | F25: =SUM(D25:E25) -> 77067.059

Sheet MEMBERS SHARES HOLDING
B4: MEMBERS SHARES HOLDING | G4: SHARES DEVIDENTS ON DUES | N4: TREASURER BILL
B5: NO. | C5: ELDER | D5: SHARES TOTAL | E5: TREASURER BILL TOTAL | F5: GRAND AMOUNT | G5: TOTAL | H5: 2023 | I5: 2024 | J5: 2025 | K5: 2026 | L5: VEHICLE | M5: 2027 | N5: NO. 1 T/BILL | O5: NO. 2 T/BILL | P5: NO. 3 T/BILL | Q5: NO. 4 T/BILL | R5: NO. 5 T/BILL
D6: ='CASH FLOW'!C41 -> 66564.36 | E6: ='CASH FLOW'!C42 -> 10502.699 | F6: =SUM(D6:E6) -> 77067.059 | G6: ¢ | H6: ¢ | I6: ¢ | J6: ¢ | K6: ¢ | M6: ¢ | N6: ¢ | O6: ¢ | P6: ¢ | Q6: ¢ | R6: ¢
B7: 1 | C7: ALEX ACKAH | D7: =$D$6/$G$27*G7 -> 3034.8492 | E7: =SUM(N7:R7) -> 2.1460892 | F7: =SUM(D7:E7) -> 3036.9953 | G7: =SUM(H7:M7) -> 60 | H7: =IFERROR(VLOOKUP($C7,'MONTHLY DUES 2023'!$C$5:$E$24,3,0),0) -> 0 | I7: =IFERROR(VLOOKUP($C7,'MONTHLY DUES 2024'!$C$5:$E$26,3,0),0) -> 18 | J7: =IFERROR(VLOOKUP($C7,'MONTHLY DUES 2025'!$C$5:$E$27,3,0),0) -> 24 | K7: =IFERROR(VLOOKUP($C7,'MONTHLY DUES 2026'!$C$5:$E$25,3,0),0) -> 18 | L7: =IFERROR(VLOOKUP($C7,'VEHICLE SHARES HOLDING'!$C$17:$E$31,3,0),0) -> 0 | N7: =IFERROR(VLOOKUP($C7,'B O G SHARES DEVIDENT '!$C$8:$D$21,2,0),0) -> 0 | O7: =IFERROR(VLOOKUP($C7,'B O G SHARES DEVIDENT '!$C$30:$D$42,2,0),0) -> 0 | P7: =IFERROR(VLOOKUP($C7,'B O G SHARES DEVIDENT '!$C$50:$D$63,2,0),0) -> 0 | Q7: =IFERROR(VLOOKUP($C7,'B O G SHARES DEVIDENT '!$C$71:$D$87,2,0),0) -> 2.1460892 | R7: =IFERROR(VLOOKUP($C7,'B O G SHARES DEVIDENT '!$C$71:$C$88,3,0),0) -> 0
B8: 2 | C8: DANSO KINGSLEY | D8: =$D$6/$G$27*G8 -> 1517.4246 | E8: =SUM(N8:R8) -> 56.169082 | F8: =SUM(D8:E8) -> 1573.5937 | G8: =SUM(H8:M8) -> 30 | H8: =IFERROR(VLOOKUP($C8,'MONTHLY DUES 2023'!$C$5:$E$24,3,0),0) -> 0 | I8: =IFERROR(VLOOKUP($C8,'MONTHLY DUES 2024'!$C$5:$E$26,3,0),0) -> 0 | J8: =IFERROR(VLOOKUP($C8,'MONTHLY DUES 2025'!$C$5:$E$27,3,0),0) -> 24 | K8: =IFERROR(VLOOKUP($C8,'MONTHLY DUES 2026'!$C$5:$E$25,3,0),0) -> 6 | L8: =IFERROR(VLOOKUP($C8,'VEHICLE SHARES HOLDING'!$C$17:$E$31,3,0),0) -> 0 | N8: =IFERROR(VLOOKUP($C8,'B O G SHARES DEVIDENT '!$C$8:$D$21,2,0),0) -> 0 | O8: =IFERROR(VLOOKUP($C8,'B O G SHARES DEVIDENT '!$C$30:$D$42,2,0),0) -> 0 | P8: =IFERROR(VLOOKUP($C8,'B O G SHARES DEVIDENT '!$C$50:$D$63,2,0),0) -> 54.022992 | Q8: =IFERROR(VLOOKUP($C8,'B O G SHARES DEVIDENT '!$C$71:$D$87,2,0),0) -> 2.1460892 | R8: =IFERROR(VLOOKUP($C8,'B O G SHARES DEVIDENT '!$C$71:$C$88,3,0),0) -> 0
B9: 3 | C9: FANUEL HAGAN | D9: =$D$6/$G$27*G9 -> 3439.4958 | E9: =SUM(N9:R9) -> 828.35526 | F9: =SUM(D9:E9) -> 4267.8511 | G9: =SUM(H9:M9) -> 68 | H9: =IFERROR(VLOOKUP($C9,'MONTHLY DUES 2023'!$C$5:$E$24,3,0),0) -> 12 | I9: =IFERROR(VLOOKUP($C9,'MONTHLY DUES 2024'!$C$5:$E$26,3,0),0) -> 18 | J9: =IFERROR(VLOOKUP($C9,'MONTHLY DUES 2025'!$C$5:$E$27,3,0),0) -> 24 | K9: =IFERROR(VLOOKUP($C9,'MONTHLY DUES 2026'!$C$5:$E$25,3,0),0) -> 14 | L9: =IFERROR(VLOOKUP($C9,'VEHICLE SHARES HOLDING'!$C$17:$E$31,3,0),0) -> 0 | N9: =IFERROR(VLOOKUP($C9,'B O G SHARES DEVIDENT '!$C$8:$D$21,2,0),0) -> 497.68269 | O9: =IFERROR(VLOOKUP($C9,'B O G SHARES DEVIDENT '!$C$30:$D$42,2,0),0) -> 274.50348 | P9: =IFERROR(VLOOKUP($C9,'B O G SHARES DEVIDENT '!$C$50:$D$63,2,0),0) -> 54.022992 | Q9: =IFERROR(VLOOKUP($C9,'B O G SHARES DEVIDENT '!$C$71:$D$87,2,0),0) -> 2.1460892 | R9: =IFERROR(VLOOKUP($C9,'B O G SHARES DEVIDENT '!$C$71:$C$88,3,0),0) -> 0
B10: 4 | C10: FREDERICK WORTEY TAWIAH | D10: =$D$6/$G$27*G10 -> 3439.4958 | E10: =SUM(N10:R10) -> 828.35526 | F10: =SUM(D10:E10) -> 4267.8511 | G10: =SUM(H10:M10) -> 68 | H10: =IFERROR(VLOOKUP($C10,'MONTHLY DUES 2023'!$C$5:$E$24,3,0),0) -> 12 | I10: =IFERROR(VLOOKUP($C10,'MONTHLY DUES 2024'!$C$5:$E$26,3,0),0) -> 18 | J10: =IFERROR(VLOOKUP($C10,'MONTHLY DUES 2025'!$C$5:$E$27,3,0),0) -> 24 | K10: =IFERROR(VLOOKUP($C10,'MONTHLY DUES 2026'!$C$5:$E$25,3,0),0) -> 14 | L10: =IFERROR(VLOOKUP($C10,'VEHICLE SHARES HOLDING'!$C$17:$E$31,3,0),0) -> 0 | N10: =IFERROR(VLOOKUP($C10,'B O G SHARES DEVIDENT '!$C$8:$D$21,2,0),0) -> 497.68269 | O10: =IFERROR(VLOOKUP($C10,'B O G SHARES DEVIDENT '!$C$30:$D$42,2,0),0) -> 274.50348 | P10: =IFERROR(VLOOKUP($C10,'B O G SHARES DEVIDENT '!$C$50:$D$63,2,0),0) -> 54.022992 | Q10: =IFERROR(VLOOKUP($C10,'B O G SHARES DEVIDENT '!$C$71:$D$87,2,0),0) -> 2.1460892 | R10: =IFERROR(VLOOKUP($C10,'B O G SHARES DEVIDENT '!$C$71:$C$88,3,0),0) -> 0
B11: 5 | C11: ISAAC DARKO | D11: =$D$6/$G$27*G11 -> 3945.304 | E11: =SUM(N11:R11) -> 2.1460892 | F11: =SUM(D11:E11) -> 3947.4501 | G11: =SUM(H11:M11) -> 78 | H11: =IFERROR(VLOOKUP($C11,'MONTHLY DUES 2023'!$C$5:$E$24,3,0),0) -> 12 | I11: =IFERROR(VLOOKUP($C11,'MONTHLY DUES 2024'!$C$5:$E$26,3,0),0) -> 18 | J11: =IFERROR(VLOOKUP($C11,'MONTHLY DUES 2025'!$C$5:$E$27,3,0),0) -> 24 | K11: =IFERROR(VLOOKUP($C11,'MONTHLY DUES 2026'!$C$5:$E$25,3,0),0) -> 24 | L11: =IFERROR(VLOOKUP($C11,'VEHICLE SHARES HOLDING'!$C$17:$E$31,3,0),0) -> 0 | N11: =IFERROR(VLOOKUP($C11,'B O G SHARES DEVIDENT '!$C$8:$D$21,2,0),0) -> 0 | O11: =IFERROR(VLOOKUP($C11,'B O G SHARES DEVIDENT '!$C$30:$D$42,2,0),0) -> 0 | P11: =IFERROR(VLOOKUP($C11,'B O G SHARES DEVIDENT '!$C$50:$D$63,2,0),0) -> 0 | Q11: =IFERROR(VLOOKUP($C11,'B O G SHARES DEVIDENT '!$C$71:$D$87,2,0),0) -> 2.1460892 | R11: =IFERROR(VLOOKUP($C11,'B O G SHARES DEVIDENT '!$C$71:$C$88,3,0),0) -> 0
B12: 6 | C12: ISAAC DONKOR | D12: =$D$6/$G$27*G12 -> 3338.3342 | E12: =SUM(N12:R12) -> 56.169082 | F12: =SUM(D12:E12) -> 3394.5032 | G12: =SUM(H12:M12) -> 66 | H12: =IFERROR(VLOOKUP($C12,'MONTHLY DUES 2023'!$C$5:$E$24,3,0),0) -> 0 | I12: =IFERROR(VLOOKUP($C12,'MONTHLY DUES 2024'!$C$5:$E$26,3,0),0) -> 18 | J12: =IFERROR(VLOOKUP($C12,'MONTHLY DUES 2025'!$C$5:$E$27,3,0),0) -> 24 | K12: =IFERROR(VLOOKUP($C12,'MONTHLY DUES 2026'!$C$5:$E$25,3,0),0) -> 24 | L12: =IFERROR(VLOOKUP($C12,'VEHICLE SHARES HOLDING'!$C$17:$E$31,3,0),0) -> 0 | N12: =IFERROR(VLOOKUP($C12,'B O G SHARES DEVIDENT '!$C$8:$D$21,2,0),0) -> 0 | O12: =IFERROR(VLOOKUP($C12,'B O G SHARES DEVIDENT '!$C$30:$D$42,2,0),0) -> 0 | P12: =IFERROR(VLOOKUP($C12,'B O G SHARES DEVIDENT '!$C$50:$D$63,2,0),0) -> 54.022992 | Q12: =IFERROR(VLOOKUP($C12,'B O G SHARES DEVIDENT '!$C$71:$D$87,2,0),0) -> 2.1460892 | R12: =IFERROR(VLOOKUP($C12,'B O G SHARES DEVIDENT '!$C$71:$C$88,3,0),0) -> 0
B13: 66 | C13: JOHN AIDOO | D13: =$D$6/$G$27*G13 -> 910.45477 | E13: =SUM(N13:R13) -> 0 | F13: =SUM(D13:E13) -> 910.45477 | G13: =SUM(H13:M13) -> 18 | H13: =IFERROR(VLOOKUP($C13,'MONTHLY DUES 2023'!$C$5:$E$24,3,0),0) -> 0 | I13: =IFERROR(VLOOKUP($C13,'MONTHLY DUES 2024'!$C$5:$E$26,3,0),0) -> 0 | J13: =IFERROR(VLOOKUP($C13,'MONTHLY DUES 2025'!$C$5:$E$27,3,0),0) -> 0 | K13: =IFERROR(VLOOKUP($C13,'MONTHLY DUES 2026'!$C$5:$E$25,3,0),0) -> 18 | L13: =IFERROR(VLOOKUP($C13,'VEHICLE SHARES HOLDING'!$C$17:$E$31,3,0),0) -> 0 | N13: =IFERROR(VLOOKUP($C13,'B O G SHARES DEVIDENT '!$C$8:$D$21,2,0),0) -> 0 | O13: =IFERROR(VLOOKUP($C13,'B O G SHARES DEVIDENT '!$C$30:$D$42,2,0),0) -> 0 | P13: =IFERROR(VLOOKUP($C13,'B O G SHARES DEVIDENT '!$C$50:$D$63,2,0),0) -> 0 | Q13: =IFERROR(VLOOKUP($C13,'B O G SHARES DEVIDENT '!$C$71:$D$87,2,0),0) -> 0
B14: 7 | C14: JOHN OFOSUHENE ASARE | D14: =$D$6/$G$27*G14 -> 3439.4958 | E14: =SUM(N14:R14) -> 499.82878 | F14: =SUM(D14:E14) -> 3939.3246 | G14: =SUM(H14:M14) -> 68 | H14: =IFERROR(VLOOKUP($C14,'MONTHLY DUES 2023'!$C$5:$E$24,3,0),0) -> 12 | I14: =IFERROR(VLOOKUP($C14,'MONTHLY DUES 2024'!$C$5:$E$26,3,0),0) -> 18 | J14: =IFERROR(VLOOKUP($C14,'MONTHLY DUES 2025'!$C$5:$E$27,3,0),0) -> 24 | K14: =IFERROR(VLOOKUP($C14,'MONTHLY DUES 2026'!$C$5:$E$25,3,0),0) -> 14 | L14: =IFERROR(VLOOKUP($C14,'VEHICLE SHARES HOLDING'!$C$17:$E$31,3,0),0) -> 0 | N14: =IFERROR(VLOOKUP($C14,'B O G SHARES DEVIDENT '!$C$8:$D$21,2,0),0) -> 497.68269 | O14: =IFERROR(VLOOKUP($C14,'B O G SHARES DEVIDENT '!$C$30:$D$42,2,0),0) -> 0 | P14: =IFERROR(VLOOKUP($C14,'B O G SHARES DEVIDENT '!$C$50:$D$63,2,0),0) -> 0 | Q14: =IFERROR(VLOOKUP($C14,'B O G SHARES DEVIDENT '!$C$71:$D$87,2,0),0) -> 2.1460892 | R14: =IFERROR(VLOOKUP($C14,'B O G SHARES DEVIDENT '!$C$71:$C$88,3,0),0) -> 0
B15: 8 | C15: JOHNSON WOOD | D15: =$D$6/$G$27*G15 -> 3540.6574 | E15: =SUM(N15:R15) -> 828.35526 | F15: =SUM(D15:E15) -> 4369.0127 | G15: =SUM(H15:M15) -> 70 | H15: =IFERROR(VLOOKUP($C15,'MONTHLY DUES 2023'!$C$5:$E$24,3,0),0) -> 12 | I15: =IFERROR(VLOOKUP($C15,'MONTHLY DUES 2024'!$C$5:$E$26,3,0),0) -> 18 | J15: =IFERROR(VLOOKUP($C15,'MONTHLY DUES 2025'!$C$5:$E$27,3,0),0) -> 24 | K15: =IFERROR(VLOOKUP($C15,'MONTHLY DUES 2026'!$C$5:$E$25,3,0),0) -> 16 | L15: =IFERROR(VLOOKUP($C15,'VEHICLE SHARES HOLDING'!$C$17:$E$31,3,0),0) -> 0 | N15: =IFERROR(VLOOKUP($C15,'B O G SHARES DEVIDENT '!$C$8:$D$21,2,0),0) -> 497.68269 | O15: =IFERROR(VLOOKUP($C15,'B O G SHARES DEVIDENT '!$C$30:$D$42,2,0),0) -> 274.50348 | P15: =IFERROR(VLOOKUP($C15,'B O G SHARES DEVIDENT '!$C$50:$D$63,2,0),0) -> 54.022992 | Q15: =IFERROR(VLOOKUP($C15,'B O G SHARES DEVIDENT '!$C$71:$D$87,2,0),0) -> 2.1460892 | R15: =IFERROR(VLOOKUP($C15,'B O G SHARES DEVIDENT '!$C$71:$C$88,3,0),0) -> 0
B16: 9 | C16: JONAS WEREKO | D16: =$D$6/$G$27*G16 -> 3641.8191 | E16: =SUM(N16:R16) -> 2.1460892 | F16: =SUM(D16:E16) -> 3643.9652 | G16: =SUM(H16:M16) -> 72 | H16: =IFERROR(VLOOKUP($C16,'MONTHLY DUES 2023'!$C$5:$E$24,3,0),0) -> 12 | I16: =IFERROR(VLOOKUP($C16,'MONTHLY DUES 2024'!$C$5:$E$26,3,0),0) -> 18 | J16: =IFERROR(VLOOKUP($C16,'MONTHLY DUES 2025'!$C$5:$E$27,3,0),0) -> 24 | K16: =IFERROR(VLOOKUP($C16,'MONTHLY DUES 2026'!$C$5:$E$25,3,0),0) -> 18 | L16: =IFERROR(VLOOKUP($C16,'VEHICLE SHARES HOLDING'!$C$17:$E$31,3,0),0) -> 0 | N16: =IFERROR(VLOOKUP($C16,'B O G SHARES DEVIDENT '!$C$8:$D$21,2,0),0) -> 0 | O16: =IFERROR(VLOOKUP($C16,'B O G SHARES DEVIDENT '!$C$30:$D$42,2,0),0) -> 0 | P16: =IFERROR(VLOOKUP($C16,'B O G SHARES DEVIDENT '!$C$50:$D$63,2,0),0) -> 0 | Q16: =IFERROR(VLOOKUP($C16,'B O G SHARES DEVIDENT '!$C$71:$D$87,2,0),0) -> 2.1460892 | R16: =IFERROR(VLOOKUP($C16,'B O G SHARES DEVIDENT '!$C$71:$C$88,3,0),0) -> 0
B17: 10 | C17: JONATHAN DANSO SIAW | D17: =$D$6/$G$27*G17 -> 5968.5368 | E17: =SUM(N17:R17) -> 828.35526 | F17: =SUM(D17:E17) -> 6796.8921 | G17: =SUM(H17:M17) -> 118 | H17: =IFERROR(VLOOKUP($C17,'MONTHLY DUES 2023'!$C$5:$E$24,3,0),0) -> 12 | I17: =IFERROR(VLOOKUP($C17,'MONTHLY DUES 2024'!$C$5:$E$26,3,0),0) -> 18 | J17: =IFERROR(VLOOKUP($C17,'MONTHLY DUES 2025'!$C$5:$E$27,3,0),0) -> 24 | K17: =IFERROR(VLOOKUP($C17,'MONTHLY DUES 2026'!$C$5:$E$25,3,0),0) -> 24 | L17: =IFERROR(VLOOKUP($C17,'VEHICLE SHARES HOLDING'!$C$17:$E$31,3,0),0) -> 40 | N17: =IFERROR(VLOOKUP($C17,'B O G SHARES DEVIDENT '!$C$8:$D$21,2,0),0) -> 497.68269 | O17: =IFERROR(VLOOKUP($C17,'B O G SHARES DEVIDENT '!$C$30:$D$42,2,0),0) -> 274.50348 | P17: =IFERROR(VLOOKUP($C17,'B O G SHARES DEVIDENT '!$C$50:$D$63,2,0),0) -> 54.022992 | Q17: =IFERROR(VLOOKUP($C17,'B O G SHARES DEVIDENT '!$C$71:$D$87,2,0),0) -> 2.1460892 | R17: =IFERROR(VLOOKUP($C17,'B O G SHARES DEVIDENT '!$C$71:$C$88,3,0),0) -> 0
B18: 11 | C18: JUSTICE KOJO ACHEAMPONG | D18: =$D$6/$G$27*G18 -> 3034.8492 | E18: =SUM(N18:R18) -> 772.18618 | F18: =SUM(D18:E18) -> 3807.0354 | G18: =SUM(H18:M18) -> 60 | H18: =IFERROR(VLOOKUP($C18,'MONTHLY DUES 2023'!$C$5:$E$24,3,0),0) -> 12 | I18: =IFERROR(VLOOKUP($C18,'MONTHLY DUES 2024'!$C$5:$E$26,3,0),0) -> 18 | J18: =IFERROR(VLOOKUP($C18,'MONTHLY DUES 2025'!$C$5:$E$27,3,0),0) -> 24 | K18: =IFERROR(VLOOKUP($C18,'MONTHLY DUES 2026'!$C$5:$E$25,3,0),0) -> 6 | L18: =IFERROR(VLOOKUP($C18,'VEHICLE SHARES HOLDING'!$C$17:$E$31,3,0),0) -> 0 | N18: =IFERROR(VLOOKUP($C18,'B O G SHARES DEVIDENT '!$C$8:$D$21,2,0),0) -> 497.68269 | O18: =IFERROR(VLOOKUP($C18,'B O G SHARES DEVIDENT '!$C$30:$D$42,2,0),0) -> 274.50348 | P18: =IFERROR(VLOOKUP($C18,'B O G SHARES DEVIDENT '!$C$50:$D$63,2,0),0) -> 0 | Q18: =IFERROR(VLOOKUP($C18,'B O G SHARES DEVIDENT '!$C$71:$D$87,2,0),0) -> 0 | R18: =IFERROR(VLOOKUP($C18,'B O G SHARES DEVIDENT '!$C$71:$C$88,3,0),0) -> 0
B19: 12 | C19: JUST-MARK KWABENA QUANSAH | D19: =$D$6/$G$27*G19 -> 3034.8492 | E19: =SUM(N19:R19) -> 828.35526 | F19: =SUM(D19:E19) -> 3863.2045 | G19: =SUM(H19:M19) -> 60 | H19: =IFERROR(VLOOKUP($C19,'MONTHLY DUES 2023'!$C$5:$E$24,3,0),0) -> 12 | I19: =IFERROR(VLOOKUP($C19,'MONTHLY DUES 2024'!$C$5:$E$26,3,0),0) -> 18 | J19: =IFERROR(VLOOKUP($C19,'MONTHLY DUES 2025'!$C$5:$E$27,3,0),0) -> 24 | K19: =IFERROR(VLOOKUP($C19,'MONTHLY DUES 2026'!$C$5:$E$25,3,0),0) -> 6 | L19: =IFERROR(VLOOKUP($C19,'VEHICLE SHARES HOLDING'!$C$17:$E$31,3,0),0) -> 0 | N19: =IFERROR(VLOOKUP($C19,'B O G SHARES DEVIDENT '!$C$8:$D$21,2,0),0) -> 497.68269 | O19: =IFERROR(VLOOKUP($C19,'B O G SHARES DEVIDENT '!$C$30:$D$42,2,0),0) -> 274.50348 | P19: =IFERROR(VLOOKUP($C19,'B O G SHARES DEVIDENT '!$C$50:$D$63,2,0),0) -> 54.022992 | Q19: =IFERROR(VLOOKUP($C19,'B O G SHARES DEVIDENT '!$C$71:$D$87,2,0),0) -> 2.1460892 | R19: =IFERROR(VLOOKUP($C19,'B O G SHARES DEVIDENT '!$C$71:$C$88,3,0),0) -> 0
B20: 13 | C20: MAXWELL OFEI SIAW | D20: =$D$6/$G$27*G20 -> 3742.9807 | E20: =SUM(N20:R20) -> 828.35526 | F20: =SUM(D20:E20) -> 4571.336 | G20: =SUM(H20:M20) -> 74 | H20: =IFERROR(VLOOKUP($C20,'MONTHLY DUES 2023'!$C$5:$E$24,3,0),0) -> 12 | I20: =IFERROR(VLOOKUP($C20,'MONTHLY DUES 2024'!$C$5:$E$26,3,0),0) -> 18 | J20: =IFERROR(VLOOKUP($C20,'MONTHLY DUES 2025'!$C$5:$E$27,3,0),0) -> 24 | K20: =IFERROR(VLOOKUP($C20,'MONTHLY DUES 2026'!$C$5:$E$25,3,0),0) -> 20 | L20: =IFERROR(VLOOKUP($C20,'VEHICLE SHARES HOLDING'!$C$17:$E$31,3,0),0) -> 0 | N20: =IFERROR(VLOOKUP($C20,'B O G SHARES DEVIDENT '!$C$8:$D$21,2,0),0) -> 497.68269 | O20: =IFERROR(VLOOKUP($C20,'B O G SHARES DEVIDENT '!$C$30:$D$42,2,0),0) -> 274.50348 | P20: =IFERROR(VLOOKUP($C20,'B O G SHARES DEVIDENT '!$C$50:$D$63,2,0),0) -> 54.022992 | Q20: =IFERROR(VLOOKUP($C20,'B O G SHARES DEVIDENT '!$C$71:$D$87,2,0),0) -> 2.1460892 | R20: =IFERROR(VLOOKUP($C20,'B O G SHARES DEVIDENT '!$C$71:$C$88,3,0),0) -> 0
B21: 14 | C21: MOSES ODURO | D21: =$D$6/$G$27*G21 -> 3945.304 | E21: =SUM(N21:R21) -> 828.35526 | F21: =SUM(D21:E21) -> 4773.6593 | G21: =SUM(H21:M21) -> 78 | H21: =IFERROR(VLOOKUP($C21,'MONTHLY DUES 2023'!$C$5:$E$24,3,0),0) -> 12 | I21: =IFERROR(VLOOKUP($C21,'MONTHLY DUES 2024'!$C$5:$E$26,3,0),0) -> 18 | J21: =IFERROR(VLOOKUP($C21,'MONTHLY DUES 2025'!$C$5:$E$27,3,0),0) -> 24 | K21: =IFERROR(VLOOKUP($C21,'MONTHLY DUES 2026'!$C$5:$E$25,3,0),0) -> 24 | L21: =IFERROR(VLOOKUP($C21,'VEHICLE SHARES HOLDING'!$C$17:$E$31,3,0),0) -> 0 | N21: =IFERROR(VLOOKUP($C21,'B O G SHARES DEVIDENT '!$C$8:$D$21,2,0),0) -> 497.68269 | O21: =IFERROR(VLOOKUP($C21,'B O G SHARES DEVIDENT '!$C$30:$D$42,2,0),0) -> 274.50348 | P21: =IFERROR(VLOOKUP($C21,'B O G SHARES DEVIDENT '!$C$50:$D$63,2,0),0) -> 54.022992 | Q21: =IFERROR(VLOOKUP($C21,'B O G SHARES DEVIDENT '!$C$71:$D$87,2,0),0) -> 2.1460892 | R21: =IFERROR(VLOOKUP($C21,'B O G SHARES DEVIDENT '!$C$71:$C$88,3,0),0) -> 0
B22: 15 | C22: OSEI KWAME | D22: =$D$6/$G$27*G22 -> 5563.8903 | E22: =SUM(N22:R22) -> 828.35526 | F22: =SUM(D22:E22) -> 6392.2455 | G22: =SUM(H22:M22) -> 110 | H22: =IFERROR(VLOOKUP($C22,'MONTHLY DUES 2023'!$C$5:$E$24,3,0),0) -> 12 | I22: =IFERROR(VLOOKUP($C22,'MONTHLY DUES 2024'!$C$5:$E$26,3,0),0) -> 18 | J22: =IFERROR(VLOOKUP($C22,'MONTHLY DUES 2025'!$C$5:$E$27,3,0),0) -> 24 | K22: =IFERROR(VLOOKUP($C22,'MONTHLY DUES 2026'!$C$5:$E$25,3,0),0) -> 16 | L22: =IFERROR(VLOOKUP($C22,'VEHICLE SHARES HOLDING'!$C$17:$E$31,3,0),0) -> 40 | N22: =IFERROR(VLOOKUP($C22,'B O G SHARES DEVIDENT '!$C$8:$D$21,2,0),0) -> 497.68269 | O22: =IFERROR(VLOOKUP($C22,'B O G SHARES DEVIDENT '!$C$30:$D$42,2,0),0) -> 274.50348 | P22: =IFERROR(VLOOKUP($C22,'B O G SHARES DEVIDENT '!$C$50:$D$63,2,0),0) -> 54.022992 | Q22: =IFERROR(VLOOKUP($C22,'B O G SHARES DEVIDENT '!$C$71:$D$87,2,0),0) -> 2.1460892 | R22: =IFERROR(VLOOKUP($C22,'B O G SHARES DEVIDENT '!$C$71:$C$88,3,0),0) -> 0
B23: 16 | C23: PRINCE ASANTE AHWIRENG | D23: =$D$6/$G$27*G23 -> 3338.3342 | E23: =SUM(N23:R23) -> 828.35526 | F23: =SUM(D23:E23) -> 4166.6894 | G23: =SUM(H23:M23) -> 66 | H23: =IFERROR(VLOOKUP($C23,'MONTHLY DUES 2023'!$C$5:$E$24,3,0),0) -> 12 | I23: =IFERROR(VLOOKUP($C23,'MONTHLY DUES 2024'!$C$5:$E$26,3,0),0) -> 18 | J23: =IFERROR(VLOOKUP($C23,'MONTHLY DUES 2025'!$C$5:$E$27,3,0),0) -> 24 | K23: =IFERROR(VLOOKUP($C23,'MONTHLY DUES 2026'!$C$5:$E$25,3,0),0) -> 12 | L23: =IFERROR(VLOOKUP($C23,'VEHICLE SHARES HOLDING'!$C$17:$E$31,3,0),0) -> 0 | N23: =IFERROR(VLOOKUP($C23,'B O G SHARES DEVIDENT '!$C$8:$D$21,2,0),0) -> 497.68269 | O23: =IFERROR(VLOOKUP($C23,'B O G SHARES DEVIDENT '!$C$30:$D$42,2,0),0) -> 274.50348 | P23: =IFERROR(VLOOKUP($C23,'B O G SHARES DEVIDENT '!$C$50:$D$63,2,0),0) -> 54.022992 | Q23: =IFERROR(VLOOKUP($C23,'B O G SHARES DEVIDENT '!$C$71:$D$87,2,0),0) -> 2.1460892 | R23: =IFERROR(VLOOKUP($C23,'B O G SHARES DEVIDENT '!$C$71:$C$88,3,0),0) -> 0
B24: 17 | C24: VINCENT AGAMATEY | D24: =$D$6/$G$27*G24 -> 3742.9807 | E24: =SUM(N24:R24) -> 828.35526 | F24: =SUM(D24:E24) -> 4571.336 | G24: =SUM(H24:M24) -> 74 | H24: =IFERROR(VLOOKUP($C24,'MONTHLY DUES 2023'!$C$5:$E$24,3,0),0) -> 12 | I24: =IFERROR(VLOOKUP($C24,'MONTHLY DUES 2024'!$C$5:$E$26,3,0),0) -> 18 | J24: =IFERROR(VLOOKUP($C24,'MONTHLY DUES 2025'!$C$5:$E$27,3,0),0) -> 24 | K24: =IFERROR(VLOOKUP($C24,'MONTHLY DUES 2026'!$C$5:$E$25,3,0),0) -> 20 | L24: =IFERROR(VLOOKUP($C24,'VEHICLE SHARES HOLDING'!$C$17:$E$31,3,0),0) -> 0 | N24: =IFERROR(VLOOKUP($C24,'B O G SHARES DEVIDENT '!$C$8:$D$21,2,0),0) -> 497.68269 | O24: =IFERROR(VLOOKUP($C24,'B O G SHARES DEVIDENT '!$C$30:$D$42,2,0),0) -> 274.50348 | P24: =IFERROR(VLOOKUP($C24,'B O G SHARES DEVIDENT '!$C$50:$D$63,2,0),0) -> 54.022992 | Q24: =IFERROR(VLOOKUP($C24,'B O G SHARES DEVIDENT '!$C$71:$D$87,2,0),0) -> 2.1460892 | R24: =IFERROR(VLOOKUP($C24,'B O G SHARES DEVIDENT '!$C$71:$C$88,3,0),0) -> 0
B25: 18 | C25: WILLIAM KOJO ANANE | D25: =$D$6/$G$27*G25 -> 3945.304 | E25: =SUM(N25:R25) -> 828.35526 | F25: =SUM(D25:E25) -> 4773.6593 | G25: =SUM(H25:M25) -> 78 | H25: =IFERROR(VLOOKUP($C25,'MONTHLY DUES 2023'!$C$5:$E$24,3,0),0) -> 12 | I25: =IFERROR(VLOOKUP($C25,'MONTHLY DUES 2024'!$C$5:$E$26,3,0),0) -> 18 | J25: =IFERROR(VLOOKUP($C25,'MONTHLY DUES 2025'!$C$5:$E$27,3,0),0) -> 24 | K25: =IFERROR(VLOOKUP($C25,'MONTHLY DUES 2026'!$C$5:$E$25,3,0),0) -> 24 | L25: =IFERROR(VLOOKUP($C25,'VEHICLE SHARES HOLDING'!$C$17:$E$31,3,0),0) -> 0 | N25: =IFERROR(VLOOKUP($C25,'B O G SHARES DEVIDENT '!$C$8:$D$21,2,0),0) -> 497.68269 | O25: =IFERROR(VLOOKUP($C25,'B O G SHARES DEVIDENT '!$C$30:$D$42,2,0),0) -> 274.50348 | P25: =IFERROR(VLOOKUP($C25,'B O G SHARES DEVIDENT '!$C$50:$D$63,2,0),0) -> 54.022992 | Q25: =IFERROR(VLOOKUP($C25,'B O G SHARES DEVIDENT '!$C$71:$D$87,2,0),0) -> 2.1460892 | R25: =IFERROR(VLOOKUP($C25,'B O G SHARES DEVIDENT '!$C$71:$C$88,3,0),0) -> 0
I26: =IFERROR(VLOOKUP($C26,'MONTHLY DUES 2024'!$C$5:$E$26,3,0),0) -> 0 | J26: =IFERROR(VLOOKUP($C26,'MONTHLY DUES 2025'!$C$5:$E$27,3,0),0) -> 0 | K26: =IFERROR(VLOOKUP($C26,'MONTHLY DUES 2026'!$C$5:$E$25,3,0),0) -> 0 | L26: =IFERROR(VLOOKUP($C26,'VEHICLE SHARES HOLDING'!$C$17:$E$31,3,0),0) -> 0 | Q26: =IFERROR(VLOOKUP($C26,'B O G SHARES DEVIDENT '!$C$71:$D$87,2,0),0) -> 0 | R26: =IFERROR(VLOOKUP($C26,'B O G SHARES DEVIDENT '!$C$71:$C$88,3,0),0) -> 0
B27: =SUBTOTAL(3,B7:B26) -> 19 | C27: =SUBTOTAL(3,C7:C26) -> 19 | D27: =SUM(D7:D25) -> 66564.36 | E27: =SUM(E7:E26) -> 10502.699 | F27: =SUM(F7:F26) -> 77067.059 | G27: =SUM(G7:G26) -> 1316 | H27: =SUM(H7:H26) -> 180 | I27: =SUM(I7:I26) -> 306 | J27: =SUM(J7:J26) -> 432 | K27: =SUM(K7:K26) -> 318 | L27: =SUM(L7:L26) -> 80 | ... R27: =SUM(R7:R26) -> 0
N29: =SUM(N27:Q27) -> 10502.699

Sheet B O G SHARES DEVIDENT 
B4: Bog shares NO. 1
B5: FIRST YEAR - 364 DAYS
B6: 10/06/2025 - 09-06-2026
B7: NO. | C7: NAME | D7: TOTAL
B8: 1 | C8: FANUEL HAGAN | D8: ='TREASURER BILL NO 1'!G394 -> 497.68269
B9: 2 | C9: FREDERICK WORTEY TAWIAH | D9: =D8 -> 497.68269
B10: 3 | C10: JOHN OFOSUHENE ASARE | D10: =D9 -> 497.68269
B11: 4 | C11: JOHNSON WOOD | D11: =D10 -> 497.68269
B12: 5 | C12: JONATHAN DANSO SIAW | D12: =D11 -> 497.68269
B13: 6 | C13: JUSTICE KOJO ACHEAMPONG | D13: =D12 -> 497.68269
B14: 7 | C14: JUST-MARK KWABENA QUANSAH | D14: =D13 -> 497.68269
B15: 8 | C15: MAXWELL OFEI SIAW | D15: =D14 -> 497.68269
B16: 9 | C16: MOSES ODURO | D16: =D15 -> 497.68269
B17: 10 | C17: OSEI KWAME | D17: =D16 -> 497.68269
B18: 11 | C18: PRINCE ASANTE AHWIRENG | D18: =D17 -> 497.68269
B19: 12 | C19: VINCENT AGAMATEY | D19: =D18 -> 497.68269
B20: 13 | C20: WILLIAM KOJO ANANE | D20: =D19 -> 497.68269
B22: =SUBTOTAL(3,B8:B20) -> 13 | C22: TOTAL | D22: =SUM(D8:D21) -> 6469.875
B26: Bog shares No. 2
B27: 364 DAYS
B28: 17/02/2025 - 16-02-2026
B29: NO. | C29: NAME | D29: TOTAL
B30: 1 | C30: FANUEL HAGAN | D30: ='TREASURER BILL NO 2'!G392 -> 274.50348
B31: 2 | C31: FREDERICK WORTEY TAWIAH | D31: =D30 -> 274.50348
B32: 3 | C32: JOHNSON WOOD | D32: =D31 -> 274.50348
B33: 4 | C33: JONATHAN DANSO SIAW | D33: =D32 -> 274.50348
B34: 5 | C34: JUSTICE KOJO ACHEAMPONG | D34: =D33 -> 274.50348
B35: 6 | C35: JUST-MARK KWABENA QUANSAH | D35: =D34 -> 274.50348
B36: 7 | C36: MAXWELL OFEI SIAW | D36: =D35 -> 274.50348
B37: 8 | C37: MOSES ODURO | D37: =D36 -> 274.50348
B38: 9 | C38: OSEI KWAME | D38: =D37 -> 274.50348
B39: 10 | C39: PRINCE ASANTE AHWIRENG | D39: =D38 -> 274.50348
B40: 11 | C40: VINCENT AGAMATEY | D40: =D39 -> 274.50348
B41: 12 | C41: WILLIAM KOJO ANANE | D41: =D40 -> 274.50348
B43: =SUBTOTAL(3,B30:B41) -> 12 | C43: TOTAL | D43: =SUM(D30:D42) -> 3294.0418
B46: Bog shares NO. 3
B47: 182 DAYS
B48: 06/08/2025 - 04-02-2026
B49: NO. | C49: NAME | D49: TOTAL
B50: 1 | C50: DANSO KINGSLEY | D50: ='TREASURER BILL NO 3'!G212 -> 54.022992
B51: 2 | C51: FANUEL HAGAN | D51: =D50 -> 54.022992
B52: 3 | C52: FREDERICK WORTEY TAWIAH | D52: =D51 -> 54.022992
B53: 4 | C53: ISAAC DONKOR | D53: =D52 -> 54.022992
B54: 5 | C54: JOHNSON WOOD | D54: =D53 -> 54.022992
B55: 6 | C55: JONATHAN DANSO SIAW | D55: =D54 -> 54.022992
B56: 7 | C56: JUST-MARK KWABENA QUANSAH | D56: =D55 -> 54.022992
B57: 8 | C57: MAXWELL OFEI SIAW | D57: =D56 -> 54.022992
B58: 9 | C58: MOSES ODURO | D58: =D57 -> 54.022992
B59: 10 | C59: OSEI KWAME | D59: =D58 -> 54.022992
B60: 11 | C60: PRINCE ASANTE AHWIRENG | D60: =D59 -> 54.022992
B61: 12 | C61: VINCENT AGAMATEY | D61: =D60 -> 54.022992
B62: 13 | C62: WILLIAM KOJO ANANE | D62: =D61 -> 54.022992
B64: =SUBTOTAL(3,B50:B62) -> 13 | C64: TOTAL | D64: =SUM(D50:D63) -> 702.2989
B67: Bog shares NO. 4
B68: 364 DAYS
B69: 20/1/2026 - 18/01/2027
B70: NO. | D70: TOTAL
B71: 1 | C71: ALEX ACKAH | D71: ='TREASURER BILL NO 4'!G12 -> 2.1460892
B72: 2 | C72: DANSO KINGSLEY | D72: =D71 -> 2.1460892
B73: 3 | C73: FANUEL HAGAN | D73: =D72 -> 2.1460892
B74: 4 | C74: FREDERICK WORTEY TAWIAH | D74: =D73 -> 2.1460892
B75: 5 | C75: ISAAC DARKO | D75: =D74 -> 2.1460892
B76: 6 | C76: ISAAC DONKOR | D76: =D75 -> 2.1460892
B77: 7 | C77: JOHN OFOSUHENE ASARE | D77: =D76 -> 2.1460892
B78: 8 | C78: JOHNSON WOOD | D78: =D77 -> 2.1460892
B79: 9 | C79: JONAS WEREKO | D79: =D78 -> 2.1460892
B80: 10 | C80: JONATHAN DANSO SIAW | D80: =D79 -> 2.1460892
B81: 11 | C81: JUST-MARK KWABENA QUANSAH | D81: =D80 -> 2.1460892
B82: 12 | C82: MAXWELL OFEI SIAW | D82: =D81 -> 2.1460892
B83: 13 | C83: MOSES ODURO | D83: =D82 -> 2.1460892
... B87: 17 | C87: WILLIAM KOJO ANANE | D87: =D86 -> 2.1460892
B89: =SUBTOTAL(3,B71:B87) -> 17 | C89: TOTAL | D89: =SUM(D71:D88) -> 36.483516

Sheet CHECK YOUR SHARES HOLDING
B4: CHECK YOUR SHARES HOLDING | D4: DUES | E4: T/BILL | F4: TREASURER BILL
B5: NAME | C5: TOTAL AMOUNT | D5: =VLOOKUP($B6,'MEMBERS SHARES HOLDING'!$C$7:$N$26,4,0) -> 3863.2045 | E5: SUB TOTAL | F5: NO. 1 T/BILL | G5: NO. 2 T/BILL | H5: NO. 3 T/BILL | I5: NO. 4 T/BILL
B6: JUST-MARK KWABENA QUANSAH | C6: =E6+D6 -> 3863.2045 | D6: =IFERROR(VLOOKUP($B6,'SHARES HOLDINGS'!$C$5:$E$24,2,0),0) -> 3034.8492 | E6: =SUM(F6:I6) -> 828.35526 | F6: =IFERROR(VLOOKUP($B6,'TREASURE BILL FOR MEMBERS'!$C$6:$H$24,3,0),0) -> 497.68269 | G6: =IFERROR(VLOOKUP($B6,'TREASURE BILL FOR MEMBERS'!$C$6:$H$24,4,0),0) -> 274.50348 | H6: =IFERROR(VLOOKUP($B6,'TREASURE BILL FOR MEMBERS'!$C$6:$H$24,5,0),0) -> 54.022992 | I6: =IFERROR(VLOOKUP($B6,'TREASURE BILL FOR MEMBERS'!$C$6:$H$24,6,0),0) -> 2.1460892

Sheet TREASURER BILL NO 1
C4: JUST-MARK KWABENA QUANSAH
C5: bog treasurer bill - NO 1 FIRST YEAR
C7: PRINCIPAL AMOUNT | D7: RATE PER ANNUAL | E7: TOTAL INTREST RATE | F7: TOTAL (PRI) | G7: 45817
C8: 15000 | D8: 0.274 | E8: =C8*D8 -> 4110 | F8: =C8+E8 -> 19110 | G8: =VLOOKUP($G7,$C$16:$H$379,3,0) -> MONDAY | I8: =B8/#REF! -> #REF!
C9: DURATION | D9: FROM | E9: TO | F9: ONE YEAR TREASURER BILL (DAYS) | G9: DAYS MATURED | H9: DAYS REMAINED
C10: FIRST YEAR | D10: =C16 -> 45454 | E10: =C379 -> 45817 | F10: 364 | G10: =VLOOKUP($G7,$C$16:$H$379,2,0) -> 364 | H10: =F10-G10 -> 0
C11: TOTAL MMBERS QUALIFIED | D11: DAYLY INTREST AS AT DATE | E11: DAYLY INTREST AS AT DATE FOR MEMBERS | F11: TOTAL AMOUNT | G11: TOTAL INTREST FOR A MEMBER | H11: TOTAL INTREST
C12: ='B O G SHARES DEVIDENT '!B22 -> 13 | D12: =VLOOKUP($G7,$C$16:$H$379,4,0) -> 4110 | E12: =D12/$C$12 -> 316.15385 | F12: =D12+C8 -> 19110 | G12: =E12 -> 316.15385 | H12: =D12 -> 4110 | L12: `
C14: DATE | D14: DAY | E14: WEEKS | F14: DAYLY INTREST | G14: DAYLY INTREST FOR MEMBERS | H14: TOTAL
C16: 45454 | D16: 1 | E16: TUESDAY | F16: =$E$8/$F$10*D16 -> 11.291209 | G16: =F16/$C$12 -> 0.86855452 | H16: =$C$8+F16 -> 15011.291
